Workbook

Sheet README
B1: Vyomaa Energy — P3 & P4 Capital Raise Model
B2: Read me first
B4: Purpose: size senior debt first at SPV3 (P3, 25 MW) and SPV4 (P4, 50 MW), then fund the residual from one HoldCo, and show how HoldCo money reaches each SPV and comes back to investors.
B6: Structure: Investors (promoter, institutional partner) → HoldCo → SPV3 and SPV4 (100% owned). Lenders lend to each SPV.
B7: HoldCo → SPV: equity shares plus CCDs (85% CCD by default; NCD selectable). SPV → HoldCo, in order: CCD / NCD coupon, NCD principal (debt ranks ahead of dividends), dividends capped at distributable profit, capital reduction after senior debt, final-year capital return.
B8: HoldCo funding order: promoter cash → optional HNI pre-COD CCDs → equity bridge → institutional round priced at P3 COD (15% CCPS + 85% partner CCD that mirrors the SPV CCDs).
B10: Basis: unit economics (cost per kWp, yield, tariff, opex, debt terms) are taken from the Arclight lender pack V23 (P3.1: 75 rooftop sites, 9.47 MWp) and scaled to 25 MW and 50 MW.
B11: Replace them with P3 and P4 EPC quotes, yield reports and lender term sheets as they arrive. Yellow cells are the assumptions to confirm first.
B13: Sheets: README · Dashboard · Inputs · P3 Lender View · Funding Plan · Funding Timeline · Sources & Uses · Construction Draws · SPV3 · SPV4 · HoldCo · Checks.
B14: Colour code: blue = input, black = formula, green = link to another sheet, yellow fill = key assumption.
B16: What the switches on Inputs do:
B17: · Financing case (1 base, 2 recommended, 3 worst, 0 custom) sets each SPV's rate and gearing. Draw order per SPV sets construction interest and bridge cost.
... B25: Not legal or tax advice. Instrument choice, lender consent to shareholder-debt servicing, Companies Act limits and RBI rules on financing promoter contribution need counsel's sign-off.

Sheet Dashboard
B1: Vyomaa Energy — P3 (25 MW) & P4 (50 MW) Capital Raise: Dashboard
B2: Debt first at each SPV, HoldCo equity for the residual. All figures live from the model unless marked captured.
B4: Key outputs | C4: SPV3 (P3) | D4: SPV4 (P4) | E4: Portfolio
B5: Capacity (MWp) | C5: ='Sources & Uses'!C6 -> 25 | D5: ='Sources & Uses'!D6 -> 50 | E5: ='Sources & Uses'!E6 -> 75
B6: Construction capex (₹ Cr) | C6: ='Sources & Uses'!C11 -> 80.13265 | D6: ='Sources & Uses'!D11 -> 160.2653 | E6: ='Sources & Uses'!E11 -> 240.39795
B7: Total uses (₹ Cr) | C7: ='Sources & Uses'!C27 -> 81.824918 | D7: ='Sources & Uses'!D27 -> 163.41973 | E7: ='Sources & Uses'!E27 -> 245.24465
B8: Senior debt, sized first (₹ Cr) | C8: ='Sources & Uses'!C19 -> 53.524953 | D8: ='Sources & Uses'!D19 -> 107.04991 | E8: ='Sources & Uses'!E19 -> 160.57486
B9: Gearing | C9: ='Sources & Uses'!C34 -> 0.65414001 | D9: ='Sources & Uses'!D34 -> 0.65506109 | E9: ='Sources & Uses'!E34 -> 0.65475378
B10: Binding constraint | C10: ='Sources & Uses'!C20 -> DSCR, P90 case | D10: ='Sources & Uses'!D20 -> DSCR, P90 case
B11: Construction draw order | C11: ='Sources & Uses'!C25 -> Debt first | D11: ='Sources & Uses'!D25 -> Equity first
B12: Contingent equity vs 70% plan (₹ Cr) | C12: ='Sources & Uses'!C21 -> 3.8374179 | D12: ='Sources & Uses'!D21 -> 7.4985759 | E12: ='Sources & Uses'!E21 -> 11.335994
B13: HoldCo injection into SPV (₹ Cr) | C13: ='Sources & Uses'!C30 -> 28.299966 | D13: ='Sources & Uses'!D30 -> 56.369822 | E13: ='Sources & Uses'!E30 -> 84.669788
B14: as equity shares | C14: ='Sources & Uses'!C31 -> 4.2449948 | D14: ='Sources & Uses'!D31 -> 8.4554734 | E14: ='Sources & Uses'!E31 -> 12.700468
B15: as CCD / NCD | C15: ='Sources & Uses'!C32 -> 24.054971 | D15: ='Sources & Uses'!D32 -> 47.914349 | E15: ='Sources & Uses'!E32 -> 71.96932
B16: Pre-close cash: PMC + PBG margin (₹ Cr) | C16: ='Sources & Uses'!C41 -> 5.39125 | D16: ='Sources & Uses'!D41 -> 10.7825 | E16: ='Sources & Uses'!E41 -> 16.17375
B17: Minimum DSCR, P50 | C17: =SPV3!D31 -> 1.4064783 | D17: =SPV4!D31 -> 1.4064783
B18: Minimum DSCR, P90 | C18: =SPV3!D32 -> 1.3 | D18: =SPV4!D32 -> 1.3
B19: Project IRR, pre-tax | C19: =SPV3!D92 -> 0.15930435 | D19: =SPV4!D92 -> 0.15441507
B20: SPV equity IRR, lender-pack basis | C20: =SPV3!D91 -> 0.14564579 | D20: =SPV4!D91 -> 0.14292302
B21: SPV equity IRR to HoldCo, with instrument limits | C21: =SPV3!D90 -> 0.14114412 | D21: =SPV4!D90 -> 0.13994361
B22: Peak cash trapped in the SPV (₹ Cr) | C22: =SPV3!D95 -> 8.5057283 | D22: =SPV4!D95 -> 13.825459
B24: HoldCo capital raise | E24: Portfolio
B25: Total HoldCo funding need incl. pre-close (₹ Cr) | E25: =HoldCo!D25 -> 98.128686
B26: Promoter cash used (₹ Cr) | E26: =HoldCo!D29 -> 10
B27: Peak equity bridge (₹ Cr) | E27: =HoldCo!D38 -> 36.871689
B28: Bridge interest (₹ Cr) | E28: =HoldCo!D36 -> 1.9979733
B29: Institutional raise at COD (₹ Cr) | E29: =HoldCo!D39 -> 90.126659
B30: as CCPS (₹ Cr) | E30: =HoldCo!D40 -> 13.518999
B31: as partner CCD / NCD (₹ Cr) | E31: =HoldCo!D41 -> 76.607661
B32: Partner share of HoldCo equity | E32: =HoldCo!D107 -> 0.87844039
B33: Promoter share of HoldCo equity | E33: =HoldCo!D108 -> 0.12155961
B34: Promoter share if priced at cost | E34: =HoldCo!D109 -> 0.080529964
B35: Partner IRR / hurdle 15% | E35: =HoldCo!D110 -> 0.14537767
B36: Partner MOIC | E36: =HoldCo!D111 -> 5.0640892
B37: Promoter IRR | E37: =HoldCo!D113 -> 0.094467413
B38: Promoter MOIC | E38: =HoldCo!D114 -> 4.9779834
B39: Peak cash held at HoldCo (₹ Cr) | E39: =HoldCo!D75 -> 0
B40: HoldCo tax, life of project (₹ Cr) | E40: =HoldCo!D59 -> 0.23230653
B41: Peak SPV tax losses carried forward (₹ Cr) | E41: =MAX(SPV3!E45:AD45)+MAX(SPV4!E45:AD45) -> 176.07793
B42: Cash held in the DSRAs at peak; freed by an LC (₹ Cr) | E42: =MAX(SPV3!E56:AD56)+MAX(SPV4!E56:AD56) -> 13.521176
B43: SPV CCDs converted, incl. rolled-up coupon (₹ Cr) | E43: =SPV3!D73+SPV4!D73 -> 81.797332
B44: Partner CCD converted (₹ Cr) | E44: =HoldCo!D66 -> 100.65838
B45: Partner stake sale: price (₹ Cr) | E45: =HoldCo!D116 -> 129.77748
B46: Partner stake sale: net proceeds (₹ Cr) | E46: =HoldCo!D120 -> 118.55998
B47: Partner IRR with stake sale | E47: =HoldCo!D121 -> 0.14808975
B48: Partner MOIC with stake sale | E48: =HoldCo!D122 -> 1.8274047
B49: Financing case in use | E49: =CHOOSE(Inputs!$C$103+1,"Custom inputs","1 · Base","2 · Recommended","3 · Worst realistic") -> 1 · Base
B50: Performance guarantee | E50: =IF(Inputs!$C$106=2,"Insurance surety bond","Bank guarantee with cash margin") -> Bank guarantee with cash margin
B51: Partner residence (s.94B) | E51: =IF(Inputs!$C$104=1,"Non-resident: s.94B cap applies","Resident") -> Resident
B52: HNI pre-COD CCD subscribed (₹ Cr) | E52: =HoldCo!D32 -> 0
B53: HNI share sold to the partner at COD | E53: =Inputs!$C$98 -> 0
B54: HNI tranche price at the COD round, 100% (₹ Cr) | E54: =HoldCo!D132 -> 0
B55: HNI return selling at the round, annualised (pre / post tax) | E55: =IF(HoldCo!D32=0,"-",TEXT(HoldCo!D133,"0.0%")&" / "&TEXT(HoldCo!D134,"0.0%")) -> -
B56: HNI IRR after personal tax | E56: =HoldCo!D135 -> 0
B57: Partner's HNI buy-out at the round (₹ Cr) | E57: =HoldCo!D136 -> 0
B58: HNI share of HoldCo equity | E58: =HoldCo!D124 -> 0
B59: HNI IRR, hold to term | E59: =HoldCo!D126 -> 0
B60: HNI IRR with sale | E60: =HoldCo!D129 -> 0
B61: HNI sale: net proceeds (₹ Cr) | E61: =HoldCo!D128 -> 0
B62: All model checks pass | E62: =Checks!C28 -> TRUE
B64: How HoldCo money moves (₹ Cr, life of project) | C64: SPV3 (P3) | D64: SPV4 (P4) | E64: Portfolio
B65: Down: equity shares subscribed | C65: =SPV3!D61 -> 8.2299948 | D65: =SPV4!D61 -> 16.425473 | E65: =C65+D65 -> 24.655468
B66: Down: CCD / NCD subscribed | C66: =SPV3!D63 -> 24.054971 | D66: =SPV4!D63 -> 47.914349 | E66: =C66+D66 -> 71.96932
B67: Up 1: CCD / NCD coupon | C67: =SPV3!D65 -> 30.525949 | D67: =SPV4!D65 -> 61.864869 | E67: =C67+D67 -> 92.390818
B68: Up 2: dividends | C68: =SPV3!D69 -> 104.469 | D68: =SPV4!D69 -> 207.20507 | E68: =C68+D68 -> 311.67407
B69: Up 3: NCD principal (nil for CCD) | C69: =SPV3!D72 -> 0 | D69: =SPV4!D72 -> 0 | E69: =C69+D69 -> 0
B70: Up 4: capital reduction | C70: =SPV3!D77 -> 34.51244 | D70: =SPV4!D77 -> 71.940361 | E70: =C70+D70 -> 106.4528
B71: Up 5: final-year capital return | C71: =SPV3!D80 -> 0 | D71: =SPV4!D80 -> 0 | E71: =C71+D71 -> 0
B72: Total paid up to HoldCo | C72: =SPV3!D83 -> 169.50738 | D72: =SPV4!D83 -> 341.0103 | E72: =C72+D72 -> 510.51768
B74: Scenarios (captured values, not live) | C74: Senior debt | D74: Min P90 DSCR | E74: Institutional raise | F74: Partner share | G74: Partner IRR | H74: Promoter IRR | I74: SPV3 equity IRR | J74: Peak SPV3 trapped cash | K74: Promoter share | L74: All-investor IRR | M74: HoldCo tax (₹ Cr) | N74: Peak bridge (₹ Cr) | O74: All checks pass
B75: Base: P3 debt first, P4 equity first; SPV CCD 85% at 12% to debt maturity; partner CCD 85% to FY39 | C75: 160.57486 | D75: 1.3 | E75: 90.126659 | F75: 0.87844039 | G75: 0.14537767 | H75: 0.094467413 | I75: 0.14114412 | J75: 8.5057283 | K75: 0.12155961 | L75: 0.13777698 | M75: 0.23230653 | N75: 36.871689 | O75: Yes
B76: Previous partner terms: 30% CCD converting FY34 | C76: 160.57486 | D76: 1.3 | E76: 90.126659 | F76: 0.85527321 | G76: 0.12719576 | H76: 0.13398985 | I76: 0.14114412 | J76: 8.5057283 | K76: 0.14472679 | L76: 0.12821226 | M76: 19.682568 | N76: 36.871689 | O76: Yes
B77: P3 equity first | C77: 160.57486 | D77: 1.3 | E77: 90.424286 | F77: 0.87912101 | G77: 0.14504874 | H77: 0.094069435 | I77: 0.14266667 | J77: 8.4457194 | K77: 0.12087899 | L77: 0.13747052 | M77: 0.33209813 | N77: 37.069524 | O77: Yes
B78: P3 pro-rata | C78: 160.57486 | D78: 1.3 | E78: 90.256201 | F78: 0.87873549 | G78: 0.14523497 | H78: 0.094294873 | I78: 0.14179408 | J78: 8.4782523 | K78: 0.12126451 | L78: 0.13764405 | M78: 0.27537803 | N78: 36.958159 | O78: Yes
B79: P4 pro-rata | C79: 160.57486 | D79: 1.3 | E79: 90.944229 | F79: 0.88070069 | G79: 0.14437243 | H79: 0.093203861 | I79: 0.14114412 | J79: 8.5057283 | K79: 0.11929931 | L79: 0.13683649 | M79: 0.23230653 | N79: 36.871689 | O79: Yes
B80: P4 debt first | C80: 160.57486 | D80: 1.3 | E80: 91.644035 | F80: 0.88259766 | G80: 0.14351153 | H80: 0.092129233 | I80: 0.14114412 | J80: 8.5057283 | K80: 0.11740234 | L80: 0.13603162 | M80: 0.23230653 | N80: 36.871689 | O80: Yes
B81: SPV CCD 65% of injection | C81: 160.57486 | D81: 1.3 | E81: 90.048312 | F81: 0.89857102 | G81: 0.13830517 | H81: 0.084345494 | I81: 0.13444261 | J81: 10.101382 | K81: 0.10142898 | L81: 0.13104377 | M81: 0.15395864 | N81: 36.871689 | O81: Yes
B82: SPV CCD as in the draft term sheet: 35%, 10%, converts year 2 | C82: 160.57486 | D82: 1.3 | E82: 91.21295 | F82: 0.90756481 | G82: 0.12667294 | H82: 0.07330624 | I82: 0.12267715 | J82: 14.146487 | K82: 0.092435185 | L82: 0.12022631 | M82: 0.013585338 | N82: 36.871689 | O82: Yes
B83: SPV CCD converts in year 2 (only change) | C83: 160.57486 | D83: 1.3 | E83: 90.726659 | F83: 0.91010377 | G83: 0.12838554 | H83: 0.074141277 | I83: 0.12569569 | J83: 15.109912 | K83: 0.089896227 | L83: 0.12177673 | M83: 0.23230653 | N83: 36.871689 | O83: Yes
B84: NCD instead of CCD at both levels (85%), repayable from year 1 | C84: 160.57486 | D84: 1.3 | E84: 90.126659 | F84: 0.46110029 | G84: 0.13804536 | H84: 0.1511418 | I84: 0.14555897 | J84: 0 | K84: 0.53889971 | L84: 0.14144576 | M84: 0.23230653 | N84: 36.871689 | O84: Yes
B85: NCD at both levels (85%), principal locked until senior debt is repaid | C85: 160.57486 | D85: 1.3 | E85: 90.126659 | F85: 0.46110029 | G85: 0.13585354 | H85: 0.14696537 | I85: 0.14188604 | J85: 8.5057283 | K85: 0.53889971 | L85: 0.13862526 | M85: 0.23230653 | N85: 36.871689 | O85: Yes
B86: Equity shares only: no CCD/NCD, no capital reduction | C86: 160.57486 | D86: 1.3 | E86: 92.435261 | F86: 0.85402169 | G86: 0.095869057 | H86: 0.11818839 | I86: 0.10417934 | J86: 32.284966 | K86: 0.14597831 | L86: 0.098902019 | M86: 0 | N86: 36.871689 | O86: Yes
... B110: Non-resident partner: s.94B caps HoldCo's coupon deduction | C110: 160.57486 | D110: 1.3 | E110: 90.126659 | F110: 0.89694808 | G110: 0.13572815 | H110: 0.082492793 | I110: 0.14114412 | J110: 8.5057283 | K110: 0.10305192 | L110: 0.12846803 | M110: 17.620139 | N110: 36.871689 | O110: Yes
B111: Captured 16 Oct 2026 on model v8 by changing the named inputs and recalculating this workbook. Re-run after changing inputs. NCD rows use the same 85% share as the CCD base, so the comparison is like-for-like.
B113: HNI cases (captured values) | C113: HNI IRR, as held/sold | D113: HNI IRR, FY33 sale | E113: Sell at COD, annualised | F113: Sell at COD, after tax | G113: HNI IRR after tax | H113: Partner buy-out (₹ Cr) | I113: Promoter IRR | J113: 10-year rule met
B114: ₹35 Cr HNI, all hold (converts FY37) | C114: 0.14369891 | D114: 0.13392227 | E114: 0.78747969 | F114: 0.45103961 | G114: 0.11091403 | H114: 0 | I114: 0.085285792 | J114: Yes
B115: Half sell at the COD round | C115: 0.15893345 | D115: 0.18593444 | E115: 0.78747969 | F115: 0.45103961 | G115: 0.11699909 | H115: 22.8375 | I115: 0.085285792 | J115: Yes
B116: All sell at the COD round | C116: 0.305 | D116: 0.305 | E116: 0.78747969 | F116: 0.45103961 | G116: 0.18605 | H116: 45.675 | I116: 0.085285792 | J116: Yes
B117: Converting FY39 instead | C117: 0.14940663 | D117: 0.14263827 | E117: 0.78747969 | F117: 0.45103961 | G117: 0.115115 | H117: 0 | I117: 0.081306906 | J117: No
B118: All on the recommended financing case (P3 NBFC at 11.5%, 60%; P4 bank at 10.5%). HNI money is committed at close and called with the P3 equity draw (about 5.5 months before the round), so selling at COD is annualised over that period; escrowed money (Inputs row 100) uses 10 months.
B120: Calibration to the Arclight lender pack (P3.1) | C120: Lender pack | D120: This model
B121: Senior debt facility (₹ Cr) | C121: 21.66 | D121: 21.682591
B122: Total uses (₹ Cr) | C122: 30.94 | D122: 30.97513
B123: Equity IRR, all free cash paid | C123: 0.155 | D123: 0.15648434
B124: Equity IRR, dividends only | C124: 0.131 | D124: 0.12604676
B125: Peak cash held back in the debt period (₹ Cr) | C125: 3.72 | D125: 3.8630404
B126: Captured on v8: P3 inputs set to 9.47 MWp, P50 sizing, pro-rata draws, no CCD, PMC outside the SPV (the pack’s scope); "dividends only" with no capital reduction; peak over years 1–10. Dividends-only IRR is 0.3 pt lower than in v7 because inverter replacement is now expensed in book profit. Pack figures from its KPI, Sources & Uses and the Arclight deck (slide 14).

Sheet Inputs
B1: Vyomaa Energy — P3 & P4 Capital Raise Model: Inputs
B2: ₹ Cr unless stated (₹1 Cr = ₹10 million). FY = year ending 31 March, labelled by end year (FY2028 = Apr-2027 to Mar-2028).
B3: Legend: blue = input · black = formula · green = link to another sheet · yellow fill = key assumption to confirm before term sheet.
B5: SPV project inputs | C5: SPV3 (P3) | D5: SPV4 (P4) | E5: Unit | F5: Source / note
B6: Capacity | C6: 25 | D6: 50 | E6: MWp | F6: User, 16 Oct 2026
B7: Financial close & construction FY | C7: 2028 | D7: 2029 | E7: FY | F7: Assumption: P3 follows the P3.1 timetable (build Jul–Oct 2027); P4 one year later
B8: Construction start month within the FY (1 = April) | C8: 4 | D8: 4 | E8: month | F8: P3.1: build starts July 2027. P4 assumed July 2028
B9: Months of operation in the construction FY | C9: =MAX(0,12-(C8-1)-C35) -> 5 | D9: =MAX(0,12-(D8-1)-D35) -> 3 | E9: months | F9: Formula: 12 − months before start − construction months
B10: Hard capex (EPC scope) | C10: 27251 | D10: 27251 | E10: ₹/kWp | F10: Arclight lender pack V23, P3.1 (75 rooftop sites, 9.47 MWp): ₹27.25/Wp. Replace with P3/P4 EPC quotes
B11: Developer fee | C11: 0.03 | D11: 0.03 | E11: % of hard capex | F11: Arclight lender pack V23, P3.1 (75 rooftop sites, 9.47 MWp)
B12: Pre-operative cost | C12: 31.67 | D12: 31.67 | E12: ₹ lakh/MWp | F12: Arclight lender pack V23, P3.1 (75 rooftop sites, 9.47 MWp): ₹3.00 Cr ÷ 9.47 MWp (₹4 lakh per site)
B13: Contingency | C13: 0.03 | D13: 0.03 | E13: % of hard capex | F13: Arclight lender pack V23, P3.1 (75 rooftop sites, 9.47 MWp)
B14: Specific yield, year 1, P50 | C14: 1492 | D14: 1492 | E14: kWh/kWp | F14: Arclight lender pack V23, P3.1 (75 rooftop sites, 9.47 MWp): 14,132.6 MWh ÷ 9,471.9 kWp
B15: Annual degradation | C15: 0.004 | D15: 0.004 | E15: % a year | F15: Arclight lender pack V23, P3.1 (75 rooftop sites, 9.47 MWp): generation FY29 → FY30
B16: PPA tariff (flat) | C16: 4.04 | D16: 4.04 | E16: ₹/kWh | F16: Arclight lender pack V23, P3.1 (75 rooftop sites, 9.47 MWp): weighted LOA tariff ₹4.04
B17: PPA term | C17: 25 | D17: 25 | E17: years | F17: Arclight lender pack V23, P3.1 (75 rooftop sites, 9.47 MWp)
B18: All-in opex, year 1 | C18: 932 | D18: 932 | E18: ₹/kWp/yr | F18: Arclight lender pack V23, P3.1 (75 rooftop sites, 9.47 MWp): ₹931.5 (benchmark ₹650–900)
B19: Opex escalation | C19: 0 | D19: 0 | E19: % a year | F19: P3.1 holds opex flat; test 2–4% (Dashboard scenarios)
B20: Inverter replacement | C20: 2354 | D20: 2354 | E20: ₹/kWp | F20: Arclight lender pack V23, P3.1 (75 rooftop sites, 9.47 MWp): ₹2.23 Cr in Oct 2039
B21: Inverter replacement, operating year | C21: 12 | D21: 12 | E21: year | F21: Arclight lender pack V23, P3.1 (75 rooftop sites, 9.47 MWp)
... B25: Corporate tax rate | C25: 0.25168 | D25: 0.25168 | E25: % | F25: Section 115BAA
B27: Senior debt (lent to each SPV) | C27: SPV3 (P3) | D27: SPV4 (P4) | E27: Unit | F27: Source / note
B28: Maximum gearing, custom (used when financing case = 0) | C28: 0.7 | D28: 0.7 | E28: % | F28: Arclight lender pack V23, P3.1 (75 rooftop sites, 9.47 MWp)
B29: Target DSCR for sculpting | C29: 1.3 | D29: 1.3 | E29: x | F29: Arclight lender pack V23, P3.1 (75 rooftop sites, 9.47 MWp)
B30: All-in interest rate, custom (used when financing case = 0) | C30: 0.105 | D30: 0.105 | E30: % a year | F30: Arclight lender pack V23, P3.1 (75 rooftop sites, 9.47 MWp): 6.0% base + 4.5% margin
B31: Repayment tenor after COD | C31: 10 | D31: 10 | E31: years | F31: Arclight lender pack V23, P3.1 (75 rooftop sites, 9.47 MWp)
B32: Arrangement fee | C32: 0.0125 | D32: 0.0125 | E32: % of facility | F32: Arclight lender pack V23, P3.1 (75 rooftop sites, 9.47 MWp)
B33: Commitment fee | C33: 0.01 | D33: 0.01 | E33: % a year on undrawn | F33: Arclight lender pack V23, P3.1 (75 rooftop sites, 9.47 MWp)
B34: Commitment fee period, average | C34: 5.9 | D34: 5.9 | E34: months | F34: Calibrated: P3.1 commitment fee = 0.49% of facility
B35: Construction period | C35: 4 | D35: 6 | E35: months | F35: P3.1: 4-month build. P4 (50 MW) assumed 6 months
B36: Construction draw order: 0 = lowest cost, 1 = equity first, 2 = pro-rata, 3 = debt first | C36: 3 | D36: 0 | E36: switch | F36: P3: debt first (equity is bridge-funded). P4: lowest cost of the three (round cash already raised)
B37: Cost of HoldCo cash drawn into construction | C37: =IF(AND(C92>0,C100=1),C102,C76) -> 0.125 | D37: =C102 -> 0.065 | E37: % a year | F37: P3: equity bridge rate (linked). P4: deposit yield forgone on round cash
B38: Debt sizing case: 1 = P50 base, 2 = P90 lender case | C38: 2 | D38: 2 | E38: switch | F38: Recommendation: size on the lender (P90) case
B39: P90 yield haircut vs P50 | C39: 0.064 | D39: 0.064 | E39: % | F39: 1.282 × σ 5% (P3.1 Monte Carlo yield σ)
B40: DSRA: months of forward debt service | C40: 6 | D40: 6 | E40: months | F40: Arclight lender pack V23, P3.1 (75 rooftop sites, 9.47 MWp)
B41: DSRA form: 1 = cash, 2 = bank LC | C41: 1 | D41: 1 | E41: switch | F41: LC needs lender consent; Dashboard scenario
B42: LC fee | C42: 0.015 | D42: 0.015 | E42: % a year | F42: Assumption (deck: 1–2%)
B44: Financing cases (pick one with the selector in the HoldCo section) | C44: SPV3 (P3) | D44: SPV4 (P4) | E44: Unit | F44: Source / note
B45: Case 1 · Base: all-in rate | C45: 0.105 | D45: 0.105 | E45: % a year | F45: Both SPVs at 10.5%, sized on P90 within a 70% cap
B46: Case 1 · Base: maximum gearing | C46: 0.7 | D46: 0.7 | E46: %
B47: Case 2 · Recommended: all-in rate | C47: 0.115 | D47: 0.105 | E47: % a year | F47: P3 from a green NBFC; P4 from a bank or IREDA a year later
B48: Case 2 · Recommended: maximum gearing | C48: 0.6 | D48: 0.7 | E48: % | F48: P3 capped at 60% (promoter-credit mitigation)
B49: Case 3 · Worst realistic: all-in rate | C49: 0.115 | D49: 0.115 | E49: % a year | F49: Both SPVs from NBFCs
B50: Case 3 · Worst realistic: maximum gearing | C50: 0.6 | D50: 0.6 | E50: %
B51: All-in interest rate used | C51: =IF($C$103=0,C30,CHOOSE($C$103,C45,C47,C49)) -> 0.105 | D51: =IF($C$103=0,D30,CHOOSE($C$103,D45,D47,D49)) -> 0.105 | E51: % a year | F51: Formula: the selected case, or the custom rate when the case is 0
B52: Maximum gearing used | C52: =IF($C$103=0,C28,CHOOSE($C$103,C46,C48,C50)) -> 0.7 | D52: =IF($C$103=0,D28,CHOOSE($C$103,D46,D48,D50)) -> 0.7 | E52: % | F52: Formula: the selected case, or the custom gearing when the case is 0
B54: HoldCo → SPV funding instruments | C54: SPV3 (P3) | D54: SPV4 (P4) | E54: Unit | F54: Source / note
B55: Share of HoldCo injection as CCD / NCD (rest equity shares) | C55: 0.85 | D55: 0.85 | E55: % | F55: Equity shares then ≈ 5% of project cost, CCD ≈ 29%; in line with the draft term sheet's 5–10% pure equity
B56: HoldCo → SPV instrument: 1 = CCD, 2 = NCD | C56: 1 | D56: 1 | E56: switch | F56: CCD: lenders count it as equity; coupon from surplus only; converts to shares. NCD: repayable subordinated debt
B57: CCD coupon (cumulative, paid from surplus cash only) | C57: 0.12 | D57: 0.12 | E57: % a year | F57: Draft term sheet had 10%; 12% lets the coupon carry more of the early cash
B58: CCD converts to equity shares at end of operating year | C58: 10 | D58: 10 | E58: year | F58: At senior-debt maturity. Draft term sheet had COD + 12 months / 36 months (≈ year 2), which traps cash
B59: NCD coupon (used only if NCD is chosen) | C59: 0.12 | D59: 0.12 | E59: % a year | F59: Assumption: arm's length, subordinated to senior debt
B60: CCD / NCD servicing allowed from operating year | C60: 1 | D60: 1 | E60: year | F60: Subject to lender restricted-payment conditions
B61: NCD principal repayment allowed from operating year | C61: 1 | D61: 1 | E61: year | F61: Many lenders require sponsor debt to stay in until senior debt is repaid (then 11)
B62: Capital reduction allowed from operating year | C62: 11 | D62: 11 | E62: year | F62: After senior debt is repaid; s.66 Companies Act 2013, NCLT and creditor approval
B64: Pre-close cash (funded by HoldCo, outside sources & uses) | C64: SPV3 (P3) | D64: SPV4 (P4) | E64: Unit | F64: Source / note
B65: PMC / owner's engineer | C65: 15.94 | D65: 15.94 | E65: ₹ lakh/MWp | F65: LOA register: ₹1.27 Cr incl. GST for 7.99 MWp
B66: PMC already inside pre-op allowance? 1 = yes, 0 = no | C66: 0 | D66: 0 | E66: switch | F66: Conservative: treat as extra (Arclight deck, slide 17)
B67: Performance bank guarantee | C67: 2250 | D67: 2250 | E67: ₹/kW | F67: LOA terms
B68: Cash margin required on the PBG | C68: 0.25 | D68: 0.25 | E68: % | F68: Assumption, bank-specific. SPVs hold no margin money today
B69: PBG margin released in operating year | C69: 1 | D69: 1 | E69: year | F69: Assumption
B71: HoldCo and investor terms (single value, column C)
B72: Promoter cash available at HoldCo | C72: 10 | E72: ₹ Cr | F72: HoldCo register: ₹10 Cr paid in (₹1 Cr already in Arclight Projects 3)
B73: Additional promoter cash commitment | C73: 0 | E73: ₹ Cr | F73: Assumption
B74: HoldCo running cost | C74: 0.2 | E74: ₹ Cr/yr | F74: Assumption
B75: First FY shown in the HoldCo timeline | C75: 2027 | E75: FY | F75: Pre-close year for P3
B76: Equity bridge interest rate | C76: 0.125 | E76: % a year | F76: NBFC or sponsor bridge. A partner commitment letter at P3 close could cut this (scenario: 11%)
B77: Institutional round FY (priced at P3 COD) | C77: 2029 | E77: FY | F77: Bridge is repaid at the start of this FY
B78: Promoter value step-up at COD pricing | C78: 1.58 | E78: x | F78: Arclight deck slide 11: equity value ÷ invested at COD
B79: Partner funding via HoldCo CCD / NCD (rest CCPS) | C79: 0.85 | E79: % | F79: Mirrors the SPV CCDs: HoldCo's coupon paid ≈ coupon received, so HoldCo pays little tax while the SPVs carry losses
B80: Partner tranche instrument: 1 = CCD, 2 = NCD | C80: 1 | E80: switch | F80: CCD/CCPS are FDI-eligible. Foreign partner: s.94B caps HoldCo's deduction and withholding tax applies to the coupon
B81: Partner CCD / NCD coupon | C81: 0.12 | E81: % a year | F81: Assumption
B82: Partner CCD converts to HoldCo equity in FY | C82: 2039 | E82: FY | F82: Same year the SPV4 CCDs convert (SPV3: FY38)
B83: Partner preferred return (hurdle) | C83: 0.15 | E83: % a year | F83: Arclight deck: 15% hurdle
... B111: Partner tax on gains from CCDs sold before conversion (s.50AA) | C111: 0.25168 | E111: % | F111: Gains on unlisted debentures are deemed short-term; domestic-company rate. The CCPS part keeps the long-term rate above. Confirm with tax adviser
B112: HNI coupon months before the round (formula) | C112: =IF(C100=1,C99,'Construction Draws'!$C$38*12) -> 5.5 | E112: months | F112: Escrow: from P3 close (row 99). Called when drawn: from the P3 equity draw

Sheet P3 Lender View
B1: P3 Lender View — the numbers behind the debt deck and teaser
B2: Live from SPV3 and Sources & Uses. Stress cases hold the loan and repayment schedule fixed. Edit the blue stress parameters to test others.
B4: Facility
B5: Senior facility (₹ Cr) | C5: ='Sources & Uses'!$C$19 -> 53.524953
B6: Total project cost (₹ Cr) | C6: ='Sources & Uses'!$C$27 -> 81.824918
B7: Gearing | C7: ='Sources & Uses'!$C$34 -> 0.65414001
B8: All-in rate used | C8: =Inputs!$C$51 -> 0.105
B9: Tenor after COD (years) | C9: =Inputs!$C$31 -> 10
B10: Target DSCR for sculpting | C10: =Inputs!$C$29 -> 1.3
B11: Sizing case | C11: =IF(Inputs!$C$38=2,"P90 lender case","P50 base case") -> P90 lender case
B12: Binding constraint | C12: ='Sources & Uses'!$C$20 -> DSCR, P90 case
B13: Construction draw order | C13: ='Sources & Uses'!$C$25 -> Debt first
B14: HoldCo equity into P3 (₹ Cr) | C14: ='Sources & Uses'!$C$30 -> 28.299966
B16: Cover ratios
B17: Minimum DSCR, P50 | C17: =SPV3!D31 -> 1.4064783
B18: Minimum DSCR, P90 | C18: =SPV3!D32 -> 1.3
B19: Average DSCR, P50 | C19: =SPV3!D96 -> 1.4068652
B20: LLCR, P50 | C20: =SUMPRODUCT(SPV3!F16:AD16,SPV3!F20:AD20)/$C$5 -> 1.4067918
B21: LLCR, P90 | C21: =SUMPRODUCT(SPV3!F17:AD17,SPV3!F20:AD20)/$C$5 -> 1.3
B22: PLCR, P50 | C22: =NPV($C$8,SPV3!F16:AD16)/$C$5 -> 2.0026488
B23: Years of PPA left after the loan | C23: =Inputs!$C$17-Inputs!$C$31 -> 15
B25: Annual cover, years 1–10 (₹ Cr)
B26: Operating year | D26: =SPV3!F5 -> 1 | E26: =SPV3!G5 -> 2 | F26: =SPV3!H5 -> 3 | G26: =SPV3!I5 -> 4 | H26: =SPV3!J5 -> 5 | I26: =SPV3!K5 -> 6 | J26: =SPV3!L5 -> 7 | K26: =SPV3!M5 -> 8 | ... M26: =SPV3!O5 -> 10
B27: Financial year | D27: =SPV3!F6 -> 2029 | E27: =SPV3!G6 -> 2030 | F27: =SPV3!H6 -> 2031 | G27: =SPV3!I6 -> 2032 | H27: =SPV3!J6 -> 2033 | I27: =SPV3!K6 -> 2034 | J27: =SPV3!L6 -> 2035 | K27: =SPV3!M6 -> 2036 | ... M27: =SPV3!O6 -> 2038
B28: CFADS, P50 (pre-tax) | D28: =SPV3!F16 -> 12.7392 | E28: =SPV3!G16 -> 12.678923 | F28: =SPV3!H16 -> 12.618888 | G28: =SPV3!I16 -> 12.559092 | H28: =SPV3!J16 -> 12.499536 | I28: =SPV3!K16 -> 12.440217 | J28: =SPV3!L16 -> 12.381137 | K28: =SPV3!M16 -> 12.322292 | ... M28: =SPV3!O16 -> 12.205308
B29: CFADS, P90 | D29: =SPV3!F17 -> 11.774771 | E29: =SPV3!G17 -> 11.718352 | F29: =SPV3!H17 -> 11.662159 | G29: =SPV3!I17 -> 11.60619 | H29: =SPV3!J17 -> 11.550445 | I29: =SPV3!K17 -> 11.494924 | J29: =SPV3!L17 -> 11.439624 | K29: =SPV3!M17 -> 11.384545 | ... M29: =SPV3!O17 -> 11.275048
B30: Senior debt service | D30: =SPV3!F30 -> 9.0575163 | E30: =SPV3!G30 -> 9.014117 | F30: =SPV3!H30 -> 8.9708913 | G30: =SPV3!I30 -> 8.9278385 | H30: =SPV3!J30 -> 8.8849579 | I30: =SPV3!K30 -> 8.8422489 | J30: =SPV3!L30 -> 8.7997106 | K30: =SPV3!M30 -> 8.7573426 | ... M30: =SPV3!O30 -> 8.6731142
B31: DSCR, P50 | D31: =SPV3!F31 -> 1.4064783 | E31: =SPV3!G31 -> 1.406563 | F31: =SPV3!H31 -> 1.4066481 | G31: =SPV3!I31 -> 1.4067338 | H31: =SPV3!J31 -> 1.4068199 | I31: =SPV3!K31 -> 1.4069065 | J31: =SPV3!L31 -> 1.4069936 | K31: =SPV3!M31 -> 1.4070812 | ... M31: =SPV3!O31 -> 1.4072579
B32: DSCR, P90 | D32: =SPV3!F32 -> 1.3 | E32: =SPV3!G32 -> 1.3 | F32: =SPV3!H32 -> 1.3 | G32: =SPV3!I32 -> 1.3 | H32: =SPV3!J32 -> 1.3 | I32: =SPV3!K32 -> 1.3 | J32: =SPV3!L32 -> 1.3 | K32: =SPV3!M32 -> 1.3 | ... M32: =SPV3!O32 -> 1.3
B33: Loan balance, closing | D33: =SPV3!F29 -> 50.087557 | E33: =SPV3!G29 -> 46.332633 | F33: =SPV3!H29 -> 42.226668 | G33: =SPV3!I29 -> 37.73263 | H33: =SPV3!J29 -> 32.809598 | I33: =SPV3!K29 -> 27.412357 | J33: =SPV3!L29 -> 21.490944 | K33: =SPV3!M29 -> 14.99015 | ... M33: =SPV3!O29 -> 0
B35: Downside cases on the same loan (minimum DSCR, years 1–10)
B36: Case | C36: Yield × | D36: Tariff × | E36: Opex × | F36: + rate (bp) | H36: Min DSCR
B37: P50 base | C37: 1 | D37: 1 | E37: 1 | F37: 0 | H37: =N46 -> 1.4064783
B38: P90 yield | C38: =1-Inputs!$C$39 -> 0.936 | D38: 1 | E38: 1 | F38: 0 | H38: =N47 -> 1.3
B39: Tariff −5% | C39: 1 | D39: 0.95 | E39: 1 | F39: 0 | H39: =N48 -> 1.3232921
B40: Opex +10% | C40: 1 | D40: 1 | E40: 1.1 | F40: 0 | H40: =N49 -> 1.3803932
B41: One-year yield −10% (≈ P99) | C41: 0.9 | D41: 1 | E41: 1 | F41: 0 | H41: =N50 -> 1.2396675
B42: Interest +100 bp | C42: 1 | D42: 1 | E42: 1 | F42: 100 | H42: =N51 -> 1.3280007
B43: Combined: P90, tariff −5%, opex +10% | C43: =1-Inputs!$C$39 -> 0.936 | D43: 0.95 | E43: 1.1 | F43: 0 | H43: =N52 -> 1.1947031
B45: DSCR by year under each case | D45: =SPV3!F5 -> 1 | E45: =SPV3!G5 -> 2 | F45: =SPV3!H5 -> 3 | G45: =SPV3!I5 -> 4 | H45: =SPV3!J5 -> 5 | I45: =SPV3!K5 -> 6 | J45: =SPV3!L5 -> 7 | K45: =SPV3!M5 -> 8 | ... M45: =SPV3!O5 -> 10 | N45: Minimum
B46: =B37 -> P50 base | D46: =IF(SPV3!F30=0,"",(SPV3!F13*$C$37*$D$37-SPV3!F15*$E$37)/(SPV3!F30+SPV3!F25*$F$37/10000)) -> 1.4064783 | E46: =IF(SPV3!G30=0,"",(SPV3!G13*$C$37*$D$37-SPV3!G15*$E$37)/(SPV3!G30+SPV3!G25*$F$37/10000)) -> 1.406563 | F46: =IF(SPV3!H30=0,"",(SPV3!H13*$C$37*$D$37-SPV3!H15*$E$37)/(SPV3!H30+SPV3!H25*$F$37/10000)) -> 1.4066481 | G46: =IF(SPV3!I30=0,"",(SPV3!I13*$C$37*$D$37-SPV3!I15*$E$37)/(SPV3!I30+SPV3!I25*$F$37/10000)) -> 1.4067338 | H46: =IF(SPV3!J30=0,"",(SPV3!J13*$C$37*$D$37-SPV3!J15*$E$37)/(SPV3!J30+SPV3!J25*$F$37/10000)) -> 1.4068199 | I46: =IF(SPV3!K30=0,"",(SPV3!K13*$C$37*$D$37-SPV3!K15*$E$37)/(SPV3!K30+SPV3!K25*$F$37/10000)) -> 1.4069065 | J46: =IF(SPV3!L30=0,"",(SPV3!L13*$C$37*$D$37-SPV3!L15*$E$37)/(SPV3!L30+SPV3!L25*$F$37/10000)) -> 1.4069936 | K46: =IF(SPV3!M30=0,"",(SPV3!M13*$C$37*$D$37-SPV3!M15*$E$37)/(SPV3!M30+SPV3!M25*$F$37/10000)) -> 1.4070812 | ... M46: =IF(SPV3!O30=0,"",(SPV3!O13*$C$37*$D$37-SPV3!O15*$E$37)/(SPV3!O30+SPV3!O25*$F$37/10000)) -> 1.4072579 | N46: =MIN(D46:M46) -> 1.4064783
B47: =B38 -> P90 yield | D47: =IF(SPV3!F30=0,"",(SPV3!F13*$C$38*$D$38-SPV3!F15*$E$38)/(SPV3!F30+SPV3!F25*$F$38/10000)) -> 1.3 | E47: =IF(SPV3!G30=0,"",(SPV3!G13*$C$38*$D$38-SPV3!G15*$E$38)/(SPV3!G30+SPV3!G25*$F$38/10000)) -> 1.3 | F47: =IF(SPV3!H30=0,"",(SPV3!H13*$C$38*$D$38-SPV3!H15*$E$38)/(SPV3!H30+SPV3!H25*$F$38/10000)) -> 1.3 | G47: =IF(SPV3!I30=0,"",(SPV3!I13*$C$38*$D$38-SPV3!I15*$E$38)/(SPV3!I30+SPV3!I25*$F$38/10000)) -> 1.3 | H47: =IF(SPV3!J30=0,"",(SPV3!J13*$C$38*$D$38-SPV3!J15*$E$38)/(SPV3!J30+SPV3!J25*$F$38/10000)) -> 1.3 | I47: =IF(SPV3!K30=0,"",(SPV3!K13*$C$38*$D$38-SPV3!K15*$E$38)/(SPV3!K30+SPV3!K25*$F$38/10000)) -> 1.3 | J47: =IF(SPV3!L30=0,"",(SPV3!L13*$C$38*$D$38-SPV3!L15*$E$38)/(SPV3!L30+SPV3!L25*$F$38/10000)) -> 1.3 | K47: =IF(SPV3!M30=0,"",(SPV3!M13*$C$38*$D$38-SPV3!M15*$E$38)/(SPV3!M30+SPV3!M25*$F$38/10000)) -> 1.3 | ... M47: =IF(SPV3!O30=0,"",(SPV3!O13*$C$38*$D$38-SPV3!O15*$E$38)/(SPV3!O30+SPV3!O25*$F$38/10000)) -> 1.3 | N47: =MIN(D47:M47) -> 1.3
B48: =B39 -> Tariff −5% | D48: =IF(SPV3!F30=0,"",(SPV3!F13*$C$39*$D$39-SPV3!F15*$E$39)/(SPV3!F30+SPV3!F25*$F$39/10000)) -> 1.3232921 | E48: =IF(SPV3!G30=0,"",(SPV3!G13*$C$39*$D$39-SPV3!G15*$E$39)/(SPV3!G30+SPV3!G25*$F$39/10000)) -> 1.3233106 | F48: =IF(SPV3!H30=0,"",(SPV3!H13*$C$39*$D$39-SPV3!H15*$E$39)/(SPV3!H30+SPV3!H25*$F$39/10000)) -> 1.3233293 | G48: =IF(SPV3!I30=0,"",(SPV3!I13*$C$39*$D$39-SPV3!I15*$E$39)/(SPV3!I30+SPV3!I25*$F$39/10000)) -> 1.323348 | H48: =IF(SPV3!J30=0,"",(SPV3!J13*$C$39*$D$39-SPV3!J15*$E$39)/(SPV3!J30+SPV3!J25*$F$39/10000)) -> 1.3233669 | I48: =IF(SPV3!K30=0,"",(SPV3!K13*$C$39*$D$39-SPV3!K15*$E$39)/(SPV3!K30+SPV3!K25*$F$39/10000)) -> 1.3233858 | J48: =IF(SPV3!L30=0,"",(SPV3!L13*$C$39*$D$39-SPV3!L15*$E$39)/(SPV3!L30+SPV3!L25*$F$39/10000)) -> 1.3234049 | K48: =IF(SPV3!M30=0,"",(SPV3!M13*$C$39*$D$39-SPV3!M15*$E$39)/(SPV3!M30+SPV3!M25*$F$39/10000)) -> 1.323424 | ... M48: =IF(SPV3!O30=0,"",(SPV3!O13*$C$39*$D$39-SPV3!O15*$E$39)/(SPV3!O30+SPV3!O25*$F$39/10000)) -> 1.3234627 | N48: =MIN(D48:M48) -> 1.3232921
B49: =B40 -> Opex +10% | D49: =IF(SPV3!F30=0,"",(SPV3!F13*$C$40*$D$40-SPV3!F15*$E$40)/(SPV3!F30+SPV3!F25*$F$40/10000)) -> 1.3807538 | E49: =IF(SPV3!G30=0,"",(SPV3!G13*$C$40*$D$40-SPV3!G15*$E$40)/(SPV3!G30+SPV3!G25*$F$40/10000)) -> 1.3807146 | F49: =IF(SPV3!H30=0,"",(SPV3!H13*$C$40*$D$40-SPV3!H15*$E$40)/(SPV3!H30+SPV3!H25*$F$40/10000)) -> 1.3806752 | G49: =IF(SPV3!I30=0,"",(SPV3!I13*$C$40*$D$40-SPV3!I15*$E$40)/(SPV3!I30+SPV3!I25*$F$40/10000)) -> 1.3806356 | H49: =IF(SPV3!J30=0,"",(SPV3!J13*$C$40*$D$40-SPV3!J15*$E$40)/(SPV3!J30+SPV3!J25*$F$40/10000)) -> 1.3805958 | I49: =IF(SPV3!K30=0,"",(SPV3!K13*$C$40*$D$40-SPV3!K15*$E$40)/(SPV3!K30+SPV3!K25*$F$40/10000)) -> 1.3805557 | J49: =IF(SPV3!L30=0,"",(SPV3!L13*$C$40*$D$40-SPV3!L15*$E$40)/(SPV3!L30+SPV3!L25*$F$40/10000)) -> 1.3805155 | K49: =IF(SPV3!M30=0,"",(SPV3!M13*$C$40*$D$40-SPV3!M15*$E$40)/(SPV3!M30+SPV3!M25*$F$40/10000)) -> 1.3804749 | ... M49: =IF(SPV3!O30=0,"",(SPV3!O13*$C$40*$D$40-SPV3!O15*$E$40)/(SPV3!O30+SPV3!O25*$F$40/10000)) -> 1.3803932 | N49: =MIN(D49:M49) -> 1.3803932
B50: =B41 -> One-year yield −10% (≈ P99) | D50: =IF(SPV3!F30=0,"",(SPV3!F13*$C$41*$D$41-SPV3!F15*$E$41)/(SPV3!F30+SPV3!F25*$F$41/10000)) -> 1.240106 | E50: =IF(SPV3!G30=0,"",(SPV3!G13*$C$41*$D$41-SPV3!G15*$E$41)/(SPV3!G30+SPV3!G25*$F$41/10000)) -> 1.2400583 | F50: =IF(SPV3!H30=0,"",(SPV3!H13*$C$41*$D$41-SPV3!H15*$E$41)/(SPV3!H30+SPV3!H25*$F$41/10000)) -> 1.2400104 | G50: =IF(SPV3!I30=0,"",(SPV3!I13*$C$41*$D$41-SPV3!I15*$E$41)/(SPV3!I30+SPV3!I25*$F$41/10000)) -> 1.2399623 | H50: =IF(SPV3!J30=0,"",(SPV3!J13*$C$41*$D$41-SPV3!J15*$E$41)/(SPV3!J30+SPV3!J25*$F$41/10000)) -> 1.2399138 | I50: =IF(SPV3!K30=0,"",(SPV3!K13*$C$41*$D$41-SPV3!K15*$E$41)/(SPV3!K30+SPV3!K25*$F$41/10000)) -> 1.2398651 | J50: =IF(SPV3!L30=0,"",(SPV3!L13*$C$41*$D$41-SPV3!L15*$E$41)/(SPV3!L30+SPV3!L25*$F$41/10000)) -> 1.2398161 | K50: =IF(SPV3!M30=0,"",(SPV3!M13*$C$41*$D$41-SPV3!M15*$E$41)/(SPV3!M30+SPV3!M25*$F$41/10000)) -> 1.2397668 | ... M50: =IF(SPV3!O30=0,"",(SPV3!O13*$C$41*$D$41-SPV3!O15*$E$41)/(SPV3!O30+SPV3!O25*$F$41/10000)) -> 1.2396675 | N50: =MIN(D50:M50) -> 1.2396675
B51: =B42 -> Interest +100 bp | D51: =IF(SPV3!F30=0,"",(SPV3!F13*$C$42*$D$42-SPV3!F15*$E$42)/(SPV3!F30+SPV3!F25*$F$42/10000)) -> 1.3280007 | E51: =IF(SPV3!G30=0,"",(SPV3!G13*$C$42*$D$42-SPV3!G15*$E$42)/(SPV3!G30+SPV3!G25*$F$42/10000)) -> 1.3325206 | F51: =IF(SPV3!H30=0,"",(SPV3!H13*$C$42*$D$42-SPV3!H15*$E$42)/(SPV3!H30+SPV3!H25*$F$42/10000)) -> 1.3375659 | G51: =IF(SPV3!I30=0,"",(SPV3!I13*$C$42*$D$42-SPV3!I15*$E$42)/(SPV3!I30+SPV3!I25*$F$42/10000)) -> 1.3432033 | H51: =IF(SPV3!J30=0,"",(SPV3!J13*$C$42*$D$42-SPV3!J15*$E$42)/(SPV3!J30+SPV3!J25*$F$42/10000)) -> 1.349509 | I51: =IF(SPV3!K30=0,"",(SPV3!K13*$C$42*$D$42-SPV3!K15*$E$42)/(SPV3!K30+SPV3!K25*$F$42/10000)) -> 1.3565703 | J51: =IF(SPV3!L30=0,"",(SPV3!L13*$C$42*$D$42-SPV3!L15*$E$42)/(SPV3!L30+SPV3!L25*$F$42/10000)) -> 1.3644879 | K51: =IF(SPV3!M30=0,"",(SPV3!M13*$C$42*$D$42-SPV3!M15*$E$42)/(SPV3!M30+SPV3!M25*$F$42/10000)) -> 1.3733778 | ... M51: =IF(SPV3!O30=0,"",(SPV3!O13*$C$42*$D$42-SPV3!O15*$E$42)/(SPV3!O30+SPV3!O25*$F$42/10000)) -> 1.3946367 | N51: =MIN(D51:M51) -> 1.3280007
B52: =B43 -> Combined: P90, tariff −5%, opex +10% | D52: =IF(SPV3!F30=0,"",(SPV3!F13*$C$43*$D$43-SPV3!F15*$E$43)/(SPV3!F30+SPV3!F25*$F$43/10000)) -> 1.1964133 | E52: =IF(SPV3!G30=0,"",(SPV3!G13*$C$43*$D$43-SPV3!G15*$E$43)/(SPV3!G30+SPV3!G25*$F$43/10000)) -> 1.1962275 | F52: =IF(SPV3!H30=0,"",(SPV3!H13*$C$43*$D$43-SPV3!H15*$E$43)/(SPV3!H30+SPV3!H25*$F$43/10000)) -> 1.1960407 | G52: =IF(SPV3!I30=0,"",(SPV3!I13*$C$43*$D$43-SPV3!I15*$E$43)/(SPV3!I30+SPV3!I25*$F$43/10000)) -> 1.1958528 | H52: =IF(SPV3!J30=0,"",(SPV3!J13*$C$43*$D$43-SPV3!J15*$E$43)/(SPV3!J30+SPV3!J25*$F$43/10000)) -> 1.1956639 | I52: =IF(SPV3!K30=0,"",(SPV3!K13*$C$43*$D$43-SPV3!K15*$E$43)/(SPV3!K30+SPV3!K25*$F$43/10000)) -> 1.1954739 | J52: =IF(SPV3!L30=0,"",(SPV3!L13*$C$43*$D$43-SPV3!L15*$E$43)/(SPV3!L30+SPV3!L25*$F$43/10000)) -> 1.1952828 | K52: =IF(SPV3!M30=0,"",(SPV3!M13*$C$43*$D$43-SPV3!M15*$E$43)/(SPV3!M30+SPV3!M25*$F$43/10000)) -> 1.1950906 | ... M52: =IF(SPV3!O30=0,"",(SPV3!O13*$C$43*$D$43-SPV3!O15*$E$43)/(SPV3!O30+SPV3!O25*$F$43/10000)) -> 1.1947031 | N52: =MIN(D52:M52) -> 1.1947031
B54: Revenue fall to break-even (DSCR 1.00x) by year | D54: =IF(SPV3!F13=0,"",1-(SPV3!F30+SPV3!F15)/SPV3!F13) -> 0.24431846 | E54: =IF(SPV3!G13=0,"",1-(SPV3!G30+SPV3!G15)/SPV3!G13) -> 0.24417516 | F54: =IF(SPV3!H13=0,"",1-(SPV3!H30+SPV3!H15)/SPV3!H13) -> 0.24403128 | G54: =IF(SPV3!I13=0,"",1-(SPV3!I30+SPV3!I15)/SPV3!I13) -> 0.24388683 | H54: =IF(SPV3!J13=0,"",1-(SPV3!J30+SPV3!J15)/SPV3!J13) -> 0.2437418 | I54: =IF(SPV3!K13=0,"",1-(SPV3!K30+SPV3!K15)/SPV3!K13) -> 0.24359618 | J54: =IF(SPV3!L13=0,"",1-(SPV3!L30+SPV3!L15)/SPV3!L13) -> 0.24344998 | K54: =IF(SPV3!M13=0,"",1-(SPV3!M30+SPV3!M15)/SPV3!M13) -> 0.24330319 | ... M54: =IF(SPV3!O13=0,"",1-(SPV3!O30+SPV3!O15)/SPV3!O13) -> 0.24300785 | N54: =MIN(D54:M54) -> 0.24300785
B56: Margin money before first drawdown (debt-first draws)
B57: Margin required: HoldCo equity into P3 (₹ Cr) | C57: ='Sources & Uses'!$C$30 -> 28.299966
B58: Upfront share the lender wants | C58: =Inputs!$C$109 -> 0.25
B59: Upfront margin required (₹ Cr) | C59: =C57*C58 -> 7.0749914
B60: Certified pre-close project spend: P3 PMC (₹ Cr) | C60: ='Sources & Uses'!$C$37 -> 3.985
B61: Promoter cash left at HoldCo for P3 equity (₹ Cr) | C61: =MAX(0,Inputs!$C$72+Inputs!$C$73-SUMIF(HoldCo!E5:AH5,"<"&Inputs!$C$7,HoldCo!E16:AH16)) -> 4.40875
B62: HNI money paid into escrow at close (₹ Cr) | C62: =IF(Inputs!$C$100=1,Inputs!$C$92,0) -> 0
B63: Margin available upfront (₹ Cr) | C63: =C60+C61+C62 -> 8.39375
B64: Upfront surplus / (shortfall) (₹ Cr) | C64: =C63-C59 -> 1.3187586
B65: HNI money committed, called when drawn (₹ Cr) | C65: =IF(Inputs!$C$100=0,Inputs!$C$92,0) -> 0
B66: Margin still to be committed (₹ Cr) | C66: =MAX(0,C57-C63-C65) -> 19.906216
B67: Status | C67: =IF(C64<0,"Upfront margin short",IF(C66>0,"Upfront covered; rest still to commit","Margin covered")) -> Upfront covered; rest still to commit
B69: Certified PMC is capitalised in SPV3 as share capital (row 43 on Sources & Uses), so it counts as project spend and margin; confirm the lender accepts certified pre-close spend as margin.

Sheet Funding Plan
B1: Funding Plan — three tracks for P3 and P4, targets, instruments and timeline
B2: Amounts link to the model. Names and cost ranges are from knowledge to mid-2026: confirm each institution's current appetite before outreach.
B4: 1. The three funding tracks (plus P4 debt later)
B5: Track | C5: Ask | D5: Who to approach | E5: Commit by | F5: Money in
B6: 1. P3 senior debt | C6: ="₹"&TEXT('Sources & Uses'!$C$19,"0.0")&" Cr loan, "&TEXT('Sources & Uses'!$C$34,"0%")&" gearing, "&Inputs!$C$31&" years" -> ₹53.5 Cr loan, 65% gearing, 10 years | D6: Green NBFCs first (Tata Cleantech Capital, Ecofy, L&T Finance); test bank pricing (IREDA, SBI, Axis) | E6: Sanction Apr–May 2027 | F6: Drawn in the Jul–Oct 2027 build
B7: 2. P3 pre-COD HNI equity | C7: =IF(Inputs!$C$92=0,"₹35 Cr HoldCo CCDs (switch on in Inputs)","₹"&TEXT(Inputs!$C$92,"0.0")&" Cr HoldCo CCDs, "&TEXT(Inputs!$C$94,"0%")&" cumulative coupon, COD liquidity window") -> ₹35 Cr HoldCo CCDs (switch on in Inputs) | D7: Family offices and HNIs through wealth platforms (360 ONE, Nuvama Private, Kotak Private, ASK, Waterfield) | E7: Subscriptions Mar–Apr 2027 | F7: At P3 close, June 2027
B8: 3. Institutional partner, P3+P4 | C8: ="≈ ₹"&TEXT(HoldCo!$D$39,"0")&" Cr new money"&IF(Inputs!$C$92=0,", plus an option to buy any HNI CCDs at COD",", plus an option to buy the HNI CCDs (≈ ₹"&TEXT(HoldCo!$D$132,"0")&" Cr for 100%)") -> ≈ ₹90 Cr new money, plus an option to buy any HNI CCDs at COD | D8: Climate and infrastructure funds, rooftop platforms, development investors | E8: Commitment letter by P3 close | F8: Round after P3 COD (≈ Apr 2028), priced at COD
B9: 4. P4 senior debt (later) | C9: ="≈ ₹"&TEXT('Sources & Uses'!$D$19,"0")&" Cr" -> ≈ ₹107 Cr | D9: Banks or IREDA, on P3's operating record | E9: FY29 | F9: P4 build
B10: Shared groundwork: promoter-group disclosure note, certified pre-close spend, LOA status of the remaining 15.5 MWp, lender-controlled escrow, ring-fenced board.
B12: 2. Debt providers
B13: Type | C13: Names to approach | D13: All-in cost | E13: Tenor | F13: Sanction time | G13: Credit tolerance | H13: Role for Arclight
B14: Public-sector lenders | C14: IREDA, SBI, Bank of Baroda, Union Bank, Canara Bank; REC and PFC at the margin | D14: 9.5–10.5% | E14: 10–15 yrs | F14: 4–6 months | G14: Strict | H14: Best cost, once a partner is signed
B15: Private banks | C15: Axis, HDFC Bank, ICICI, Kotak, IndusInd, Yes Bank | D15: 10–11% | E15: 7–12 yrs | F15: 3–5 months | G15: Strict | H15: As above; guarantee limits
B16: Green and infra NBFCs | C16: Tata Cleantech Capital, Ecofy, L&T Finance, Aditya Birla Finance, Tata Capital | D16: 10.5–12% | E16: 8–12 yrs | F16: 6–12 weeks | G16: Moderate: lend on project cash flow | H16: First lender for P3; refinance after a year
B17: Private credit funds | C17: Vivriti, Northern Arc, InCred Alternatives, Neo, Nuvama Alternatives, Kotak Alternate Assets | D17: 13–17% | E17: 2–5 yrs | F17: 4–8 weeks | G17: Flexible; secured and costly | H17: Equity bridge or HoldCo loan
B18: Development and foreign lenders | C18: IFC, ADB, FMO, Proparco, DEG, BII, US DFC; SMBC, MUFG, StanChart, DBS | D18: 10–12% hedged | E18: 10–15 yrs | F18: 6–12 months | G18: Strict integrity checks | H18: Mostly via the NBFCs at this size
B20: 3. Equity partners
B21: Type | C21: Names to approach | D21: Return expected | E21: Ticket and terms | F21: Time to close | G21: What they check | H21: Fit
B22: Rooftop and C&I platforms | C22: CleanMax, Fourth Partner Energy, Amplus (Gentari), Radiance Renewables, Sunsure | D22: 11–13% | E22: Full ₹90 Cr; often want control or a forward purchase | F22: 3–6 months | G22: The assets more than the promoter | H22: Strategic route; most certain
B23: Indian climate and infra funds | C23: Eversource Capital, SBICAP Ventures (Neev), Aavishkaar, Kotak Alternate Assets, Nuvama/EAAA | D23: 15–18% | E23: ₹50–150 Cr minority; CCPS or CCD | F23: 4–8 months | G23: Governance, integrity, pipeline | H23: Track 3 lead candidates
B24: Global development and climate investors | C24: BII, Norfund, DEG, FMO, Proparco, ORIX | D24: 13–16% (₹) | E24: Usually $15–25M+ | F24: 6–12 months | G24: Strict integrity and ESG | H24: Platform pitch (P3, P4, P5…)
B25: Family offices and HNIs | C25: Via 360 ONE, Nuvama Private, Kotak Private, ASK, Waterfield, Centrum, Anand Rathi | D25: 12–15% coupon; 18%+ equity | E25: ₹1–25 Cr each; quarterly coupon | F25: 4–10 weeks | G25: Coupon reliability, exit date | H25: Track 2 (pre-COD CCDs)
B27: 4. Which instrument for the HNI tranche
C28: CCD (recommended) | D28: CCPS | E28: NCD
B29: Counted as P3 equity by the lender | C29: Usually, as quasi-equity; confirm in the term sheet | D29: Yes: pure equity | E29: No: borrowed margin
B30: Cash to HNIs before conversion | C30: 12% cumulative coupon from FY30–31 | D30: Little or none for about 10 years | E30: Fixed coupon; no HoldCo cash in construction
B31: HoldCo tax | C31: Deductible: offsets SPV coupons (mirror) | D31: Not deductible: about ₹17 Cr of tax returns | E31: Deductible
B32: Upside | C32: Converts with the pre-COD credit | D32: Full equity upside | E32: None
B33: Exit at the COD round | C33: Sold to the partner at the round price | D33: Same | E33: Repaid from the round, diverting P4 money
B34: HNI tax | C34: Coupon at slab with TDS; 12.5% LTCG on shares after conversion; s.50AA slab on CCD sale | D34: Dividends at slab; 12.5% LTCG after 24 months | E34: Interest at slab
B35: Regulatory catch | C35: Convert within 10 years of issue, else a deposit | D35: None major | E35: Unsecured, unlisted NCDs to individuals are deposits
B37: 5. Construction draw order
C38: Equity first | D38: Pro-rata | E38: Debt first | F38: Selected / lowest cost
B39: P3 total cost (₹ Cr) | C39: ='Construction Draws'!F30 -> 0.97635871 | D39: ='Construction Draws'!F31 -> 0.93188356 | E39: ='Construction Draws'!F32 -> 0.89862394 | F39: ='Construction Draws'!C35&" / "&'Construction Draws'!C39 -> Debt first / Debt first
B40: P4 total cost (₹ Cr) | C40: ='Construction Draws'!F68 -> 2.4446526 | D40: ='Construction Draws'!F69 -> 2.7561076 | E40: ='Construction Draws'!F70 -> 3.0227005 | F40: ='Construction Draws'!C73&" / "&'Construction Draws'!C77 -> Equity first / Equity first
B41: Debt first saves money only while equity is committed but not yet paid in; escrowed cash at close makes equity first cheapest.

Sheet Funding Timeline
B1: Funding Timeline — October 2026 to April 2028
B2: Bars show when each activity runs, by track. Amber = decision or money-in point. Dates are targets for discussion.
B4: Activity | C4: Track | D4: Oct-26 | E4: Nov-26 | F4: Dec-26 | G4: Jan-27 | H4: Feb-27 | I4: Mar-27 | J4: Apr-27 | K4: May-27 | L4: Jun-27 | M4: Jul-27 | N4: Aug-27 | O4: Sep-27 | P4: Oct-27 | Q4: Nov-27 | R4: Dec-27 | S4: Jan-28 | T4: Feb-28 | U4: Mar-28 | V4: Apr-28
B5: Disclosure note, credit clean-up, board and escrow | C5: Groundwork
B6: Information memorandum, data room, model | C6: Groundwork
B7: NBFC indicative terms | C7: 1 · P3 debt
B8: Lead lender, independent engineer report | C8: 1 · P3 debt
B9: Credit approval and loan documents | C9: 1 · P3 debt
B10: P3 financial close | C10: 1 · P3 debt
B11: Build and debt draws (Jul–Oct) | C11: 1 · P3 debt
B12: P3 COD | C12: 1 · P3 debt
B13: HNI soft commitments (aim 1.3–1.5x) | C13: 2 · HNI
B14: HNI subscriptions signed, conditional on close | C14: 2 · HNI
B15: HNI money in at close | C15: 2 · HNI
B16: COD liquidity window: HNIs may sell | C16: 2 · HNI
... B21: P4 loan process (banks / IREDA) | C21: 4 · P4 debt
B23: Amber = decision or money-in point. Dates are targets for discussion.

Sheet Sources & Uses
B1: Sources & Uses and Debt Sizing — per SPV
B2: Debt is sized first: the facility is the lower of 70% gearing and DSCR capacity on the chosen case. HoldCo funds the residual.
B4: ₹ Cr | C4: SPV3 (P3) | D4: SPV4 (P4) | E4: Portfolio
B5: Construction cost
B6: Capacity (MWp) | C6: =Inputs!$C$6 -> 25 | D6: =Inputs!$D$6 -> 50 | E6: =C6+D6 -> 75
B7: Hard capex (EPC) | C7: =Inputs!$C$6*Inputs!$C$10/10000 -> 68.1275 | D7: =Inputs!$D$6*Inputs!$D$10/10000 -> 136.255 | E7: =C7+D7 -> 204.3825
B8: Developer fee | C8: =C7*Inputs!$C$11 -> 2.043825 | D8: =D7*Inputs!$D$11 -> 4.08765 | E8: =C8+D8 -> 6.131475
B9: Pre-operative cost | C9: =Inputs!$C$6*Inputs!$C$12/100 -> 7.9175 | D9: =Inputs!$D$6*Inputs!$D$12/100 -> 15.835 | E9: =C9+D9 -> 23.7525
B10: Contingency | C10: =C7*Inputs!$C$13 -> 2.043825 | D10: =D7*Inputs!$D$13 -> 4.08765 | E10: =C10+D10 -> 6.131475
B11: Construction capex | C11: =SUM(C7:C10) -> 80.13265 | D11: =SUM(D7:D10) -> 160.2653 | E11: =C11+D11 -> 240.39795
B12: Construction capex per kWp (₹) | C12: =C11*10000/C6 -> 32053.06 | D12: =D11*10000/D6 -> 32053.06 | E12: =E11*10000/E6 -> 32053.06
B13: Debt sizing (debt first)
B14: Financing cost factor (IDC + fees, % of facility) | C14: =Inputs!$C$32+Inputs!$C$33*Inputs!$C$34/12+'Construction Draws'!$C$36 -> 0.03161644 | D14: =Inputs!$D$32+Inputs!$D$33*Inputs!$D$34/12+'Construction Draws'!$C$74 -> 0.029466894
B15: A. Gearing-sized debt: 70% of total uses | C15: =Inputs!$C$52*C11/(1-Inputs!$C$52*C14) -> 57.362371 | D15: =Inputs!$D$52*D11/(1-Inputs!$D$52*D14) -> 114.54848 | E15: =C15+D15 -> 171.91085
B16: B. DSCR capacity at target, P50 base case | C16: =SPV3!$D$21 -> 57.921895 | D16: =SPV4!$D$21 -> 115.84379 | E16: =C16+D16 -> 173.76568
B17: C. DSCR capacity at target, P90 lender case | C17: =SPV3!$D$22 -> 53.524953 | D17: =SPV4!$D$22 -> 107.04991 | E17: =C17+D17 -> 160.57486
B18: DSCR capacity on the chosen sizing case | C18: =IF(Inputs!$C$38=2,C17,C16) -> 53.524953 | D18: =IF(Inputs!$D$38=2,D17,D16) -> 107.04991 | E18: =C18+D18 -> 160.57486
B19: Senior debt facility = lower of A and chosen case | C19: =MIN(C15,C18) -> 53.524953 | D19: =MIN(D15,D18) -> 107.04991 | E19: =C19+D19 -> 160.57486
B20: Binding constraint | C20: =IF(C15<=C18,"Gearing 70%",IF(Inputs!$C$38=2,"DSCR, P90 case","DSCR, P50 case")) -> DSCR, P90 case | D20: =IF(D15<=D18,"Gearing 70%",IF(Inputs!$D$38=2,"DSCR, P90 case","DSCR, P50 case")) -> DSCR, P90 case
B21: Equity needed above the 70% plan (contingent equity) | C21: =MAX(0,C15-C19) -> 3.8374179 | D21: =MAX(0,D15-D19) -> 7.4985759 | E21: =C21+D21 -> 11.335994
B22: Uses
B23: Construction capex | C23: =C11 -> 80.13265 | D23: =D11 -> 160.2653 | E23: =C23+D23 -> 240.39795
B24: Interest during construction (chosen draw order) | C24: =C19*'Construction Draws'!$C$36 -> 0.76004218 | D24: =D19*'Construction Draws'!$C$74 -> 1.2899757 | E24: =C24+D24 -> 2.0500178
B25: Construction draw order used | C25: ='Construction Draws'!$C$35 -> Debt first | D25: ='Construction Draws'!$C$73 -> Equity first
B26: Arrangement and commitment fees | C26: =C19*(Inputs!$C$32+Inputs!$C$33*Inputs!$C$34/12) -> 0.93222626 | D26: =D19*(Inputs!$D$32+Inputs!$D$33*Inputs!$D$34/12) -> 1.8644525 | E26: =C26+D26 -> 2.7966788
B27: Total uses (incl. any DSRA funded at COD, row 44) | C27: =C23+C24+C26+C44 -> 81.824918 | D27: =D23+D24+D26+D44 -> 163.41973 | E27: =C27+D27 -> 245.24465
B28: Sources
B29: Senior debt (SPV) | C29: =C19 -> 53.524953 | D29: =D19 -> 107.04991 | E29: =C29+D29 -> 160.57486
B30: HoldCo injection (residual) | C30: =C27-C29 -> 28.299966 | D30: =D27-D29 -> 56.369822 | E30: =C30+D30 -> 84.669788
B31: of which equity shares | C31: =C30*(1-Inputs!$C$55) -> 4.2449948 | D31: =D30*(1-Inputs!$D$55) -> 8.4554734 | E31: =C31+D31 -> 12.700468
B32: of which CCD / NCD | C32: =C30*Inputs!$C$55 -> 24.054971 | D32: =D30*Inputs!$D$55 -> 47.914349 | E32: =C32+D32 -> 71.96932
B33: Total sources | C33: =C29+C30 -> 81.824918 | D33: =D29+D30 -> 163.41973 | E33: =C33+D33 -> 245.24465
B34: Gearing (debt ÷ total uses) | C34: =C29/C27 -> 0.65414001 | D34: =D29/D27 -> 0.65506109 | E34: =E29/E27 -> 0.65475378
B35: Check: sources − uses | C35: =C33-C27 -> 0 | D35: =D33-D27 -> 0 | E35: =C35+D35 -> 0
B36: Pre-close cash (HoldCo-funded before close; PMC and premium are capitalised in the SPV, row 43)
B37: PMC / owner's engineer | C37: =IF(Inputs!$C$66=1,0,Inputs!$C$6*Inputs!$C$65/100) -> 3.985 | D37: =IF(Inputs!$D$66=1,0,Inputs!$D$6*Inputs!$D$65/100) -> 7.97 | E37: =C37+D37 -> 11.955
B38: Performance bank guarantee (non-cash) | C38: =Inputs!$C$6*Inputs!$C$67/10000 -> 5.625 | D38: =Inputs!$D$6*Inputs!$D$67/10000 -> 11.25 | E38: =C38+D38 -> 16.875
B39: Cash margin on the PBG (nil with a surety bond) | C39: =IF(Inputs!$C$106=2,0,C38*Inputs!$C$68) -> 1.40625 | D39: =IF(Inputs!$C$106=2,0,D38*Inputs!$D$68) -> 2.8125 | E39: =C39+D39 -> 4.21875
B40: Surety-bond premium (if used) | C40: =IF(Inputs!$C$106=2,C38*Inputs!$C$107*Inputs!$C$108,0) -> 0 | D40: =IF(Inputs!$C$106=2,D38*Inputs!$C$107*Inputs!$C$108,0) -> 0 | E40: =C40+D40 -> 0
B41: Pre-close cash need | C41: =C37+C39+C40 -> 5.39125 | D41: =D37+D39+D40 -> 10.7825 | E41: =C41+D41 -> 16.17375
B42: Total HoldCo funding for the SPV | C42: =C30+C41 -> 33.691216 | D42: =D30+D41 -> 67.152322 | E42: =C42+D42 -> 100.84354
B43: Capitalised cost in the SPV (uses excl. DSRA, plus PMC and surety premium) | C43: =C23+C24+C26+C37+C40 -> 85.809918 | D43: =D23+D24+D26+D37+D40 -> 171.38973 | E43: =C43+D43 -> 257.19965
B44: DSRA funded in cash at COD (in total uses when switched on) | C44: =IF(Inputs!$C$110=1,SPV3!$E$52,0) -> 0 | D44: =IF(Inputs!$C$110=1,SPV4!$E$52,0) -> 0 | E44: =C44+D44 -> 0

Sheet Construction Draws
B1: Construction draws — equity first, pro-rata or debt first, per SPV
B2: Monthly. Debt share = lower of max gearing and DSCR capacity ÷ capex. Cost of each order = IDC on debt + carrying cost of HoldCo cash, both to COD. The chosen order feeds Sources & Uses and the HoldCo bridge.
B4: SPV3 (P3)
B5: Construction month | D5: 1 | E5: 2 | F5: 3 | G5: 4 | H5: 5 | I5: 6 | J5: 7 | K5: 8 | L5: 9 | M5: 10 | N5: 11 | O5: 12 | P5: Total
B6: Capex draw profile (input) | D6: 0.05 | E6: 0.15 | F6: 0.3 | G6: 0.5 | H6: 0 | I6: 0 | J6: 0 | K6: 0 | L6: 0 | M6: 0 | N6: 0 | O6: 0 | P6: =SUM(D6:O6) -> 1
B7: Capex drawn (₹ Cr) | D7: =$C$25*D6 -> 4.0066325 | E7: =$C$25*E6 -> 12.019898 | F7: =$C$25*F6 -> 24.039795 | G7: =$C$25*G6 -> 40.066325 | H7: =$C$25*H6 -> 0 | I7: =$C$25*I6 -> 0 | J7: =$C$25*J6 -> 0 | K7: =$C$25*K6 -> 0 | ... O7: =$C$25*O6 -> 0 | P7: =SUM(D7:O7) -> 80.13265
B8: Cumulative capex | D8: =D7 -> 4.0066325 | E8: =D8+E7 -> 16.02653 | F8: =E8+F7 -> 40.066325 | G8: =F8+G7 -> 80.13265 | H8: =G8+H7 -> 80.13265 | I8: =H8+I7 -> 80.13265 | J8: =I8+J7 -> 80.13265 | K8: =J8+K7 -> 80.13265 | L8: =K8+L7 -> 80.13265 | ... O8: =N8+O7 -> 80.13265
B9: 1. Equity first — cumulative debt | D9: =MAX(0,D8-$C$25*(1-$C$26)) -> 0 | E9: =MAX(0,E8-$C$25*(1-$C$26)) -> 0 | F9: =MAX(0,F8-$C$25*(1-$C$26)) -> 13.458628 | G9: =MAX(0,G8-$C$25*(1-$C$26)) -> 53.524953 | H9: =MAX(0,H8-$C$25*(1-$C$26)) -> 53.524953 | I9: =MAX(0,I8-$C$25*(1-$C$26)) -> 53.524953 | J9: =MAX(0,J8-$C$25*(1-$C$26)) -> 53.524953 | K9: =MAX(0,K8-$C$25*(1-$C$26)) -> 53.524953 | ... O9: =MAX(0,O8-$C$25*(1-$C$26)) -> 53.524953
B10: debt drawn | D10: =D9 -> 0 | E10: =E9-D9 -> 0 | F10: =F9-E9 -> 13.458628 | G10: =G9-F9 -> 40.066325 | H10: =H9-G9 -> 0 | I10: =I9-H9 -> 0 | J10: =J9-I9 -> 0 | K10: =K9-J9 -> 0 | L10: =L9-K9 -> 0 | ... O10: =O9-N9 -> 0 | P10: =SUM(D10:O10) -> 53.524953
B11: HoldCo cash drawn | D11: =D7-D10 -> 4.0066325 | E11: =E7-E10 -> 12.019898 | F11: =F7-F10 -> 10.581167 | G11: =G7-G10 -> 0 | H11: =H7-H10 -> 0 | I11: =I7-I10 -> 0 | J11: =J7-J10 -> 0 | K11: =K7-K10 -> 0 | ... O11: =O7-O10 -> 0 | P11: =SUM(D11:O11) -> 26.607697
B12: IDC | D12: =IF(D$5<=Inputs!$C$35,(0+D9)/2*Inputs!$C$51/12,0) -> 0 | E12: =IF(E$5<=Inputs!$C$35,(D9+E9)/2*Inputs!$C$51/12,0) -> 0 | F12: =IF(F$5<=Inputs!$C$35,(E9+F9)/2*Inputs!$C$51/12,0) -> 0.058881497 | G12: =IF(G$5<=Inputs!$C$35,(F9+G9)/2*Inputs!$C$51/12,0) -> 0.29305317 | H12: =IF(H$5<=Inputs!$C$35,(G9+H9)/2*Inputs!$C$51/12,0) -> 0 | I12: =IF(I$5<=Inputs!$C$35,(H9+I9)/2*Inputs!$C$51/12,0) -> 0 | J12: =IF(J$5<=Inputs!$C$35,(I9+J9)/2*Inputs!$C$51/12,0) -> 0 | K12: =IF(K$5<=Inputs!$C$35,(J9+K9)/2*Inputs!$C$51/12,0) -> 0 | L12: =IF(L$5<=Inputs!$C$35,(K9+L9)/2*Inputs!$C$51/12,0) -> 0 | ... O12: =IF(O$5<=Inputs!$C$35,(N9+O9)/2*Inputs!$C$51/12,0) -> 0 | P12: =SUM(D12:O12) -> 0.35193466
B13: carrying cost of HoldCo cash to COD | D13: =IF(D$5<=Inputs!$C$35,D11*Inputs!$C$37*(Inputs!$C$35-D$5+0.5)/12,0) -> 0.14607514 | E13: =IF(E$5<=Inputs!$C$35,E11*Inputs!$C$37*(Inputs!$C$35-E$5+0.5)/12,0) -> 0.31301816 | F13: =IF(F$5<=Inputs!$C$35,F11*Inputs!$C$37*(Inputs!$C$35-F$5+0.5)/12,0) -> 0.16533074 | G13: =IF(G$5<=Inputs!$C$35,G11*Inputs!$C$37*(Inputs!$C$35-G$5+0.5)/12,0) -> 0 | H13: =IF(H$5<=Inputs!$C$35,H11*Inputs!$C$37*(Inputs!$C$35-H$5+0.5)/12,0) -> 0 | I13: =IF(I$5<=Inputs!$C$35,I11*Inputs!$C$37*(Inputs!$C$35-I$5+0.5)/12,0) -> 0 | J13: =IF(J$5<=Inputs!$C$35,J11*Inputs!$C$37*(Inputs!$C$35-J$5+0.5)/12,0) -> 0 | K13: =IF(K$5<=Inputs!$C$35,K11*Inputs!$C$37*(Inputs!$C$35-K$5+0.5)/12,0) -> 0 | ... O13: =IF(O$5<=Inputs!$C$35,O11*Inputs!$C$37*(Inputs!$C$35-O$5+0.5)/12,0) -> 0 | P13: =SUM(D13:O13) -> 0.62442404
B14: 2. Pro-rata — cumulative debt | D14: =D8*$C$26 -> 2.6762476 | E14: =E8*$C$26 -> 10.704991 | F14: =F8*$C$26 -> 26.762476 | G14: =G8*$C$26 -> 53.524953 | H14: =H8*$C$26 -> 53.524953 | I14: =I8*$C$26 -> 53.524953 | J14: =J8*$C$26 -> 53.524953 | K14: =K8*$C$26 -> 53.524953 | ... O14: =O8*$C$26 -> 53.524953
B15: debt drawn | D15: =D14 -> 2.6762476 | E15: =E14-D14 -> 8.0287429 | F15: =F14-E14 -> 16.057486 | G15: =G14-F14 -> 26.762476 | H15: =H14-G14 -> 0 | I15: =I14-H14 -> 0 | J15: =J14-I14 -> 0 | K15: =K14-J14 -> 0 | L15: =L14-K14 -> 0 | ... O15: =O14-N14 -> 0 | P15: =SUM(D15:O15) -> 53.524953
B16: HoldCo cash drawn | D16: =D7-D15 -> 1.3303849 | E16: =E7-E15 -> 3.9911546 | F16: =F7-F15 -> 7.9823091 | G16: =G7-G15 -> 13.303849 | H16: =H7-H15 -> 0 | I16: =I7-I15 -> 0 | J16: =J7-J15 -> 0 | K16: =K7-K15 -> 0 | ... O16: =O7-O15 -> 0 | P16: =SUM(D16:O16) -> 26.607697
B17: IDC | D17: =IF(D$5<=Inputs!$C$35,(0+D14)/2*Inputs!$C$51/12,0) -> 0.011708583 | E17: =IF(E$5<=Inputs!$C$35,(D14+E14)/2*Inputs!$C$51/12,0) -> 0.058542917 | F17: =IF(F$5<=Inputs!$C$35,(E14+F14)/2*Inputs!$C$51/12,0) -> 0.16392017 | G17: =IF(G$5<=Inputs!$C$35,(F14+G14)/2*Inputs!$C$51/12,0) -> 0.3512575 | H17: =IF(H$5<=Inputs!$C$35,(G14+H14)/2*Inputs!$C$51/12,0) -> 0 | I17: =IF(I$5<=Inputs!$C$35,(H14+I14)/2*Inputs!$C$51/12,0) -> 0 | J17: =IF(J$5<=Inputs!$C$35,(I14+J14)/2*Inputs!$C$51/12,0) -> 0 | K17: =IF(K$5<=Inputs!$C$35,(J14+K14)/2*Inputs!$C$51/12,0) -> 0 | L17: =IF(L$5<=Inputs!$C$35,(K14+L14)/2*Inputs!$C$51/12,0) -> 0 | ... O17: =IF(O$5<=Inputs!$C$35,(N14+O14)/2*Inputs!$C$51/12,0) -> 0 | P17: =SUM(D17:O17) -> 0.58542917
B18: carrying cost of HoldCo cash to COD | D18: =IF(D$5<=Inputs!$C$35,D16*Inputs!$C$37*(Inputs!$C$35-D$5+0.5)/12,0) -> 0.048503615 | E18: =IF(E$5<=Inputs!$C$35,E16*Inputs!$C$37*(Inputs!$C$35-E$5+0.5)/12,0) -> 0.10393632 | F18: =IF(F$5<=Inputs!$C$35,F16*Inputs!$C$37*(Inputs!$C$35-F$5+0.5)/12,0) -> 0.12472358 | G18: =IF(G$5<=Inputs!$C$35,G16*Inputs!$C$37*(Inputs!$C$35-G$5+0.5)/12,0) -> 0.069290878 | H18: =IF(H$5<=Inputs!$C$35,H16*Inputs!$C$37*(Inputs!$C$35-H$5+0.5)/12,0) -> 0 | I18: =IF(I$5<=Inputs!$C$35,I16*Inputs!$C$37*(Inputs!$C$35-I$5+0.5)/12,0) -> 0 | J18: =IF(J$5<=Inputs!$C$35,J16*Inputs!$C$37*(Inputs!$C$35-J$5+0.5)/12,0) -> 0 | K18: =IF(K$5<=Inputs!$C$35,K16*Inputs!$C$37*(Inputs!$C$35-K$5+0.5)/12,0) -> 0 | ... O18: =IF(O$5<=Inputs!$C$35,O16*Inputs!$C$37*(Inputs!$C$35-O$5+0.5)/12,0) -> 0 | P18: =SUM(D18:O18) -> 0.34645439
B19: 3. Debt first — cumulative debt | D19: =MIN(D8,$C$27) -> 4.0066325 | E19: =MIN(E8,$C$27) -> 16.02653 | F19: =MIN(F8,$C$27) -> 40.066325 | G19: =MIN(G8,$C$27) -> 53.524953 | H19: =MIN(H8,$C$27) -> 53.524953 | I19: =MIN(I8,$C$27) -> 53.524953 | J19: =MIN(J8,$C$27) -> 53.524953 | K19: =MIN(K8,$C$27) -> 53.524953 | ... O19: =MIN(O8,$C$27) -> 53.524953
B20: debt drawn | D20: =D19 -> 4.0066325 | E20: =E19-D19 -> 12.019898 | F20: =F19-E19 -> 24.039795 | G20: =G19-F19 -> 13.458628 | H20: =H19-G19 -> 0 | I20: =I19-H19 -> 0 | J20: =J19-I19 -> 0 | K20: =K19-J19 -> 0 | L20: =L19-K19 -> 0 | ... O20: =O19-N19 -> 0 | P20: =SUM(D20:O20) -> 53.524953
B21: HoldCo cash drawn | D21: =D7-D20 -> 0 | E21: =E7-E20 -> 0 | F21: =F7-F20 -> 0 | G21: =G7-G20 -> 26.607697 | H21: =H7-H20 -> 0 | I21: =I7-I20 -> 0 | J21: =J7-J20 -> 0 | K21: =K7-K20 -> 0 | ... O21: =O7-O20 -> 0 | P21: =SUM(D21:O21) -> 26.607697
B22: IDC | D22: =IF(D$5<=Inputs!$C$35,(0+D19)/2*Inputs!$C$51/12,0) -> 0.017529017 | E22: =IF(E$5<=Inputs!$C$35,(D19+E19)/2*Inputs!$C$51/12,0) -> 0.087645086 | F22: =IF(F$5<=Inputs!$C$35,(E19+F19)/2*Inputs!$C$51/12,0) -> 0.24540624 | G22: =IF(G$5<=Inputs!$C$35,(F19+G19)/2*Inputs!$C$51/12,0) -> 0.40946184 | H22: =IF(H$5<=Inputs!$C$35,(G19+H19)/2*Inputs!$C$51/12,0) -> 0 | I22: =IF(I$5<=Inputs!$C$35,(H19+I19)/2*Inputs!$C$51/12,0) -> 0 | J22: =IF(J$5<=Inputs!$C$35,(I19+J19)/2*Inputs!$C$51/12,0) -> 0 | K22: =IF(K$5<=Inputs!$C$35,(J19+K19)/2*Inputs!$C$51/12,0) -> 0 | L22: =IF(L$5<=Inputs!$C$35,(K19+L19)/2*Inputs!$C$51/12,0) -> 0 | ... O22: =IF(O$5<=Inputs!$C$35,(N19+O19)/2*Inputs!$C$51/12,0) -> 0 | P22: =SUM(D22:O22) -> 0.76004218
B23: carrying cost of HoldCo cash to COD | D23: =IF(D$5<=Inputs!$C$35,D21*Inputs!$C$37*(Inputs!$C$35-D$5+0.5)/12,0) -> 0 | E23: =IF(E$5<=Inputs!$C$35,E21*Inputs!$C$37*(Inputs!$C$35-E$5+0.5)/12,0) -> 0 | F23: =IF(F$5<=Inputs!$C$35,F21*Inputs!$C$37*(Inputs!$C$35-F$5+0.5)/12,0) -> 0 | G23: =IF(G$5<=Inputs!$C$35,G21*Inputs!$C$37*(Inputs!$C$35-G$5+0.5)/12,0) -> 0.13858176 | H23: =IF(H$5<=Inputs!$C$35,H21*Inputs!$C$37*(Inputs!$C$35-H$5+0.5)/12,0) -> 0 | I23: =IF(I$5<=Inputs!$C$35,I21*Inputs!$C$37*(Inputs!$C$35-I$5+0.5)/12,0) -> 0 | J23: =IF(J$5<=Inputs!$C$35,J21*Inputs!$C$37*(Inputs!$C$35-J$5+0.5)/12,0) -> 0 | K23: =IF(K$5<=Inputs!$C$35,K21*Inputs!$C$37*(Inputs!$C$35-K$5+0.5)/12,0) -> 0 | ... O23: =IF(O$5<=Inputs!$C$35,O21*Inputs!$C$37*(Inputs!$C$35-O$5+0.5)/12,0) -> 0 | P23: =SUM(D23:O23) -> 0.13858176
B25: Construction capex (₹ Cr) | C25: ='Sources & Uses'!$C$11 -> 80.13265
B26: Debt share of capex | C26: =MIN(Inputs!$C$52,'Sources & Uses'!$C$18/'Sources & Uses'!$C$11) -> 0.66795436
B27: Debt during construction (₹ Cr) | C27: =C25*C26 -> 53.524953
B29: Draw order | D29: IDC | E29: Cash carrying cost | F29: Total cost | G29: Equity-weighted month | H29: HoldCo cash by month 2
B30: 1. Equity first | D30: =P12 -> 0.35193466 | E30: =P13 -> 0.62442404 | F30: =D30+E30 -> 0.97635871 | G30: =IF(P11=0,0,SUMPRODUCT($D$5:$O$5,D11:O11)/P11) -> 2.2470915 | H30: =SUM(D11:E11) -> 16.02653
B31: 2. Pro-rata | D31: =P17 -> 0.58542917 | E31: =P18 -> 0.34645439 | F31: =D31+E31 -> 0.93188356 | G31: =IF(P16=0,0,SUMPRODUCT($D$5:$O$5,D16:O16)/P16) -> 3.25 | H31: =SUM(D16:E16) -> 5.3215394
B32: 3. Debt first | D32: =P22 -> 0.76004218 | E32: =P23 -> 0.13858176 | F32: =D32+E32 -> 0.89862394 | G32: =IF(P21=0,0,SUMPRODUCT($D$5:$O$5,D21:O21)/P21) -> 4 | H32: =SUM(D21:E21) -> 0
B34: Selected draw order (index) | C34: =IF(Inputs!$C$36=0,MATCH(MIN(F30:F32),F30:F32,0),Inputs!$C$36) -> 3
B35: Selected draw order | C35: =CHOOSE(C34,"Equity first","Pro-rata","Debt first") -> Debt first
B36: IDC as % of construction debt | C36: =IF($C$27=0,0,INDEX(D30:D32,C34)/$C$27) -> 0.014199773
B37: Equity-weighted draw month | C37: =INDEX(G30:G32,C34) -> 4
B38: Bridge outstanding in FC year (fraction of year) | C38: =MAX(0,(12-(Inputs!$C$8-1)-C37+0.5)/12) -> 0.45833333
B39: Lowest-cost draw order (for comparison) | C39: =CHOOSE(MATCH(MIN(F30:F32),F30:F32,0),"Equity first","Pro-rata","Debt first") -> Debt first
B42: SPV4 (P4)
B43: Construction month | D43: 1 | E43: 2 | F43: 3 | G43: 4 | H43: 5 | I43: 6 | J43: 7 | K43: 8 | L43: 9 | M43: 10 | N43: 11 | O43: 12 | P43: Total
B44: Capex draw profile (input) | D44: 0.05 | E44: 0.1 | F44: 0.15 | G44: 0.2 | H44: 0.25 | I44: 0.25 | J44: 0 | K44: 0 | L44: 0 | M44: 0 | N44: 0 | O44: 0 | P44: =SUM(D44:O44) -> 1
B45: Capex drawn (₹ Cr) | D45: =$C$63*D44 -> 8.013265 | E45: =$C$63*E44 -> 16.02653 | F45: =$C$63*F44 -> 24.039795 | G45: =$C$63*G44 -> 32.05306 | H45: =$C$63*H44 -> 40.066325 | I45: =$C$63*I44 -> 40.066325 | J45: =$C$63*J44 -> 0 | K45: =$C$63*K44 -> 0 | ... O45: =$C$63*O44 -> 0 | P45: =SUM(D45:O45) -> 160.2653
B46: Cumulative capex | D46: =D45 -> 8.013265 | E46: =D46+E45 -> 24.039795 | F46: =E46+F45 -> 48.07959 | G46: =F46+G45 -> 80.13265 | H46: =G46+H45 -> 120.19898 | I46: =H46+I45 -> 160.2653 | J46: =I46+J45 -> 160.2653 | K46: =J46+K45 -> 160.2653 | L46: =K46+L45 -> 160.2653 | ... O46: =N46+O45 -> 160.2653
B47: 1. Equity first — cumulative debt | D47: =MAX(0,D46-$C$63*(1-$C$64)) -> 0 | E47: =MAX(0,E46-$C$63*(1-$C$64)) -> 0 | F47: =MAX(0,F46-$C$63*(1-$C$64)) -> 0 | G47: =MAX(0,G46-$C$63*(1-$C$64)) -> 26.917256 | H47: =MAX(0,H46-$C$63*(1-$C$64)) -> 66.983581 | I47: =MAX(0,I46-$C$63*(1-$C$64)) -> 107.04991 | J47: =MAX(0,J46-$C$63*(1-$C$64)) -> 107.04991 | K47: =MAX(0,K46-$C$63*(1-$C$64)) -> 107.04991 | ... O47: =MAX(0,O46-$C$63*(1-$C$64)) -> 107.04991
B48: debt drawn | D48: =D47 -> 0 | E48: =E47-D47 -> 0 | F48: =F47-E47 -> 0 | G48: =G47-F47 -> 26.917256 | H48: =H47-G47 -> 40.066325 | I48: =I47-H47 -> 40.066325 | J48: =J47-I47 -> 0 | K48: =K47-J47 -> 0 | L48: =L47-K47 -> 0 | ... O48: =O47-N47 -> 0 | P48: =SUM(D48:O48) -> 107.04991
B49: HoldCo cash drawn | D49: =D45-D48 -> 8.013265 | E49: =E45-E48 -> 16.02653 | F49: =F45-F48 -> 24.039795 | G49: =G45-G48 -> 5.1358043 | H49: =H45-H48 -> 0 | I49: =I45-I48 -> 0 | J49: =J45-J48 -> 0 | K49: =K45-K48 -> 0 | ... O49: =O45-O48 -> 0 | P49: =SUM(D49:O49) -> 53.215394
B50: IDC | D50: =IF(D$43<=Inputs!$D$35,(0+D47)/2*Inputs!$D$51/12,0) -> 0 | E50: =IF(E$43<=Inputs!$D$35,(D47+E47)/2*Inputs!$D$51/12,0) -> 0 | F50: =IF(F$43<=Inputs!$D$35,(E47+F47)/2*Inputs!$D$51/12,0) -> 0 | G50: =IF(G$43<=Inputs!$D$35,(F47+G47)/2*Inputs!$D$51/12,0) -> 0.11776299 | H50: =IF(H$43<=Inputs!$D$35,(G47+H47)/2*Inputs!$D$51/12,0) -> 0.41081616 | I50: =IF(I$43<=Inputs!$D$35,(H47+I47)/2*Inputs!$D$51/12,0) -> 0.7613965 | J50: =IF(J$43<=Inputs!$D$35,(I47+J47)/2*Inputs!$D$51/12,0) -> 0 | K50: =IF(K$43<=Inputs!$D$35,(J47+K47)/2*Inputs!$D$51/12,0) -> 0 | L50: =IF(L$43<=Inputs!$D$35,(K47+L47)/2*Inputs!$D$51/12,0) -> 0 | ... O50: =IF(O$43<=Inputs!$D$35,(N47+O47)/2*Inputs!$D$51/12,0) -> 0 | P50: =SUM(D50:O50) -> 1.2899757
B51: carrying cost of HoldCo cash to COD | D51: =IF(D$43<=Inputs!$D$35,D49*Inputs!$D$37*(Inputs!$D$35-D$43+0.5)/12,0) -> 0.23872852 | E51: =IF(E$43<=Inputs!$D$35,E49*Inputs!$D$37*(Inputs!$D$35-E$43+0.5)/12,0) -> 0.39064667 | F51: =IF(F$43<=Inputs!$D$35,F49*Inputs!$D$37*(Inputs!$D$35-F$43+0.5)/12,0) -> 0.45575445 | G51: =IF(G$43<=Inputs!$D$35,G49*Inputs!$D$37*(Inputs!$D$35-G$43+0.5)/12,0) -> 0.06954735 | H51: =IF(H$43<=Inputs!$D$35,H49*Inputs!$D$37*(Inputs!$D$35-H$43+0.5)/12,0) -> 0 | I51: =IF(I$43<=Inputs!$D$35,I49*Inputs!$D$37*(Inputs!$D$35-I$43+0.5)/12,0) -> 0 | J51: =IF(J$43<=Inputs!$D$35,J49*Inputs!$D$37*(Inputs!$D$35-J$43+0.5)/12,0) -> 0 | K51: =IF(K$43<=Inputs!$D$35,K49*Inputs!$D$37*(Inputs!$D$35-K$43+0.5)/12,0) -> 0 | ... O51: =IF(O$43<=Inputs!$D$35,O49*Inputs!$D$37*(Inputs!$D$35-O$43+0.5)/12,0) -> 0 | P51: =SUM(D51:O51) -> 1.154677
B52: 2. Pro-rata — cumulative debt | D52: =D46*$C$64 -> 5.3524953 | E52: =E46*$C$64 -> 16.057486 | F52: =F46*$C$64 -> 32.114972 | G52: =G46*$C$64 -> 53.524953 | H52: =H46*$C$64 -> 80.287429 | I52: =I46*$C$64 -> 107.04991 | J52: =J46*$C$64 -> 107.04991 | K52: =K46*$C$64 -> 107.04991 | ... O52: =O46*$C$64 -> 107.04991
B53: debt drawn | D53: =D52 -> 5.3524953 | E53: =E52-D52 -> 10.704991 | F53: =F52-E52 -> 16.057486 | G53: =G52-F52 -> 21.409981 | H53: =H52-G52 -> 26.762476 | I53: =I52-H52 -> 26.762476 | J53: =J52-I52 -> 0 | K53: =K52-J52 -> 0 | L53: =L52-K52 -> 0 | ... O53: =O52-N52 -> 0 | P53: =SUM(D53:O53) -> 107.04991
B54: HoldCo cash drawn | D54: =D45-D53 -> 2.6607697 | E54: =E45-E53 -> 5.3215394 | F54: =F45-F53 -> 7.9823091 | G54: =G45-G53 -> 10.643079 | H54: =H45-H53 -> 13.303849 | I54: =I45-I53 -> 13.303849 | J54: =J45-J53 -> 0 | K54: =K45-K53 -> 0 | ... O54: =O45-O53 -> 0 | P54: =SUM(D54:O54) -> 53.215394
B55: IDC | D55: =IF(D$43<=Inputs!$D$35,(0+D52)/2*Inputs!$D$51/12,0) -> 0.023417167 | E55: =IF(E$43<=Inputs!$D$35,(D52+E52)/2*Inputs!$D$51/12,0) -> 0.093668667 | F55: =IF(F$43<=Inputs!$D$35,(E52+F52)/2*Inputs!$D$51/12,0) -> 0.2107545 | G55: =IF(G$43<=Inputs!$D$35,(F52+G52)/2*Inputs!$D$51/12,0) -> 0.37467467 | H55: =IF(H$43<=Inputs!$D$35,(G52+H52)/2*Inputs!$D$51/12,0) -> 0.58542917 | I55: =IF(I$43<=Inputs!$D$35,(H52+I52)/2*Inputs!$D$51/12,0) -> 0.81960084 | J55: =IF(J$43<=Inputs!$D$35,(I52+J52)/2*Inputs!$D$51/12,0) -> 0 | K55: =IF(K$43<=Inputs!$D$35,(J52+K52)/2*Inputs!$D$51/12,0) -> 0 | L55: =IF(L$43<=Inputs!$D$35,(K52+L52)/2*Inputs!$D$51/12,0) -> 0 | ... O55: =IF(O$43<=Inputs!$D$35,(N52+O52)/2*Inputs!$D$51/12,0) -> 0 | P55: =SUM(D55:O55) -> 2.107545
B56: carrying cost of HoldCo cash to COD | D56: =IF(D$43<=Inputs!$D$35,D54*Inputs!$D$37*(Inputs!$D$35-D$43+0.5)/12,0) -> 0.079268764 | E56: =IF(E$43<=Inputs!$D$35,E54*Inputs!$D$37*(Inputs!$D$35-E$43+0.5)/12,0) -> 0.12971252 | F56: =IF(F$43<=Inputs!$D$35,F54*Inputs!$D$37*(Inputs!$D$35-F$43+0.5)/12,0) -> 0.15133128 | G56: =IF(G$43<=Inputs!$D$35,G54*Inputs!$D$37*(Inputs!$D$35-G$43+0.5)/12,0) -> 0.14412503 | H56: =IF(H$43<=Inputs!$D$35,H54*Inputs!$D$37*(Inputs!$D$35-H$43+0.5)/12,0) -> 0.10809377 | I56: =IF(I$43<=Inputs!$D$35,I54*Inputs!$D$37*(Inputs!$D$35-I$43+0.5)/12,0) -> 0.036031257 | J56: =IF(J$43<=Inputs!$D$35,J54*Inputs!$D$37*(Inputs!$D$35-J$43+0.5)/12,0) -> 0 | K56: =IF(K$43<=Inputs!$D$35,K54*Inputs!$D$37*(Inputs!$D$35-K$43+0.5)/12,0) -> 0 | ... O56: =IF(O$43<=Inputs!$D$35,O54*Inputs!$D$37*(Inputs!$D$35-O$43+0.5)/12,0) -> 0 | P56: =SUM(D56:O56) -> 0.64856262
B57: 3. Debt first — cumulative debt | D57: =MIN(D46,$C$65) -> 8.013265 | E57: =MIN(E46,$C$65) -> 24.039795 | F57: =MIN(F46,$C$65) -> 48.07959 | G57: =MIN(G46,$C$65) -> 80.13265 | H57: =MIN(H46,$C$65) -> 107.04991 | I57: =MIN(I46,$C$65) -> 107.04991 | J57: =MIN(J46,$C$65) -> 107.04991 | K57: =MIN(K46,$C$65) -> 107.04991 | ... O57: =MIN(O46,$C$65) -> 107.04991
B58: debt drawn | D58: =D57 -> 8.013265 | E58: =E57-D57 -> 16.02653 | F58: =F57-E57 -> 24.039795 | G58: =G57-F57 -> 32.05306 | H58: =H57-G57 -> 26.917256 | I58: =I57-H57 -> 0 | J58: =J57-I57 -> 0 | K58: =K57-J57 -> 0 | L58: =L57-K57 -> 0 | ... O58: =O57-N57 -> 0 | P58: =SUM(D58:O58) -> 107.04991
B59: HoldCo cash drawn | D59: =D45-D58 -> 0 | E59: =E45-E58 -> 0 | F59: =F45-F58 -> 0 | G59: =G45-G58 -> 0 | H59: =H45-H58 -> 13.149069 | I59: =I45-I58 -> 40.066325 | J59: =J45-J58 -> 0 | K59: =K45-K58 -> 0 | ... O59: =O45-O58 -> 0 | P59: =SUM(D59:O59) -> 53.215394
B60: IDC | D60: =IF(D$43<=Inputs!$D$35,(0+D57)/2*Inputs!$D$51/12,0) -> 0.035058034 | E60: =IF(E$43<=Inputs!$D$35,(D57+E57)/2*Inputs!$D$51/12,0) -> 0.14023214 | F60: =IF(F$43<=Inputs!$D$35,(E57+F57)/2*Inputs!$D$51/12,0) -> 0.31552231 | G60: =IF(G$43<=Inputs!$D$35,(F57+G57)/2*Inputs!$D$51/12,0) -> 0.56092855 | H60: =IF(H$43<=Inputs!$D$35,(G57+H57)/2*Inputs!$D$51/12,0) -> 0.81892368 | I60: =IF(I$43<=Inputs!$D$35,(H57+I57)/2*Inputs!$D$51/12,0) -> 0.93668667 | J60: =IF(J$43<=Inputs!$D$35,(I57+J57)/2*Inputs!$D$51/12,0) -> 0 | K60: =IF(K$43<=Inputs!$D$35,(J57+K57)/2*Inputs!$D$51/12,0) -> 0 | L60: =IF(L$43<=Inputs!$D$35,(K57+L57)/2*Inputs!$D$51/12,0) -> 0 | ... O60: =IF(O$43<=Inputs!$D$35,(N57+O57)/2*Inputs!$D$51/12,0) -> 0 | P60: =SUM(D60:O60) -> 2.8073514
B61: carrying cost of HoldCo cash to COD | D61: =IF(D$43<=Inputs!$D$35,D59*Inputs!$D$37*(Inputs!$D$35-D$43+0.5)/12,0) -> 0 | E61: =IF(E$43<=Inputs!$D$35,E59*Inputs!$D$37*(Inputs!$D$35-E$43+0.5)/12,0) -> 0 | F61: =IF(F$43<=Inputs!$D$35,F59*Inputs!$D$37*(Inputs!$D$35-F$43+0.5)/12,0) -> 0 | G61: =IF(G$43<=Inputs!$D$35,G59*Inputs!$D$37*(Inputs!$D$35-G$43+0.5)/12,0) -> 0 | H61: =IF(H$43<=Inputs!$D$35,H59*Inputs!$D$37*(Inputs!$D$35-H$43+0.5)/12,0) -> 0.10683619 | I61: =IF(I$43<=Inputs!$D$35,I59*Inputs!$D$37*(Inputs!$D$35-I$43+0.5)/12,0) -> 0.10851296 | J61: =IF(J$43<=Inputs!$D$35,J59*Inputs!$D$37*(Inputs!$D$35-J$43+0.5)/12,0) -> 0 | K61: =IF(K$43<=Inputs!$D$35,K59*Inputs!$D$37*(Inputs!$D$35-K$43+0.5)/12,0) -> 0 | ... O61: =IF(O$43<=Inputs!$D$35,O59*Inputs!$D$37*(Inputs!$D$35-O$43+0.5)/12,0) -> 0 | P61: =SUM(D61:O61) -> 0.21534915
B63: Construction capex (₹ Cr) | C63: ='Sources & Uses'!$D$11 -> 160.2653
B64: Debt share of capex | C64: =MIN(Inputs!$D$52,'Sources & Uses'!$D$18/'Sources & Uses'!$D$11) -> 0.66795436
B65: Debt during construction (₹ Cr) | C65: =C63*C64 -> 107.04991
B67: Draw order | D67: IDC | E67: Cash carrying cost | F67: Total cost | G67: Equity-weighted month | H67: HoldCo cash by month 2
B68: 1. Equity first | D68: =P50 -> 1.2899757 | E68: =P51 -> 1.154677 | F68: =D68+E68 -> 2.4446526 | G68: =IF(P49=0,0,SUMPRODUCT($D$43:$O$43,D49:O49)/P49) -> 2.4941829 | H68: =SUM(D49:E49) -> 24.039795
B69: 2. Pro-rata | D69: =P55 -> 2.107545 | E69: =P56 -> 0.64856262 | F69: =D69+E69 -> 2.7561076 | G69: =IF(P54=0,0,SUMPRODUCT($D$43:$O$43,D54:O54)/P54) -> 4.25 | H69: =SUM(D54:E54) -> 7.9823091
B70: 3. Debt first | D70: =P60 -> 2.8073514 | E70: =P61 -> 0.21534915 | F70: =D70+E70 -> 3.0227005 | G70: =IF(P59=0,0,SUMPRODUCT($D$43:$O$43,D59:O59)/P59) -> 5.7529085 | H70: =SUM(D59:E59) -> 0
B72: Selected draw order (index) | C72: =IF(Inputs!$D$36=0,MATCH(MIN(F68:F70),F68:F70,0),Inputs!$D$36) -> 1
B73: Selected draw order | C73: =CHOOSE(C72,"Equity first","Pro-rata","Debt first") -> Equity first
B74: IDC as % of construction debt | C74: =IF($C$65=0,0,INDEX(D68:D70,C72)/$C$65) -> 0.012050227
B75: Equity-weighted draw month | C75: =INDEX(G68:G70,C72) -> 2.4941829
B76: Bridge outstanding in FC year (fraction of year) | C76: =MAX(0,(12-(Inputs!$D$8-1)-C75+0.5)/12) -> 0.58381809
B77: Lowest-cost draw order (for comparison) | C77: =CHOOSE(MATCH(MIN(F68:F70),F68:F70,0),"Equity first","Pro-rata","Debt first") -> Equity first
B80: Lenders normally require equity in first or alongside. Debt first for P3 needs an equity bridge, a contingent-equity LC or a sponsor guarantee that the equity will come.

Sheet SPV3
B1: SPV3 (P3) — Annual operations, senior debt and cash to HoldCo
B2: Year 0 is the construction FY (debt drawn at COD, stub months of operation). Columns E:AD = years 0–25. Column D = total or key result.
B4: Timeline
B5: Year index (0 = construction FY) | D5: Total / result | E5: 0 | F5: =E5+1 -> 1 | G5: =F5+1 -> 2 | H5: =G5+1 -> 3 | I5: =H5+1 -> 4 | J5: =I5+1 -> 5 | K5: =J5+1 -> 6 | L5: =K5+1 -> 7 | M5: =L5+1 -> 8 | ... AD5: =AC5+1 -> 25
B6: Financial year | E6: =Inputs!$C$7+E5 -> 2028 | F6: =Inputs!$C$7+F5 -> 2029 | G6: =Inputs!$C$7+G5 -> 2030 | H6: =Inputs!$C$7+H5 -> 2031 | I6: =Inputs!$C$7+I5 -> 2032 | J6: =Inputs!$C$7+J5 -> 2033 | K6: =Inputs!$C$7+K5 -> 2034 | L6: =Inputs!$C$7+L5 -> 2035 | ... AD6: =Inputs!$C$7+AD5 -> 2053
B7: Operating fraction of year | E7: =IF(E5=0,Inputs!$C$9/12,IF(E5<Inputs!$C$17,1,IF(E5=Inputs!$C$17,1-Inputs!$C$9/12,0))) -> 0.41666667 | F7: =IF(F5=0,Inputs!$C$9/12,IF(F5<Inputs!$C$17,1,IF(F5=Inputs!$C$17,1-Inputs!$C$9/12,0))) -> 1 | G7: =IF(G5=0,Inputs!$C$9/12,IF(G5<Inputs!$C$17,1,IF(G5=Inputs!$C$17,1-Inputs!$C$9/12,0))) -> 1 | H7: =IF(H5=0,Inputs!$C$9/12,IF(H5<Inputs!$C$17,1,IF(H5=Inputs!$C$17,1-Inputs!$C$9/12,0))) -> 1 | I7: =IF(I5=0,Inputs!$C$9/12,IF(I5<Inputs!$C$17,1,IF(I5=Inputs!$C$17,1-Inputs!$C$9/12,0))) -> 1 | J7: =IF(J5=0,Inputs!$C$9/12,IF(J5<Inputs!$C$17,1,IF(J5=Inputs!$C$17,1-Inputs!$C$9/12,0))) -> 1 | K7: =IF(K5=0,Inputs!$C$9/12,IF(K5<Inputs!$C$17,1,IF(K5=Inputs!$C$17,1-Inputs!$C$9/12,0))) -> 1 | L7: =IF(L5=0,Inputs!$C$9/12,IF(L5<Inputs!$C$17,1,IF(L5=Inputs!$C$17,1-Inputs!$C$9/12,0))) -> 1 | ... AD7: =IF(AD5=0,Inputs!$C$9/12,IF(AD5<Inputs!$C$17,1,IF(AD5=Inputs!$C$17,1-Inputs!$C$9/12,0))) -> 0.58333333
B8: Repayment flag | E8: =IF(AND(E5>=1,E5<=Inputs!$C$31),1,0) -> 0 | F8: =IF(AND(F5>=1,F5<=Inputs!$C$31),1,0) -> 1 | G8: =IF(AND(G5>=1,G5<=Inputs!$C$31),1,0) -> 1 | H8: =IF(AND(H5>=1,H5<=Inputs!$C$31),1,0) -> 1 | I8: =IF(AND(I5>=1,I5<=Inputs!$C$31),1,0) -> 1 | J8: =IF(AND(J5>=1,J5<=Inputs!$C$31),1,0) -> 1 | K8: =IF(AND(K5>=1,K5<=Inputs!$C$31),1,0) -> 1 | L8: =IF(AND(L5>=1,L5<=Inputs!$C$31),1,0) -> 1 | ... AD8: =IF(AND(AD5>=1,AD5<=Inputs!$C$31),1,0) -> 0
B9: Operations
B10: Degradation factor | E10: =(1-Inputs!$C$15)^MAX(0,E5-1) -> 1 | F10: =(1-Inputs!$C$15)^MAX(0,F5-1) -> 1 | G10: =(1-Inputs!$C$15)^MAX(0,G5-1) -> 0.996 | H10: =(1-Inputs!$C$15)^MAX(0,H5-1) -> 0.992016 | I10: =(1-Inputs!$C$15)^MAX(0,I5-1) -> 0.98804794 | J10: =(1-Inputs!$C$15)^MAX(0,J5-1) -> 0.98409574 | K10: =(1-Inputs!$C$15)^MAX(0,K5-1) -> 0.98015936 | L10: =(1-Inputs!$C$15)^MAX(0,L5-1) -> 0.97623872 | ... AD10: =(1-Inputs!$C$15)^MAX(0,AD5-1) -> 0.90828914
B11: Generation, P50 | C11: MWh | D11: =SUM(E11:AD11) -> 890508.28 | E11: =Inputs!$C$6*Inputs!$C$14*E10*E7 -> 15541.667 | F11: =Inputs!$C$6*Inputs!$C$14*F10*F7 -> 37300 | G11: =Inputs!$C$6*Inputs!$C$14*G10*G7 -> 37150.8 | H11: =Inputs!$C$6*Inputs!$C$14*H10*H7 -> 37002.197 | I11: =Inputs!$C$6*Inputs!$C$14*I10*I7 -> 36854.188 | J11: =Inputs!$C$6*Inputs!$C$14*J10*J7 -> 36706.771 | K11: =Inputs!$C$6*Inputs!$C$14*K10*K7 -> 36559.944 | L11: =Inputs!$C$6*Inputs!$C$14*L10*L7 -> 36413.704 | ... AD11: =Inputs!$C$6*Inputs!$C$14*AD10*AD7 -> 19762.858
B12: Generation, P90 | C12: MWh | D12: =SUM(E12:AD12) -> 833515.75 | E12: =E11*(1-Inputs!$C$39) -> 14547 | F12: =F11*(1-Inputs!$C$39) -> 34912.8 | G12: =G11*(1-Inputs!$C$39) -> 34773.149 | H12: =H11*(1-Inputs!$C$39) -> 34634.056 | I12: =I11*(1-Inputs!$C$39) -> 34495.52 | J12: =J11*(1-Inputs!$C$39) -> 34357.538 | K12: =K11*(1-Inputs!$C$39) -> 34220.108 | L12: =L11*(1-Inputs!$C$39) -> 34083.227 | ... AD12: =AD11*(1-Inputs!$C$39) -> 18498.035
B13: Revenue, P50 | C13: ₹ Cr | D13: =SUM(E13:AD13) -> 359.76535 | E13: =E11*Inputs!$C$16/10000 -> 6.2788333 | F13: =F11*Inputs!$C$16/10000 -> 15.0692 | G13: =G11*Inputs!$C$16/10000 -> 15.008923 | H13: =H11*Inputs!$C$16/10000 -> 14.948888 | I13: =I11*Inputs!$C$16/10000 -> 14.889092 | J13: =J11*Inputs!$C$16/10000 -> 14.829536 | K13: =K11*Inputs!$C$16/10000 -> 14.770217 | L13: =L11*Inputs!$C$16/10000 -> 14.711137 | ... AD13: =AD11*Inputs!$C$16/10000 -> 7.9841946
B14: Revenue, P90 | C14: ₹ Cr | D14: =SUM(E14:AD14) -> 336.74036 | E14: =E12*Inputs!$C$16/10000 -> 5.876988 | F14: =F12*Inputs!$C$16/10000 -> 14.104771 | G14: =G12*Inputs!$C$16/10000 -> 14.048352 | H14: =H12*Inputs!$C$16/10000 -> 13.992159 | I14: =I12*Inputs!$C$16/10000 -> 13.93619 | J14: =J12*Inputs!$C$16/10000 -> 13.880445 | K14: =K12*Inputs!$C$16/10000 -> 13.824924 | L14: =L12*Inputs!$C$16/10000 -> 13.769624 | ... AD14: =AD12*Inputs!$C$16/10000 -> 7.4732061
B15: Operating cost | C15: ₹ Cr | D15: =SUM(E15:AD15) -> 58.25 | E15: =Inputs!$C$6*Inputs!$C$18*(1+Inputs!$C$19)^MAX(0,E5-1)*E7/10000 -> 0.97083333 | F15: =Inputs!$C$6*Inputs!$C$18*(1+Inputs!$C$19)^MAX(0,F5-1)*F7/10000 -> 2.33 | G15: =Inputs!$C$6*Inputs!$C$18*(1+Inputs!$C$19)^MAX(0,G5-1)*G7/10000 -> 2.33 | H15: =Inputs!$C$6*Inputs!$C$18*(1+Inputs!$C$19)^MAX(0,H5-1)*H7/10000 -> 2.33 | I15: =Inputs!$C$6*Inputs!$C$18*(1+Inputs!$C$19)^MAX(0,I5-1)*I7/10000 -> 2.33 | J15: =Inputs!$C$6*Inputs!$C$18*(1+Inputs!$C$19)^MAX(0,J5-1)*J7/10000 -> 2.33 | K15: =Inputs!$C$6*Inputs!$C$18*(1+Inputs!$C$19)^MAX(0,K5-1)*K7/10000 -> 2.33 | L15: =Inputs!$C$6*Inputs!$C$18*(1+Inputs!$C$19)^MAX(0,L5-1)*L7/10000 -> 2.33 | ... AD15: =Inputs!$C$6*Inputs!$C$18*(1+Inputs!$C$19)^MAX(0,AD5-1)*AD7/10000 -> 1.3591667
B16: EBITDA, P50 (pre-tax CFADS) | C16: ₹ Cr | D16: =SUM(E16:AD16) -> 301.51535 | E16: =E13-E15 -> 5.308 | F16: =F13-F15 -> 12.7392 | G16: =G13-G15 -> 12.678923 | H16: =H13-H15 -> 12.618888 | I16: =I13-I15 -> 12.559092 | J16: =J13-J15 -> 12.499536 | K16: =K13-K15 -> 12.440217 | L16: =L13-L15 -> 12.381137 | ... AD16: =AD13-AD15 -> 6.6250279
B17: EBITDA, P90 (lender case) | C17: ₹ Cr | D17: =SUM(E17:AD17) -> 278.49036 | E17: =E14-E15 -> 4.9061547 | F17: =F14-F15 -> 11.774771 | G17: =G14-G15 -> 11.718352 | H17: =H14-H15 -> 11.662159 | I17: =I14-I15 -> 11.60619 | J17: =J14-J15 -> 11.550445 | K17: =K14-K15 -> 11.494924 | L17: =L14-L15 -> 11.439624 | ... AD17: =AD14-AD15 -> 6.1140395
B18: Debt sizing — debt first, sculpted to the target DSCR
B19: CFADS on the chosen sizing case | C19: ₹ Cr | E19: =IF(Inputs!$C$38=2,E17,E16)*E8 -> 0 | F19: =IF(Inputs!$C$38=2,F17,F16)*F8 -> 11.774771 | G19: =IF(Inputs!$C$38=2,G17,G16)*G8 -> 11.718352 | H19: =IF(Inputs!$C$38=2,H17,H16)*H8 -> 11.662159 | I19: =IF(Inputs!$C$38=2,I17,I16)*I8 -> 11.60619 | J19: =IF(Inputs!$C$38=2,J17,J16)*J8 -> 11.550445 | K19: =IF(Inputs!$C$38=2,K17,K16)*K8 -> 11.494924 | L19: =IF(Inputs!$C$38=2,L17,L16)*L8 -> 11.439624 | ... AD19: =IF(Inputs!$C$38=2,AD17,AD16)*AD8 -> 0
B20: Discount factor at the loan rate | E20: =IF(E8=1,1/(1+Inputs!$C$51)^E5,0) -> 0 | F20: =IF(F8=1,1/(1+Inputs!$C$51)^F5,0) -> 0.90497738 | G20: =IF(G8=1,1/(1+Inputs!$C$51)^G5,0) -> 0.81898405 | H20: =IF(H8=1,1/(1+Inputs!$C$51)^H5,0) -> 0.74116204 | I20: =IF(I8=1,1/(1+Inputs!$C$51)^I5,0) -> 0.67073487 | J20: =IF(J8=1,1/(1+Inputs!$C$51)^J5,0) -> 0.60699989 | K20: =IF(K8=1,1/(1+Inputs!$C$51)^K5,0) -> 0.54932116 | L20: =IF(L8=1,1/(1+Inputs!$C$51)^L5,0) -> 0.49712323 | ... AD20: =IF(AD8=1,1/(1+Inputs!$C$51)^AD5,0) -> 0
B21: PV of debt service capacity, P50 | C21: ₹ Cr | D21: =SUM(E21:AD21) -> 57.921895 | E21: =E16*E8/Inputs!$C$29*E20 -> 0 | F21: =F16*F8/Inputs!$C$29*F20 -> 8.8682214 | G21: =G16*G8/Inputs!$C$29*G20 -> 7.9875661 | H21: =H16*H8/Inputs!$C$29*H20 -> 7.1943387 | I21: =I16*I8/Inputs!$C$29*I20 -> 6.4798623 | J21: =J16*J8/Inputs!$C$29*J20 -> 5.8363205 | K21: =K16*K8/Inputs!$C$29*K20 -> 5.2566729 | L21: =L16*L8/Inputs!$C$29*L20 -> 4.7345773 | ... AD21: =AD16*AD8/Inputs!$C$29*AD20 -> 0
B22: PV of debt service capacity, P90 | C22: ₹ Cr | D22: =SUM(E22:AD22) -> 53.524953 | E22: =E17*E8/Inputs!$C$29*E20 -> 0 | F22: =F17*F8/Inputs!$C$29*F20 -> 8.1968473 | G22: =G17*G8/Inputs!$C$29*G20 -> 7.3824181 | H22: =H17*H8/Inputs!$C$29*H20 -> 6.6488841 | I22: =I17*I8/Inputs!$C$29*I20 -> 5.9882126 | J22: =J17*J8/Inputs!$C$29*J20 -> 5.3931685 | K22: =K17*K8/Inputs!$C$29*K20 -> 4.8572344 | L22: =L17*L8/Inputs!$C$29*L20 -> 4.3745405 | ... AD22: =AD17*AD8/Inputs!$C$29*AD20 -> 0
B23: Scheduled debt service (sculpted) | C23: ₹ Cr | D23: =SUM(E23:AD23) -> 88.642881 | E23: =IF('Sources & Uses'!$C$18>0,E19/Inputs!$C$29*'Sources & Uses'!$C$19/'Sources & Uses'!$C$18,0) -> 0 | F23: =IF('Sources & Uses'!$C$18>0,F19/Inputs!$C$29*'Sources & Uses'!$C$19/'Sources & Uses'!$C$18,0) -> 9.0575163 | G23: =IF('Sources & Uses'!$C$18>0,G19/Inputs!$C$29*'Sources & Uses'!$C$19/'Sources & Uses'!$C$18,0) -> 9.014117 | H23: =IF('Sources & Uses'!$C$18>0,H19/Inputs!$C$29*'Sources & Uses'!$C$19/'Sources & Uses'!$C$18,0) -> 8.9708913 | I23: =IF('Sources & Uses'!$C$18>0,I19/Inputs!$C$29*'Sources & Uses'!$C$19/'Sources & Uses'!$C$18,0) -> 8.9278385 | J23: =IF('Sources & Uses'!$C$18>0,J19/Inputs!$C$29*'Sources & Uses'!$C$19/'Sources & Uses'!$C$18,0) -> 8.8849579 | K23: =IF('Sources & Uses'!$C$18>0,K19/Inputs!$C$29*'Sources & Uses'!$C$19/'Sources & Uses'!$C$18,0) -> 8.8422489 | L23: =IF('Sources & Uses'!$C$18>0,L19/Inputs!$C$29*'Sources & Uses'!$C$19/'Sources & Uses'!$C$18,0) -> 8.7997106 | ... AD23: =IF('Sources & Uses'!$C$18>0,AD19/Inputs!$C$29*'Sources & Uses'!$C$19/'Sources & Uses'!$C$18,0) -> 0
B24: Senior debt
B25: Opening balance | C25: ₹ Cr | E25: 0 | F25: =E29 -> 53.524953 | G25: =F29 -> 50.087557 | H25: =G29 -> 46.332633 | I25: =H29 -> 42.226668 | J25: =I29 -> 37.73263 | K25: =J29 -> 32.809598 | L25: =K29 -> 27.412357 | M25: =L29 -> 21.490944 | ... AD25: =AC29 -> 0
B26: Drawdown | C26: ₹ Cr | D26: =SUM(E26:AD26) -> 53.524953 | E26: ='Sources & Uses'!$C$19 -> 53.524953 | F26: 0 | G26: 0 | H26: 0 | I26: 0 | J26: 0 | K26: 0 | L26: 0 | M26: 0 | N26: 0 | O26: 0 | P26: 0 | Q26: 0 | R26: 0 | S26: 0 | T26: 0 | U26: 0 | V26: 0 | W26: 0 | X26: 0 | Y26: 0 | Z26: 0 | AA26: 0 | AB26: 0 | AC26: 0 | AD26: 0
B27: Interest (post-COD) | C27: ₹ Cr | D27: =SUM(E27:AD27) -> 37.459645 | E27: ='Sources & Uses'!$C$19*Inputs!$C$51*Inputs!$C$9/12 -> 2.3417167 | F27: =F25*Inputs!$C$51 -> 5.62012 | G27: =G25*Inputs!$C$51 -> 5.2591934 | H27: =H25*Inputs!$C$51 -> 4.8649265 | I27: =I25*Inputs!$C$51 -> 4.4338002 | J27: =J25*Inputs!$C$51 -> 3.9619261 | K27: =K25*Inputs!$C$51 -> 3.4450078 | L27: =L25*Inputs!$C$51 -> 2.8782975 | M27: =M25*Inputs!$C$51 -> 2.2565491 | ... AD27: =AD25*Inputs!$C$51 -> 0
B28: Principal repayment | C28: ₹ Cr | D28: =SUM(E28:AD28) -> 53.524953 | E28: =IF(E5=Inputs!$C$31,E25,MIN(E25,MAX(0,E23-E27))*E8) -> 0 | F28: =IF(F5=Inputs!$C$31,F25,MIN(F25,MAX(0,F23-F27))*F8) -> 3.4373963 | G28: =IF(G5=Inputs!$C$31,G25,MIN(G25,MAX(0,G23-G27))*G8) -> 3.7549236 | H28: =IF(H5=Inputs!$C$31,H25,MIN(H25,MAX(0,H23-H27))*H8) -> 4.1059648 | I28: =IF(I5=Inputs!$C$31,I25,MIN(I25,MAX(0,I23-I27))*I8) -> 4.4940384 | J28: =IF(J5=Inputs!$C$31,J25,MIN(J25,MAX(0,J23-J27))*J8) -> 4.9230318 | K28: =IF(K5=Inputs!$C$31,K25,MIN(K25,MAX(0,K23-K27))*K8) -> 5.3972411 | L28: =IF(L5=Inputs!$C$31,L25,MIN(L25,MAX(0,L23-L27))*L8) -> 5.9214132 | ... AD28: =IF(AD5=Inputs!$C$31,AD25,MIN(AD25,MAX(0,AD23-AD27))*AD8) -> 0
B29: Closing balance | C29: ₹ Cr | D29: =AD29 -> 0 | E29: =E25+E26-E28 -> 53.524953 | F29: =F25+F26-F28 -> 50.087557 | G29: =G25+G26-G28 -> 46.332633 | H29: =H25+H26-H28 -> 42.226668 | I29: =I25+I26-I28 -> 37.73263 | J29: =J25+J26-J28 -> 32.809598 | K29: =K25+K26-K28 -> 27.412357 | L29: =L25+L26-L28 -> 21.490944 | ... AD29: =AD25+AD26-AD28 -> 0
B30: Senior debt service | C30: ₹ Cr | D30: =SUM(E30:AD30) -> 90.984598 | E30: =E27+E28 -> 2.3417167 | F30: =F27+F28 -> 9.0575163 | G30: =G27+G28 -> 9.014117 | H30: =H27+H28 -> 8.9708913 | I30: =I27+I28 -> 8.9278385 | J30: =J27+J28 -> 8.8849579 | K30: =K27+K28 -> 8.8422489 | L30: =L27+L28 -> 8.7997106 | ... AD30: =AD27+AD28 -> 0
B31: DSCR, P50 (pre-tax) | C31: x | D31: =MIN(E31:AD31) -> 1.4064783 | E31: =IF(E8=1,E16/E30,"") | F31: =IF(F8=1,F16/F30,"") -> 1.4064783 | G31: =IF(G8=1,G16/G30,"") -> 1.406563 | H31: =IF(H8=1,H16/H30,"") -> 1.4066481 | I31: =IF(I8=1,I16/I30,"") -> 1.4067338 | J31: =IF(J8=1,J16/J30,"") -> 1.4068199 | K31: =IF(K8=1,K16/K30,"") -> 1.4069065 | L31: =IF(L8=1,L16/L30,"") -> 1.4069936 | ... AD31: =IF(AD8=1,AD16/AD30,"")
B32: DSCR, P90 (pre-tax) | C32: x | D32: =MIN(E32:AD32) -> 1.3 | E32: =IF(E8=1,E17/E30,"") | F32: =IF(F8=1,F17/F30,"") -> 1.3 | G32: =IF(G8=1,G17/G30,"") -> 1.3 | H32: =IF(H8=1,H17/H30,"") -> 1.3 | I32: =IF(I8=1,I17/I30,"") -> 1.3 | J32: =IF(J8=1,J17/J30,"") -> 1.3 | K32: =IF(K8=1,K17/K30,"") -> 1.3 | L32: =IF(L8=1,L17/L30,"") -> 1.3 | ... AD32: =IF(AD8=1,AD17/AD30,"")
B33: DSCR, P50 (post-tax) | C33: x | D33: =MIN(E33:AD33) -> 1.4064783 | E33: =IF(E8=1,(E16-E46)/E30,"") | F33: =IF(F8=1,(F16-F46)/F30,"") -> 1.4064783 | G33: =IF(G8=1,(G16-G46)/G30,"") -> 1.406563 | H33: =IF(H8=1,(H16-H46)/H30,"") -> 1.4066481 | I33: =IF(I8=1,(I16-I46)/I30,"") -> 1.4067338 | J33: =IF(J8=1,(J16-J46)/J30,"") -> 1.4068199 | K33: =IF(K8=1,(K16-K46)/K30,"") -> 1.4069065 | L33: =IF(L8=1,(L16-L46)/L30,"") -> 1.4069936 | ... AD33: =IF(AD8=1,(AD16-AD46)/AD30,"")
B34: Depreciation and tax
B35: Book value, opening | C35: ₹ Cr | E35: ='Sources & Uses'!$C$43 -> 85.809918 | F35: =E37 -> 82.592047 | G35: =F37 -> 74.869154 | H35: =G37 -> 67.146261 | I35: =H37 -> 59.423369 | J35: =I37 -> 51.700476 | K35: =J37 -> 46.98093 | L35: =K37 -> 42.261385 | M35: =L37 -> 37.541839 | ... AD35: =AC37 -> 0
B36: Book depreciation | C36: ₹ Cr | D36: =SUM(E36:AD36) -> 85.809918 | E36: =MIN(E35,'Sources & Uses'!$C$43*IF(E5<=4,Inputs!$C$22,Inputs!$C$23)*E7) -> 3.2178719 | F36: =MIN(F35,'Sources & Uses'!$C$43*IF(F5<=4,Inputs!$C$22,Inputs!$C$23)*F7) -> 7.7228927 | G36: =MIN(G35,'Sources & Uses'!$C$43*IF(G5<=4,Inputs!$C$22,Inputs!$C$23)*G7) -> 7.7228927 | H36: =MIN(H35,'Sources & Uses'!$C$43*IF(H5<=4,Inputs!$C$22,Inputs!$C$23)*H7) -> 7.7228927 | I36: =MIN(I35,'Sources & Uses'!$C$43*IF(I5<=4,Inputs!$C$22,Inputs!$C$23)*I7) -> 7.7228927 | J36: =MIN(J35,'Sources & Uses'!$C$43*IF(J5<=4,Inputs!$C$22,Inputs!$C$23)*J7) -> 4.7195455 | K36: =MIN(K35,'Sources & Uses'!$C$43*IF(K5<=4,Inputs!$C$22,Inputs!$C$23)*K7) -> 4.7195455 | L36: =MIN(L35,'Sources & Uses'!$C$43*IF(L5<=4,Inputs!$C$22,Inputs!$C$23)*L7) -> 4.7195455 | ... AD36: =MIN(AD35,'Sources & Uses'!$C$43*IF(AD5<=4,Inputs!$C$22,Inputs!$C$23)*AD7) -> 0
B37: Book value, closing | C37: ₹ Cr | E37: =E35-E36 -> 82.592047 | F37: =F35-F36 -> 74.869154 | G37: =G35-G36 -> 67.146261 | H37: =H35-H36 -> 59.423369 | I37: =I35-I36 -> 51.700476 | J37: =J35-J36 -> 46.98093 | K37: =K35-K36 -> 42.261385 | L37: =L35-L36 -> 37.541839 | ... AD37: =AD35-AD36 -> 0
B38: Tax WDV, opening (incl. inverter replacement, added to the block) | C38: ₹ Cr | E38: ='Sources & Uses'!$C$43 -> 85.809918 | F38: =E40+E49 -> 68.647935 | G38: =F40+F49 -> 41.188761 | H38: =G40+G49 -> 24.713257 | I38: =H40+H49 -> 14.827954 | J38: =I40+I49 -> 8.8967723 | K38: =J40+J49 -> 5.3380634 | L38: =K40+K49 -> 3.202838 | M38: =L40+L49 -> 1.9217028 | ... AD38: =AC40+AC49 -> 0.013135644
B39: Tax depreciation | C39: ₹ Cr | D39: =SUM(E39:AD39) -> 91.687037 | E39: =E38*Inputs!$C$24*IF(Inputs!$C$9<6,0.5,1)*IF(Inputs!$C$9>0,1,0) -> 17.161984 | F39: =F38*Inputs!$C$24*IF(F7>0,1,0) -> 27.459174 | G39: =G38*Inputs!$C$24*IF(G7>0,1,0) -> 16.475504 | H39: =H38*Inputs!$C$24*IF(H7>0,1,0) -> 9.8853026 | I39: =I38*Inputs!$C$24*IF(I7>0,1,0) -> 5.9311816 | J39: =J38*Inputs!$C$24*IF(J7>0,1,0) -> 3.5587089 | K39: =K38*Inputs!$C$24*IF(K7>0,1,0) -> 2.1352254 | L39: =L38*Inputs!$C$24*IF(L7>0,1,0) -> 1.2811352 | M39: =M38*Inputs!$C$24*IF(M7>0,1,0) -> 0.76868113 | ... AD39: =AD38*Inputs!$C$24*IF(AD7>0,1,0) -> 0.0052542577
B40: Tax WDV, closing | C40: ₹ Cr | E40: =E38-E39 -> 68.647935 | F40: =F38-F39 -> 41.188761 | G40: =G38-G39 -> 24.713257 | H40: =H38-H39 -> 14.827954 | I40: =I38-I39 -> 8.8967723 | J40: =J38-J39 -> 5.3380634 | K40: =K38-K39 -> 3.202838 | L40: =L38-L39 -> 1.9217028 | ... AD40: =AD38-AD39 -> 0.0078813865
B41: LC fee (if DSRA is an LC) | C41: ₹ Cr | D41: =SUM(E41:AD41) -> 0 | E41: =IF(Inputs!$C$41=2,Inputs!$C$42*Inputs!$C$40/12*F30,0) -> 0 | F41: =IF(Inputs!$C$41=2,Inputs!$C$42*Inputs!$C$40/12*G30,0) -> 0 | G41: =IF(Inputs!$C$41=2,Inputs!$C$42*Inputs!$C$40/12*H30,0) -> 0 | H41: =IF(Inputs!$C$41=2,Inputs!$C$42*Inputs!$C$40/12*I30,0) -> 0 | I41: =IF(Inputs!$C$41=2,Inputs!$C$42*Inputs!$C$40/12*J30,0) -> 0 | J41: =IF(Inputs!$C$41=2,Inputs!$C$42*Inputs!$C$40/12*K30,0) -> 0 | K41: =IF(Inputs!$C$41=2,Inputs!$C$42*Inputs!$C$40/12*L30,0) -> 0 | L41: =IF(Inputs!$C$41=2,Inputs!$C$42*Inputs!$C$40/12*M30,0) -> 0 | ... AC41: =IF(Inputs!$C$41=2,Inputs!$C$42*Inputs!$C$40/12*AD30,0) -> 0 | AD41: 0
B42: Taxable income before losses | C42: ₹ Cr | E42: =E16-E39-E27-E64-E41 -> -15.518724 | F42: =F16-F39-F27-F64-F41 -> -23.385453 | G42: =G16-G39-G27-G64-G41 -> -12.209668 | H42: =H16-H39-H27-H64-H41 -> -5.285235 | I42: =I16-I39-I27-I64-I41 -> -0.95978316 | J42: =J16-J39-J27-J64-J41 -> 1.8250071 | K42: =K16-K39-K27-K64-K41 -> 3.7060909 | L42: =L16-L39-L27-L64-L41 -> 5.0678105 | ... AD42: =AD16-AD39-AD27-AD64-AD41 -> 6.6197737
B43: Tax losses brought forward | C43: ₹ Cr | E43: 0 | F43: =E45 -> 15.518724 | G43: =F45 -> 38.904177 | H43: =G45 -> 51.113845 | I43: =H45 -> 56.39908 | J43: =I45 -> 57.358863 | K43: =J45 -> 55.533856 | L43: =K45 -> 51.827765 | M43: =L45 -> 46.759955 | ... AD43: =AC45 -> 0
B44: Losses used | C44: ₹ Cr | E44: =IF(E42>0,MIN(E43,E42),0) -> 0 | F44: =IF(F42>0,MIN(F43,F42),0) -> 0 | G44: =IF(G42>0,MIN(G43,G42),0) -> 0 | H44: =IF(H42>0,MIN(H43,H42),0) -> 0 | I44: =IF(I42>0,MIN(I43,I42),0) -> 0 | J44: =IF(J42>0,MIN(J43,J42),0) -> 1.8250071 | K44: =IF(K42>0,MIN(K43,K42),0) -> 3.7060909 | L44: =IF(L42>0,MIN(L43,L42),0) -> 5.0678105 | ... AD44: =IF(AD42>0,MIN(AD43,AD42),0) -> 0
B45: Tax losses carried forward | C45: ₹ Cr | E45: =E43-E44+MAX(0,-E42) -> 15.518724 | F45: =F43-F44+MAX(0,-F42) -> 38.904177 | G45: =G43-G44+MAX(0,-G42) -> 51.113845 | H45: =H43-H44+MAX(0,-H42) -> 56.39908 | I45: =I43-I44+MAX(0,-I42) -> 57.358863 | J45: =J43-J44+MAX(0,-J42) -> 55.533856 | K45: =K43-K44+MAX(0,-K42) -> 51.827765 | L45: =L43-L44+MAX(0,-L42) -> 46.759955 | ... AD45: =AD43-AD44+MAX(0,-AD42) -> 0
B46: Tax paid | C46: ₹ Cr | D46: =SUM(E46:AD46) -> 35.138364 | E46: =MAX(0,E42-E44)*Inputs!$C$25 -> 0 | F46: =MAX(0,F42-F44)*Inputs!$C$25 -> 0 | G46: =MAX(0,G42-G44)*Inputs!$C$25 -> 0 | H46: =MAX(0,H42-H44)*Inputs!$C$25 -> 0 | I46: =MAX(0,I42-I44)*Inputs!$C$25 -> 0 | J46: =MAX(0,J42-J44)*Inputs!$C$25 -> 0 | K46: =MAX(0,K42-K44)*Inputs!$C$25 -> 0 | L46: =MAX(0,L42-L44)*Inputs!$C$25 -> 0 | ... AD46: =MAX(0,AD42-AD44)*Inputs!$C$25 -> 1.6660646
B47: Profit after tax (book; inverter replacement expensed) | C47: ₹ Cr | D47: =SUM(E47:AD47) -> 104.469 | E47: =E16-E36-E27-E64-E41-E46-E49 -> -1.574612 | F47: =F16-F36-F27-F64-F41-F46-F49 -> -3.649172 | G47: =G16-G36-G27-G64-G41-G46-G49 -> -3.4570563 | H47: =H16-H36-H27-H64-H41-H46-H49 -> -3.122825 | I47: =I16-I36-I27-I64-I41-I46-I49 -> -2.7514943 | J47: =J16-J36-J27-J64-J41-J46-J49 -> 0.66417055 | K47: =K16-K36-K27-K64-K41-K46-K49 -> 1.1217707 | L47: =L16-L36-L27-L64-L41-L46-L49 -> 1.6294002 | ... AD47: =AD16-AD36-AD27-AD64-AD41-AD46-AD49 -> 4.9589633
B48: Cash waterfall
B49: Inverter replacement | C49: ₹ Cr | D49: =SUM(E49:AD49) -> 5.885 | E49: =IF(E5=Inputs!$C$21,Inputs!$C$6*Inputs!$C$20/10000,0) -> 0 | F49: =IF(F5=Inputs!$C$21,Inputs!$C$6*Inputs!$C$20/10000,0) -> 0 | G49: =IF(G5=Inputs!$C$21,Inputs!$C$6*Inputs!$C$20/10000,0) -> 0 | H49: =IF(H5=Inputs!$C$21,Inputs!$C$6*Inputs!$C$20/10000,0) -> 0 | I49: =IF(I5=Inputs!$C$21,Inputs!$C$6*Inputs!$C$20/10000,0) -> 0 | J49: =IF(J5=Inputs!$C$21,Inputs!$C$6*Inputs!$C$20/10000,0) -> 0 | K49: =IF(K5=Inputs!$C$21,Inputs!$C$6*Inputs!$C$20/10000,0) -> 0 | L49: =IF(L5=Inputs!$C$21,Inputs!$C$6*Inputs!$C$20/10000,0) -> 0 | ... AD49: =IF(AD5=Inputs!$C$21,Inputs!$C$6*Inputs!$C$20/10000,0) -> 0
B50: CFADS after tax and lifecycle capex | C50: ₹ Cr | D50: =SUM(E50:AD50) -> 260.49198 | E50: =E16-E46-E49 -> 5.308 | F50: =F16-F46-F49 -> 12.7392 | G50: =G16-G46-G49 -> 12.678923 | H50: =H16-H46-H49 -> 12.618888 | I50: =I16-I46-I49 -> 12.559092 | J50: =J16-J46-J49 -> 12.499536 | K50: =K16-K46-K49 -> 12.440217 | L50: =L16-L46-L49 -> 12.381137 | ... AD50: =AD16-AD46-AD49 -> 4.9589633
B51: Cash after senior debt service | C51: ₹ Cr | E51: =E50-E30 -> 2.9662833 | F51: =F50-F30 -> 3.6816837 | G51: =G50-G30 -> 3.6648062 | H51: =H50-H30 -> 3.6479962 | I51: =I50-I30 -> 3.6312534 | J51: =J50-J30 -> 3.6145777 | K51: =K50-K30 -> 3.5979686 | L51: =L50-L30 -> 3.5814259 | ... AD51: =AD50-AD30 -> 4.9589633
B52: DSRA target (cash form) | C52: ₹ Cr | E52: =IF(Inputs!$C$41=1,Inputs!$C$40/12*F30,0) -> 4.5287582 | F52: =IF(Inputs!$C$41=1,Inputs!$C$40/12*G30,0) -> 4.5070585 | G52: =IF(Inputs!$C$41=1,Inputs!$C$40/12*H30,0) -> 4.4854457 | H52: =IF(Inputs!$C$41=1,Inputs!$C$40/12*I30,0) -> 4.4639193 | I52: =IF(Inputs!$C$41=1,Inputs!$C$40/12*J30,0) -> 4.442479 | J52: =IF(Inputs!$C$41=1,Inputs!$C$40/12*K30,0) -> 4.4211244 | K52: =IF(Inputs!$C$41=1,Inputs!$C$40/12*L30,0) -> 4.3998553 | L52: =IF(Inputs!$C$41=1,Inputs!$C$40/12*M30,0) -> 4.3786713 | ... AC52: =IF(Inputs!$C$41=1,Inputs!$C$40/12*AD30,0) -> 0 | AD52: 0
B53: DSRA opening | C53: ₹ Cr | E53: =IF(Inputs!$C$110=1,E52,0) -> 0 | F53: =E56 -> 2.9662833 | G53: =F56 -> 4.5070585 | H53: =G56 -> 4.4854457 | I53: =H56 -> 4.4639193 | J53: =I56 -> 4.442479 | K53: =J56 -> 4.4211244 | L53: =K56 -> 4.3998553 | M53: =L56 -> 4.3786713 | ... AD53: =AC56 -> 0
B54: DSRA top-up from cash | C54: ₹ Cr | D54: =SUM(E54:AD54) -> 4.5070585 | E54: =MIN(MAX(E51,0),MAX(0,E52-E53)) -> 2.9662833 | F54: =MIN(MAX(F51,0),MAX(0,F52-F53)) -> 1.5407752 | G54: =MIN(MAX(G51,0),MAX(0,G52-G53)) -> 0 | H54: =MIN(MAX(H51,0),MAX(0,H52-H53)) -> 0 | I54: =MIN(MAX(I51,0),MAX(0,I52-I53)) -> 0 | J54: =MIN(MAX(J51,0),MAX(0,J52-J53)) -> 0 | K54: =MIN(MAX(K51,0),MAX(0,K52-K53)) -> 0 | L54: =MIN(MAX(L51,0),MAX(0,L52-L53)) -> 0 | ... AD54: =MIN(MAX(AD51,0),MAX(0,AD52-AD53)) -> 0
B55: DSRA release | C55: ₹ Cr | D55: =SUM(E55:AD55) -> 4.5070585 | E55: =MAX(0,E53-E52) -> 0 | F55: =MAX(0,F53-F52) -> 0 | G55: =MAX(0,G53-G52) -> 0.021612849 | H55: =MAX(0,H53-H52) -> 0.021526398 | I55: =MAX(0,I53-I52) -> 0.021440292 | J55: =MAX(0,J53-J52) -> 0.021354531 | K55: =MAX(0,K53-K52) -> 0.021269113 | L55: =MAX(0,L53-L52) -> 0.021184037 | ... AD55: =MAX(0,AD53-AD52) -> 0
B56: DSRA closing | C56: ₹ Cr | E56: =E53+E54-E55 -> 2.9662833 | F56: =F53+F54-F55 -> 4.5070585 | G56: =G53+G54-G55 -> 4.4854457 | H56: =H53+H54-H55 -> 4.4639193 | I56: =I53+I54-I55 -> 4.442479 | J56: =J53+J54-J55 -> 4.4211244 | K56: =K53+K54-K55 -> 4.3998553 | L56: =L53+L54-L55 -> 4.3786713 | ... AD56: =AD53+AD54-AD55 -> 0
B57: Cash available for shareholders this year | C57: ₹ Cr | D57: =SUM(E57:AD57) -> 169.50738 | E57: =E51-E54+E55-E41 -> 0 | F57: =F51-F54+F55-F41 -> 2.1409085 | G57: =G51-G54+G55-G41 -> 3.686419 | H57: =H51-H54+H55-H41 -> 3.6695226 | I57: =I51-I54+I55-I41 -> 3.6526937 | J57: =J51-J54+J55-J41 -> 3.6359322 | K57: =K51-K54+K55-K41 -> 3.6192377 | L57: =L51-L54+L55-L41 -> 3.60261 | ... AD57: =AD51-AD54+AD55-AD41 -> 4.9589633
B58: Cash held in the SPV, opening | C58: ₹ Cr | E58: 0 | F58: =E81 -> 0 | G58: =F81 -> 0 | H58: =G81 -> 0.53252564 | I58: =H81 -> 1.0481548 | J58: =I81 -> 1.5469552 | K58: =J81 -> 2.028994 | L58: =K81 -> 2.4943383 | M58: =L81 -> 2.9430548 | ... AD58: =AC81 -> 0
B59: Cash available to pay HoldCo | C59: ₹ Cr | E59: =E57+E58 -> 0 | F59: =F57+F58 -> 2.1409085 | G59: =G57+G58 -> 3.686419 | H59: =H57+H58 -> 4.2020482 | I59: =I57+I58 -> 4.7008486 | J59: =J57+J58 -> 5.1828874 | K59: =K57+K58 -> 5.6482317 | L59: =L57+L58 -> 6.0969482 | ... AD59: =AD57+AD58 -> 4.9589633
B60: HoldCo → SPV instruments (equity shares + CCD or NCD) and how cash returns
B61: Equity shares subscribed by HoldCo (incl. pre-close PMC, capitalised) | C61: ₹ Cr | D61: =SUM(E61:AD61) -> 8.2299948 | E61: ='Sources & Uses'!$C$31+'Sources & Uses'!$C$37+'Sources & Uses'!$C$40 -> 8.2299948 | F61: 0 | G61: 0 | H61: 0 | I61: 0 | J61: 0 | K61: 0 | L61: 0 | M61: 0 | N61: 0 | O61: 0 | P61: 0 | Q61: 0 | R61: 0 | S61: 0 | T61: 0 | U61: 0 | V61: 0 | W61: 0 | X61: 0 | Y61: 0 | Z61: 0 | AA61: 0 | AB61: 0 | AC61: 0 | AD61: 0
B62: CCD / NCD balance, opening | C62: ₹ Cr | E62: 0 | F62: =E74 -> 25.377994 | G62: =F74 -> 26.282445 | H62: =G74 -> 26.282445 | I62: =H74 -> 26.282445 | J62: =I74 -> 26.282445 | K62: =J74 -> 26.282445 | L62: =K74 -> 26.282445 | M62: =L74 -> 26.282445 | ... AD62: =AC74 -> 0
B63: CCD / NCD subscribed by HoldCo | C63: ₹ Cr | D63: =SUM(E63:AD63) -> 24.054971 | E63: ='Sources & Uses'!$C$32 -> 24.054971 | F63: 0 | G63: 0 | H63: 0 | I63: 0 | J63: 0 | K63: 0 | L63: 0 | M63: 0 | N63: 0 | O63: 0 | P63: 0 | Q63: 0 | R63: 0 | S63: 0 | T63: 0 | U63: 0 | V63: 0 | W63: 0 | X63: 0 | Y63: 0 | Z63: 0 | AA63: 0 | AB63: 0 | AC63: 0 | AD63: 0
B64: Coupon accrued (from the date HoldCo cash goes in) | C64: ₹ Cr | D64: =SUM(E64:AD64) -> 32.753423 | E64: =(E62+E63*'Construction Draws'!$C$38)*IF(Inputs!$C$56=1,Inputs!$C$57,Inputs!$C$59) -> 1.3230234 | F64: =(F62+F63*'Construction Draws'!$C$38)*IF(Inputs!$C$56=1,Inputs!$C$57,Inputs!$C$59) -> 3.0453593 | G64: =(G62+G63*'Construction Draws'!$C$38)*IF(Inputs!$C$56=1,Inputs!$C$57,Inputs!$C$59) -> 3.1538934 | H64: =(H62+H63*'Construction Draws'!$C$38)*IF(Inputs!$C$56=1,Inputs!$C$57,Inputs!$C$59) -> 3.1538934 | I64: =(I62+I63*'Construction Draws'!$C$38)*IF(Inputs!$C$56=1,Inputs!$C$57,Inputs!$C$59) -> 3.1538934 | J64: =(J62+J63*'Construction Draws'!$C$38)*IF(Inputs!$C$56=1,Inputs!$C$57,Inputs!$C$59) -> 3.1538934 | K64: =(K62+K63*'Construction Draws'!$C$38)*IF(Inputs!$C$56=1,Inputs!$C$57,Inputs!$C$59) -> 3.1538934 | L64: =(L62+L63*'Construction Draws'!$C$38)*IF(Inputs!$C$56=1,Inputs!$C$57,Inputs!$C$59) -> 3.1538934 | ... AD64: =(AD62+AD63*'Construction Draws'!$C$38)*IF(Inputs!$C$56=1,Inputs!$C$57,Inputs!$C$59) -> 0
B65: 1. Coupon paid (surplus cash only, from the servicing year) | C65: ₹ Cr | D65: =SUM(E65:AD65) -> 30.525949 | E65: =IF(E5>=Inputs!$C$60,MIN(MAX(E59,0),E64),0) -> 0 | F65: =IF(F5>=Inputs!$C$60,MIN(MAX(F59,0),F64),0) -> 2.1409085 | G65: =IF(G5>=Inputs!$C$60,MIN(MAX(G59,0),G64),0) -> 3.1538934 | H65: =IF(H5>=Inputs!$C$60,MIN(MAX(H59,0),H64),0) -> 3.1538934 | I65: =IF(I5>=Inputs!$C$60,MIN(MAX(I59,0),I64),0) -> 3.1538934 | J65: =IF(J5>=Inputs!$C$60,MIN(MAX(J59,0),J64),0) -> 3.1538934 | K65: =IF(K5>=Inputs!$C$60,MIN(MAX(K59,0),K64),0) -> 3.1538934 | L65: =IF(L5>=Inputs!$C$60,MIN(MAX(L59,0),L64),0) -> 3.1538934 | ... AD65: =IF(AD5>=Inputs!$C$60,MIN(MAX(AD59,0),AD64),0) -> 0
B66: Unpaid coupon added to the balance (cumulative) | C66: ₹ Cr | E66: =E64-E65 -> 1.3230234 | F66: =F64-F65 -> 0.9044508 | G66: =G64-G65 -> 0 | H66: =H64-H65 -> 0 | I66: =I64-I65 -> 0 | J66: =J64-J65 -> 0 | K66: =K64-K65 -> 0 | L66: =L64-L65 -> 0 | ... AD66: =AD64-AD65 -> 0
B67: Cash after coupon | C67: ₹ Cr | E67: =E59-E65 -> 0 | F67: =F59-F65 -> 0 | G67: =G59-G65 -> 0.53252564 | H67: =H59-H65 -> 1.0481548 | I67: =I59-I65 -> 1.5469552 | J67: =J59-J65 -> 2.028994 | K67: =K59-K65 -> 2.4943383 | L67: =L59-L65 -> 2.9430548 | ... AD67: =AD59-AD65 -> 4.9589633
B68: Distributable reserves, opening | C68: ₹ Cr | E68: 0 | F68: =E70 -> -1.574612 | G68: =F70 -> -5.223784 | H68: =G70 -> -8.6808403 | I68: =H70 -> -11.803665 | J68: =I70 -> -14.55516 | K68: =J70 -> -13.890989 | L68: =K70 -> -12.769218 | M68: =L70 -> -11.139818 | ... AD68: =AC70 -> 0
B69: 2. Dividend (capped at distributable profit; after any NCD principal) | C69: ₹ Cr | D69: =SUM(E69:AD69) -> 104.469 | E69: =MAX(0,MIN(E67-E72,E68+E47)) -> 0 | F69: =MAX(0,MIN(F67-F72,F68+F47)) -> 0 | G69: =MAX(0,MIN(G67-G72,G68+G47)) -> 0 | H69: =MAX(0,MIN(H67-H72,H68+H47)) -> 0 | I69: =MAX(0,MIN(I67-I72,I68+I47)) -> 0 | J69: =MAX(0,MIN(J67-J72,J68+J47)) -> 0 | K69: =MAX(0,MIN(K67-K72,K68+K47)) -> 0 | L69: =MAX(0,MIN(L67-L72,L68+L47)) -> 0 | ... AD69: =MAX(0,MIN(AD67-AD72,AD68+AD47)) -> 4.9589633
B70: Distributable reserves, closing | C70: ₹ Cr | E70: =E68+E47-E69 -> -1.574612 | F70: =F68+F47-F69 -> -5.223784 | G70: =G68+G47-G69 -> -8.6808403 | H70: =H68+H47-H69 -> -11.803665 | I70: =I68+I47-I69 -> -14.55516 | J70: =J68+J47-J69 -> -13.890989 | K70: =K68+K47-K69 -> -12.769218 | L70: =L68+L47-L69 -> -11.139818 | ... AD70: =AD68+AD47-AD69 -> 0
B71: Cash left after coupon, NCD principal and dividends | C71: ₹ Cr | E71: =E67-E72-E69 -> 0 | F71: =F67-F72-F69 -> 0 | G71: =G67-G72-G69 -> 0.53252564 | H71: =H67-H72-H69 -> 1.0481548 | I71: =I67-I72-I69 -> 1.5469552 | J71: =J67-J72-J69 -> 2.028994 | K71: =K67-K72-K69 -> 2.4943383 | L71: =L67-L72-L69 -> 2.9430548 | ... AD71: =AD67-AD72-AD69 -> 0
B72: 3. NCD principal (ranks ahead of dividends; none for a CCD) | C72: ₹ Cr | D72: =SUM(E72:AD72) -> 0 | E72: =IF(AND(Inputs!$C$56=2,E5>=Inputs!$C$61),MIN(MAX(E67,0),E62+E66),0) -> 0 | F72: =IF(AND(Inputs!$C$56=2,F5>=Inputs!$C$61),MIN(MAX(F67,0),F62+F66),0) -> 0 | G72: =IF(AND(Inputs!$C$56=2,G5>=Inputs!$C$61),MIN(MAX(G67,0),G62+G66),0) -> 0 | H72: =IF(AND(Inputs!$C$56=2,H5>=Inputs!$C$61),MIN(MAX(H67,0),H62+H66),0) -> 0 | I72: =IF(AND(Inputs!$C$56=2,I5>=Inputs!$C$61),MIN(MAX(I67,0),I62+I66),0) -> 0 | J72: =IF(AND(Inputs!$C$56=2,J5>=Inputs!$C$61),MIN(MAX(J67,0),J62+J66),0) -> 0 | K72: =IF(AND(Inputs!$C$56=2,K5>=Inputs!$C$61),MIN(MAX(K67,0),K62+K66),0) -> 0 | L72: =IF(AND(Inputs!$C$56=2,L5>=Inputs!$C$61),MIN(MAX(L67,0),L62+L66),0) -> 0 | ... AD72: =IF(AND(Inputs!$C$56=2,AD5>=Inputs!$C$61),MIN(MAX(AD67,0),AD62+AD66),0) -> 0
B73: CCD converted into equity shares (no cash) | C73: ₹ Cr | D73: =SUM(E73:AD73) -> 26.282445 | E73: =IF(AND(Inputs!$C$56=1,E5=Inputs!$C$58),E62+E63+E66-E72,0) -> 0 | F73: =IF(AND(Inputs!$C$56=1,F5=Inputs!$C$58),F62+F63+F66-F72,0) -> 0 | G73: =IF(AND(Inputs!$C$56=1,G5=Inputs!$C$58),G62+G63+G66-G72,0) -> 0 | H73: =IF(AND(Inputs!$C$56=1,H5=Inputs!$C$58),H62+H63+H66-H72,0) -> 0 | I73: =IF(AND(Inputs!$C$56=1,I5=Inputs!$C$58),I62+I63+I66-I72,0) -> 0 | J73: =IF(AND(Inputs!$C$56=1,J5=Inputs!$C$58),J62+J63+J66-J72,0) -> 0 | K73: =IF(AND(Inputs!$C$56=1,K5=Inputs!$C$58),K62+K63+K66-K72,0) -> 0 | L73: =IF(AND(Inputs!$C$56=1,L5=Inputs!$C$58),L62+L63+L66-L72,0) -> 0 | ... AD73: =IF(AND(Inputs!$C$56=1,AD5=Inputs!$C$58),AD62+AD63+AD66-AD72,0) -> 0
B74: CCD / NCD balance, closing | C74: ₹ Cr | D74: =AD74 -> 0 | E74: =E62+E63+E66-E72-E73 -> 25.377994 | F74: =F62+F63+F66-F72-F73 -> 26.282445 | G74: =G62+G63+G66-G72-G73 -> 26.282445 | H74: =H62+H63+H66-H72-H73 -> 26.282445 | I74: =I62+I63+I66-I72-I73 -> 26.282445 | J74: =J62+J63+J66-J72-J73 -> 26.282445 | K74: =K62+K63+K66-K72-K73 -> 26.282445 | L74: =L62+L63+L66-L72-L73 -> 26.282445 | ... AD74: =AD62+AD63+AD66-AD72-AD73 -> 0
B75: Cash left after routes 1–3 | C75: ₹ Cr | E75: =E71 -> 0 | F75: =F71 -> 0 | G75: =G71 -> 0.53252564 | H75: =H71 -> 1.0481548 | I75: =I71 -> 1.5469552 | J75: =J71 -> 2.028994 | K75: =K71 -> 2.4943383 | L75: =L71 -> 2.9430548 | ... AD75: =AD71 -> 0
B76: Equity share capital, opening | C76: ₹ Cr | E76: 0 | F76: =E78 -> 8.2299948 | G76: =F78 -> 8.2299948 | H76: =G78 -> 8.2299948 | I76: =H78 -> 8.2299948 | J76: =I78 -> 8.2299948 | K76: =J78 -> 8.2299948 | L76: =K78 -> 8.2299948 | M76: =L78 -> 8.2299948 | ... AD76: =AC78 -> 0
B77: 4. Capital reduction (after senior debt is repaid) | C77: ₹ Cr | D77: =SUM(E77:AD77) -> 34.51244 | E77: =IF(E5>=Inputs!$C$62,MIN(MAX(E75,0),E76+E61+E73),0) -> 0 | F77: =IF(F5>=Inputs!$C$62,MIN(MAX(F75,0),F76+F61+F73),0) -> 0 | G77: =IF(G5>=Inputs!$C$62,MIN(MAX(G75,0),G76+G61+G73),0) -> 0 | H77: =IF(H5>=Inputs!$C$62,MIN(MAX(H75,0),H76+H61+H73),0) -> 0 | I77: =IF(I5>=Inputs!$C$62,MIN(MAX(I75,0),I76+I61+I73),0) -> 0 | J77: =IF(J5>=Inputs!$C$62,MIN(MAX(J75,0),J76+J61+J73),0) -> 0 | K77: =IF(K5>=Inputs!$C$62,MIN(MAX(K75,0),K76+K61+K73),0) -> 0 | L77: =IF(L5>=Inputs!$C$62,MIN(MAX(L75,0),L76+L61+L73),0) -> 0 | ... AD77: =IF(AD5>=Inputs!$C$62,MIN(MAX(AD75,0),AD76+AD61+AD73),0) -> 0
B78: Equity share capital, closing | C78: ₹ Cr | E78: =E76+E61+E73-E77-E80 -> 8.2299948 | F78: =F76+F61+F73-F77-F80 -> 8.2299948 | G78: =G76+G61+G73-G77-G80 -> 8.2299948 | H78: =H76+H61+H73-H77-H80 -> 8.2299948 | I78: =I76+I61+I73-I77-I80 -> 8.2299948 | J78: =J76+J61+J73-J77-J80 -> 8.2299948 | K78: =K76+K61+K73-K77-K80 -> 8.2299948 | L78: =L76+L61+L73-L77-L80 -> 8.2299948 | ... AD78: =AD76+AD61+AD73-AD77-AD80 -> 0
B79: Cash left after all routes | C79: ₹ Cr | E79: =E75-E77 -> 0 | F79: =F75-F77 -> 0 | G79: =G75-G77 -> 0.53252564 | H79: =H75-H77 -> 1.0481548 | I79: =I75-I77 -> 1.5469552 | J79: =J75-J77 -> 2.028994 | K79: =K75-K77 -> 2.4943383 | L79: =L75-L77 -> 2.9430548 | ... AD79: =AD75-AD77 -> 0
B80: 5. Final-year capital return | C80: ₹ Cr | D80: =SUM(E80:AD80) -> 0 | E80: =IF(E5=Inputs!$C$17,E79,0) -> 0 | F80: =IF(F5=Inputs!$C$17,F79,0) -> 0 | G80: =IF(G5=Inputs!$C$17,G79,0) -> 0 | H80: =IF(H5=Inputs!$C$17,H79,0) -> 0 | I80: =IF(I5=Inputs!$C$17,I79,0) -> 0 | J80: =IF(J5=Inputs!$C$17,J79,0) -> 0 | K80: =IF(K5=Inputs!$C$17,K79,0) -> 0 | L80: =IF(L5=Inputs!$C$17,L79,0) -> 0 | ... AD80: =IF(AD5=Inputs!$C$17,AD79,0) -> 0
B81: Cash held in the SPV, closing (trapped) | C81: ₹ Cr | D81: =MAX(E81:AD81) -> 8.5057283 | E81: =E79-E80 -> 0 | F81: =F79-F80 -> 0 | G81: =G79-G80 -> 0.53252564 | H81: =H79-H80 -> 1.0481548 | I81: =I79-I80 -> 1.5469552 | J81: =J79-J80 -> 2.028994 | K81: =K79-K80 -> 2.4943383 | L81: =L79-L80 -> 2.9430548 | ... AD81: =AD79-AD80 -> 0
B82: Returns to HoldCo
B83: Cash paid to HoldCo (1 to 5) | C83: ₹ Cr | D83: =SUM(E83:AD83) -> 169.50738 | E83: =E65+E69+E72+E77+E80 -> 0 | F83: =F65+F69+F72+F77+F80 -> 2.1409085 | G83: =G65+G69+G72+G77+G80 -> 3.1538934 | H83: =H65+H69+H72+H77+H80 -> 3.1538934 | I83: =I65+I69+I72+I77+I80 -> 3.1538934 | J83: =J65+J69+J72+J77+J80 -> 3.1538934 | K83: =K65+K69+K72+K77+K80 -> 3.1538934 | L83: =L65+L69+L72+L77+L80 -> 3.1538934 | ... AD83: =AD65+AD69+AD72+AD77+AD80 -> 4.9589633
B84: HoldCo investment (equity shares + CCD / NCD) | C84: ₹ Cr | D84: =SUM(E84:AD84) -> -32.284966 | E84: =-(E61+E63) -> -32.284966 | F84: =-(F61+F63) -> 0 | G84: =-(G61+G63) -> 0 | H84: =-(H61+H63) -> 0 | I84: =-(I61+I63) -> 0 | J84: =-(J61+J63) -> 0 | K84: =-(K61+K63) -> 0 | L84: =-(L61+L63) -> 0 | ... AD84: =-(AD61+AD63) -> 0
B85: Net HoldCo cash flow — with instrument limits | C85: ₹ Cr | D85: =SUM(E85:AD85) -> 137.22242 | E85: =E83+E84 -> -32.284966 | F85: =F83+F84 -> 2.1409085 | G85: =G83+G84 -> 3.1538934 | H85: =H83+H84 -> 3.1538934 | I85: =I83+I84 -> 3.1538934 | J85: =J83+J84 -> 3.1538934 | K85: =K83+K84 -> 3.1538934 | L85: =L83+L84 -> 3.1538934 | ... AD85: =AD83+AD84 -> 4.9589633
B86: Net cash flow if all free cash could leave (lender-pack basis) | C86: ₹ Cr | D86: =SUM(E86:AD86) -> 137.22242 | E86: =E57+E84 -> -32.284966 | F86: =F57+F84 -> 2.1409085 | G86: =G57+G84 -> 3.686419 | H86: =H57+H84 -> 3.6695226 | I86: =I57+I84 -> 3.6526937 | J86: =J57+J84 -> 3.6359322 | K86: =K57+K84 -> 3.6192377 | L86: =L57+L84 -> 3.60261 | ... AD86: =AD57+AD84 -> 4.9589633
B87: Project cash flow, pre-tax, unlevered | C87: ₹ Cr | D87: =SUM(E87:AD87) -> 215.4977 | E87: =-'Sources & Uses'!$C$11+E16 -> -74.82465 | F87: =F16-F49 -> 12.7392 | G87: =G16-G49 -> 12.678923 | H87: =H16-H49 -> 12.618888 | I87: =I16-I49 -> 12.559092 | J87: =J16-J49 -> 12.499536 | K87: =K16-K49 -> 12.440217 | L87: =L16-L49 -> 12.381137 | M87: =M16-M49 -> 12.322292 | ... AD87: =AD16-AD49 -> 6.6250279
B89: Key results
B90: SPV equity IRR to HoldCo — with instrument limits | D90: =IRR(E85:AD85) -> 0.14114412
B91: SPV equity IRR — lender-pack basis (all free cash paid) | D91: =IRR(E86:AD86) -> 0.14564579
B92: Project IRR, pre-tax, unlevered | D92: =IRR(E87:AD87) -> 0.15930435
B93: NPV of HoldCo cash flow at the discount rate (₹ Cr) | D93: =E85+NPV(Inputs!$C$86,F85:AD85) -> -2.3614803
B94: HoldCo MOIC (cash back ÷ invested) | D94: =D83/-D84 -> 5.2503505
B95: Peak cash trapped in the SPV (₹ Cr) | D95: =MAX(E81:AD81) -> 8.5057283
B96: Average DSCR, P50, repayment years | D96: =AVERAGE(F31:AD31) -> 1.4068652
B98: Balance sheet check
B99: Assets: book value + DSRA + cash held | C99: ₹ Cr | E99: =E37+E56+E81 -> 85.55833 | F99: =F37+F56+F81 -> 79.376212 | G99: =G37+G56+G81 -> 72.164232 | H99: =H37+H56+H81 -> 64.935443 | I99: =I37+I56+I81 -> 57.68991 | J99: =J37+J56+J81 -> 53.431049 | K99: =K37+K56+K81 -> 49.155578 | L99: =L37+L56+L81 -> 44.863565 | ... AD99: =AD37+AD56+AD81 -> 0
B100: Liabilities: senior debt + CCD / NCD | C100: ₹ Cr | E100: =E29+E74 -> 78.902947 | F100: =F29+F74 -> 76.370002 | G100: =G29+G74 -> 72.615078 | H100: =H29+H74 -> 68.509113 | I100: =I29+I74 -> 64.015075 | J100: =J29+J74 -> 59.092043 | K100: =K29+K74 -> 53.694802 | L100: =L29+L74 -> 47.773389 | ... AD100: =AD29+AD74 -> 0
B101: Equity: share capital + distributable reserves | C101: ₹ Cr | E101: =E78+E70 -> 6.6553828 | F101: =F78+F70 -> 3.0062108 | G101: =G78+G70 -> -0.45084548 | H101: =H78+H70 -> -3.5736705 | I101: =I78+I70 -> -6.3251648 | J101: =J78+J70 -> -5.6609942 | K101: =K78+K70 -> -4.5392235 | L101: =L78+L70 -> -2.9098233 | ... AD101: =AD78+AD70 -> 0
B102: Difference (should be zero) | C102: ₹ Cr | D102: =SUMPRODUCT(ABS(E102:AD102)) -> 2.4868996e-14 | E102: =E99-E100-E101 -> 0 | F102: =F99-F100-F101 -> 0 | G102: =G99-G100-G101 -> 1.5987212e-14 | H102: =H99-H100-H101 -> 0 | I102: =I99-I100-I101 -> 0 | J102: =J99-J100-J101 -> 0 | K102: =K99-K100-K101 -> 0 | L102: =L99-L100-L101 -> 0 | ... AD102: =AD99-AD100-AD101 -> 0

Sheet SPV4
B1: SPV4 (P4) — Annual operations, senior debt and cash to HoldCo
B2: Year 0 is the construction FY (debt drawn at COD, stub months of operation). Columns E:AD = years 0–25. Column D = total or key result.
B4: Timeline
B5: Year index (0 = construction FY) | D5: Total / result | E5: 0 | F5: =E5+1 -> 1 | G5: =F5+1 -> 2 | H5: =G5+1 -> 3 | I5: =H5+1 -> 4 | J5: =I5+1 -> 5 | K5: =J5+1 -> 6 | L5: =K5+1 -> 7 | M5: =L5+1 -> 8 | ... AD5: =AC5+1 -> 25
B6: Financial year | E6: =Inputs!$D$7+E5 -> 2029 | F6: =Inputs!$D$7+F5 -> 2030 | G6: =Inputs!$D$7+G5 -> 2031 | H6: =Inputs!$D$7+H5 -> 2032 | I6: =Inputs!$D$7+I5 -> 2033 | J6: =Inputs!$D$7+J5 -> 2034 | K6: =Inputs!$D$7+K5 -> 2035 | L6: =Inputs!$D$7+L5 -> 2036 | ... AD6: =Inputs!$D$7+AD5 -> 2054
B7: Operating fraction of year | E7: =IF(E5=0,Inputs!$D$9/12,IF(E5<Inputs!$D$17,1,IF(E5=Inputs!$D$17,1-Inputs!$D$9/12,0))) -> 0.25 | F7: =IF(F5=0,Inputs!$D$9/12,IF(F5<Inputs!$D$17,1,IF(F5=Inputs!$D$17,1-Inputs!$D$9/12,0))) -> 1 | G7: =IF(G5=0,Inputs!$D$9/12,IF(G5<Inputs!$D$17,1,IF(G5=Inputs!$D$17,1-Inputs!$D$9/12,0))) -> 1 | H7: =IF(H5=0,Inputs!$D$9/12,IF(H5<Inputs!$D$17,1,IF(H5=Inputs!$D$17,1-Inputs!$D$9/12,0))) -> 1 | I7: =IF(I5=0,Inputs!$D$9/12,IF(I5<Inputs!$D$17,1,IF(I5=Inputs!$D$17,1-Inputs!$D$9/12,0))) -> 1 | J7: =IF(J5=0,Inputs!$D$9/12,IF(J5<Inputs!$D$17,1,IF(J5=Inputs!$D$17,1-Inputs!$D$9/12,0))) -> 1 | K7: =IF(K5=0,Inputs!$D$9/12,IF(K5<Inputs!$D$17,1,IF(K5=Inputs!$D$17,1-Inputs!$D$9/12,0))) -> 1 | L7: =IF(L5=0,Inputs!$D$9/12,IF(L5<Inputs!$D$17,1,IF(L5=Inputs!$D$17,1-Inputs!$D$9/12,0))) -> 1 | ... AD7: =IF(AD5=0,Inputs!$D$9/12,IF(AD5<Inputs!$D$17,1,IF(AD5=Inputs!$D$17,1-Inputs!$D$9/12,0))) -> 0.75
B8: Repayment flag | E8: =IF(AND(E5>=1,E5<=Inputs!$D$31),1,0) -> 0 | F8: =IF(AND(F5>=1,F5<=Inputs!$D$31),1,0) -> 1 | G8: =IF(AND(G5>=1,G5<=Inputs!$D$31),1,0) -> 1 | H8: =IF(AND(H5>=1,H5<=Inputs!$D$31),1,0) -> 1 | I8: =IF(AND(I5>=1,I5<=Inputs!$D$31),1,0) -> 1 | J8: =IF(AND(J5>=1,J5<=Inputs!$D$31),1,0) -> 1 | K8: =IF(AND(K5>=1,K5<=Inputs!$D$31),1,0) -> 1 | L8: =IF(AND(L5>=1,L5<=Inputs!$D$31),1,0) -> 1 | ... AD8: =IF(AND(AD5>=1,AD5<=Inputs!$D$31),1,0) -> 0
B9: Operations
B10: Degradation factor | E10: =(1-Inputs!$D$15)^MAX(0,E5-1) -> 1 | F10: =(1-Inputs!$D$15)^MAX(0,F5-1) -> 1 | G10: =(1-Inputs!$D$15)^MAX(0,G5-1) -> 0.996 | H10: =(1-Inputs!$D$15)^MAX(0,H5-1) -> 0.992016 | I10: =(1-Inputs!$D$15)^MAX(0,I5-1) -> 0.98804794 | J10: =(1-Inputs!$D$15)^MAX(0,J5-1) -> 0.98409574 | K10: =(1-Inputs!$D$15)^MAX(0,K5-1) -> 0.98015936 | L10: =(1-Inputs!$D$15)^MAX(0,L5-1) -> 0.97623872 | ... AD10: =(1-Inputs!$D$15)^MAX(0,AD5-1) -> 0.90828914
B11: Generation, P50 | C11: MWh | D11: =SUM(E11:AD11) -> 1779876.3 | E11: =Inputs!$D$6*Inputs!$D$14*E10*E7 -> 18650 | F11: =Inputs!$D$6*Inputs!$D$14*F10*F7 -> 74600 | G11: =Inputs!$D$6*Inputs!$D$14*G10*G7 -> 74301.6 | H11: =Inputs!$D$6*Inputs!$D$14*H10*H7 -> 74004.394 | I11: =Inputs!$D$6*Inputs!$D$14*I10*I7 -> 73708.376 | J11: =Inputs!$D$6*Inputs!$D$14*J10*J7 -> 73413.543 | K11: =Inputs!$D$6*Inputs!$D$14*K10*K7 -> 73119.888 | L11: =Inputs!$D$6*Inputs!$D$14*L10*L7 -> 72827.409 | ... AD11: =Inputs!$D$6*Inputs!$D$14*AD10*AD7 -> 50818.777
B12: Generation, P90 | C12: MWh | D12: =SUM(E12:AD12) -> 1665964.2 | E12: =E11*(1-Inputs!$D$39) -> 17456.4 | F12: =F11*(1-Inputs!$D$39) -> 69825.6 | G12: =G11*(1-Inputs!$D$39) -> 69546.298 | H12: =H11*(1-Inputs!$D$39) -> 69268.112 | I12: =I11*(1-Inputs!$D$39) -> 68991.04 | J12: =J11*(1-Inputs!$D$39) -> 68715.076 | K12: =K11*(1-Inputs!$D$39) -> 68440.215 | L12: =L11*(1-Inputs!$D$39) -> 68166.455 | ... AD12: =AD11*(1-Inputs!$D$39) -> 47566.376
B13: Revenue, P50 | C13: ₹ Cr | D13: =SUM(E13:AD13) -> 719.07002 | E13: =E11*Inputs!$D$16/10000 -> 7.5346 | F13: =F11*Inputs!$D$16/10000 -> 30.1384 | G13: =G11*Inputs!$D$16/10000 -> 30.017846 | H13: =H11*Inputs!$D$16/10000 -> 29.897775 | I13: =I11*Inputs!$D$16/10000 -> 29.778184 | J13: =J11*Inputs!$D$16/10000 -> 29.659071 | K13: =K11*Inputs!$D$16/10000 -> 29.540435 | L13: =L11*Inputs!$D$16/10000 -> 29.422273 | ... AD13: =AD11*Inputs!$D$16/10000 -> 20.530786
B14: Revenue, P90 | C14: ₹ Cr | D14: =SUM(E14:AD14) -> 673.04954 | E14: =E12*Inputs!$D$16/10000 -> 7.0523856 | F14: =F12*Inputs!$D$16/10000 -> 28.209542 | G14: =G12*Inputs!$D$16/10000 -> 28.096704 | H14: =H12*Inputs!$D$16/10000 -> 27.984317 | I14: =I12*Inputs!$D$16/10000 -> 27.87238 | J14: =J12*Inputs!$D$16/10000 -> 27.760891 | K14: =K12*Inputs!$D$16/10000 -> 27.649847 | L14: =L12*Inputs!$D$16/10000 -> 27.539248 | ... AD14: =AD12*Inputs!$D$16/10000 -> 19.216816
B15: Operating cost | C15: ₹ Cr | D15: =SUM(E15:AD15) -> 116.5 | E15: =Inputs!$D$6*Inputs!$D$18*(1+Inputs!$D$19)^MAX(0,E5-1)*E7/10000 -> 1.165 | F15: =Inputs!$D$6*Inputs!$D$18*(1+Inputs!$D$19)^MAX(0,F5-1)*F7/10000 -> 4.66 | G15: =Inputs!$D$6*Inputs!$D$18*(1+Inputs!$D$19)^MAX(0,G5-1)*G7/10000 -> 4.66 | H15: =Inputs!$D$6*Inputs!$D$18*(1+Inputs!$D$19)^MAX(0,H5-1)*H7/10000 -> 4.66 | I15: =Inputs!$D$6*Inputs!$D$18*(1+Inputs!$D$19)^MAX(0,I5-1)*I7/10000 -> 4.66 | J15: =Inputs!$D$6*Inputs!$D$18*(1+Inputs!$D$19)^MAX(0,J5-1)*J7/10000 -> 4.66 | K15: =Inputs!$D$6*Inputs!$D$18*(1+Inputs!$D$19)^MAX(0,K5-1)*K7/10000 -> 4.66 | L15: =Inputs!$D$6*Inputs!$D$18*(1+Inputs!$D$19)^MAX(0,L5-1)*L7/10000 -> 4.66 | ... AD15: =Inputs!$D$6*Inputs!$D$18*(1+Inputs!$D$19)^MAX(0,AD5-1)*AD7/10000 -> 3.495
B16: EBITDA, P50 (pre-tax CFADS) | C16: ₹ Cr | D16: =SUM(E16:AD16) -> 602.57002 | E16: =E13-E15 -> 6.3696 | F16: =F13-F15 -> 25.4784 | G16: =G13-G15 -> 25.357846 | H16: =H13-H15 -> 25.237775 | I16: =I13-I15 -> 25.118184 | J16: =J13-J15 -> 24.999071 | K16: =K13-K15 -> 24.880435 | L16: =L13-L15 -> 24.762273 | ... AD16: =AD13-AD15 -> 17.035786
B17: EBITDA, P90 (lender case) | C17: ₹ Cr | D17: =SUM(E17:AD17) -> 556.54954 | E17: =E14-E15 -> 5.8873856 | F17: =F14-F15 -> 23.549542 | G17: =G14-G15 -> 23.436704 | H17: =H14-H15 -> 23.324317 | I17: =I14-I15 -> 23.21238 | J17: =J14-J15 -> 23.100891 | K17: =K14-K15 -> 22.989847 | L17: =L14-L15 -> 22.879248 | ... AD17: =AD14-AD15 -> 15.721816
B18: Debt sizing — debt first, sculpted to the target DSCR
B19: CFADS on the chosen sizing case | C19: ₹ Cr | E19: =IF(Inputs!$D$38=2,E17,E16)*E8 -> 0 | F19: =IF(Inputs!$D$38=2,F17,F16)*F8 -> 23.549542 | G19: =IF(Inputs!$D$38=2,G17,G16)*G8 -> 23.436704 | H19: =IF(Inputs!$D$38=2,H17,H16)*H8 -> 23.324317 | I19: =IF(Inputs!$D$38=2,I17,I16)*I8 -> 23.21238 | J19: =IF(Inputs!$D$38=2,J17,J16)*J8 -> 23.100891 | K19: =IF(Inputs!$D$38=2,K17,K16)*K8 -> 22.989847 | L19: =IF(Inputs!$D$38=2,L17,L16)*L8 -> 22.879248 | ... AD19: =IF(Inputs!$D$38=2,AD17,AD16)*AD8 -> 0
B20: Discount factor at the loan rate | E20: =IF(E8=1,1/(1+Inputs!$D$51)^E5,0) -> 0 | F20: =IF(F8=1,1/(1+Inputs!$D$51)^F5,0) -> 0.90497738 | G20: =IF(G8=1,1/(1+Inputs!$D$51)^G5,0) -> 0.81898405 | H20: =IF(H8=1,1/(1+Inputs!$D$51)^H5,0) -> 0.74116204 | I20: =IF(I8=1,1/(1+Inputs!$D$51)^I5,0) -> 0.67073487 | J20: =IF(J8=1,1/(1+Inputs!$D$51)^J5,0) -> 0.60699989 | K20: =IF(K8=1,1/(1+Inputs!$D$51)^K5,0) -> 0.54932116 | L20: =IF(L8=1,1/(1+Inputs!$D$51)^L5,0) -> 0.49712323 | ... AD20: =IF(AD8=1,1/(1+Inputs!$D$51)^AD5,0) -> 0
B21: PV of debt service capacity, P50 | C21: ₹ Cr | D21: =SUM(E21:AD21) -> 115.84379 | E21: =E16*E8/Inputs!$D$29*E20 -> 0 | F21: =F16*F8/Inputs!$D$29*F20 -> 17.736443 | G21: =G16*G8/Inputs!$D$29*G20 -> 15.975132 | H21: =H16*H8/Inputs!$D$29*H20 -> 14.388677 | I21: =I16*I8/Inputs!$D$29*I20 -> 12.959725 | J21: =J16*J8/Inputs!$D$29*J20 -> 11.672641 | K21: =K16*K8/Inputs!$D$29*K20 -> 10.513346 | L21: =L16*L8/Inputs!$D$29*L20 -> 9.4691547 | ... AD21: =AD16*AD8/Inputs!$D$29*AD20 -> 0
B22: PV of debt service capacity, P90 | C22: ₹ Cr | D22: =SUM(E22:AD22) -> 107.04991 | E22: =E17*E8/Inputs!$D$29*E20 -> 0 | F22: =F17*F8/Inputs!$D$29*F20 -> 16.393695 | G22: =G17*G8/Inputs!$D$29*G20 -> 14.764836 | H22: =H17*H8/Inputs!$D$29*H20 -> 13.297768 | I22: =I17*I8/Inputs!$D$29*I20 -> 11.976425 | J22: =J17*J8/Inputs!$D$29*J20 -> 10.786337 | K22: =K17*K8/Inputs!$D$29*K20 -> 9.7144689 | L22: =L17*L8/Inputs!$D$29*L20 -> 8.7490811 | ... AD22: =AD17*AD8/Inputs!$D$29*AD20 -> 0
B23: Scheduled debt service (sculpted) | C23: ₹ Cr | D23: =SUM(E23:AD23) -> 177.28576 | E23: =IF('Sources & Uses'!$D$18>0,E19/Inputs!$D$29*'Sources & Uses'!$D$19/'Sources & Uses'!$D$18,0) -> 0 | F23: =IF('Sources & Uses'!$D$18>0,F19/Inputs!$D$29*'Sources & Uses'!$D$19/'Sources & Uses'!$D$18,0) -> 18.115033 | G23: =IF('Sources & Uses'!$D$18>0,G19/Inputs!$D$29*'Sources & Uses'!$D$19/'Sources & Uses'!$D$18,0) -> 18.028234 | H23: =IF('Sources & Uses'!$D$18>0,H19/Inputs!$D$29*'Sources & Uses'!$D$19/'Sources & Uses'!$D$18,0) -> 17.941783 | I23: =IF('Sources & Uses'!$D$18>0,I19/Inputs!$D$29*'Sources & Uses'!$D$19/'Sources & Uses'!$D$18,0) -> 17.855677 | J23: =IF('Sources & Uses'!$D$18>0,J19/Inputs!$D$29*'Sources & Uses'!$D$19/'Sources & Uses'!$D$18,0) -> 17.769916 | K23: =IF('Sources & Uses'!$D$18>0,K19/Inputs!$D$29*'Sources & Uses'!$D$19/'Sources & Uses'!$D$18,0) -> 17.684498 | L23: =IF('Sources & Uses'!$D$18>0,L19/Inputs!$D$29*'Sources & Uses'!$D$19/'Sources & Uses'!$D$18,0) -> 17.599421 | ... AD23: =IF('Sources & Uses'!$D$18>0,AD19/Inputs!$D$29*'Sources & Uses'!$D$19/'Sources & Uses'!$D$18,0) -> 0
B24: Senior debt
B25: Opening balance | C25: ₹ Cr | E25: 0 | F25: =E29 -> 107.04991 | G25: =F29 -> 100.17511 | H25: =G29 -> 92.665266 | I25: =H29 -> 84.453336 | J25: =I29 -> 75.46526 | K25: =J29 -> 65.619196 | L25: =K29 -> 54.824714 | M25: =L29 -> 42.981888 | ... AD25: =AC29 -> 0
B26: Drawdown | C26: ₹ Cr | D26: =SUM(E26:AD26) -> 107.04991 | E26: ='Sources & Uses'!$D$19 -> 107.04991 | F26: 0 | G26: 0 | H26: 0 | I26: 0 | J26: 0 | K26: 0 | L26: 0 | M26: 0 | N26: 0 | O26: 0 | P26: 0 | Q26: 0 | R26: 0 | S26: 0 | T26: 0 | U26: 0 | V26: 0 | W26: 0 | X26: 0 | Y26: 0 | Z26: 0 | AA26: 0 | AB26: 0 | AC26: 0 | AD26: 0
B27: Interest (post-COD) | C27: ₹ Cr | D27: =SUM(E27:AD27) -> 73.045917 | E27: ='Sources & Uses'!$D$19*Inputs!$D$51*Inputs!$D$9/12 -> 2.81006 | F27: =F25*Inputs!$D$51 -> 11.24024 | G27: =G25*Inputs!$D$51 -> 10.518387 | H27: =H25*Inputs!$D$51 -> 9.7298529 | I27: =I25*Inputs!$D$51 -> 8.8676003 | J27: =J25*Inputs!$D$51 -> 7.9238523 | K27: =K25*Inputs!$D$51 -> 6.8900156 | L27: =L25*Inputs!$D$51 -> 5.756595 | M27: =M25*Inputs!$D$51 -> 4.5130982 | ... AD27: =AD25*Inputs!$D$51 -> 0
B28: Principal repayment | C28: ₹ Cr | D28: =SUM(E28:AD28) -> 107.04991 | E28: =IF(E5=Inputs!$D$31,E25,MIN(E25,MAX(0,E23-E27))*E8) -> 0 | F28: =IF(F5=Inputs!$D$31,F25,MIN(F25,MAX(0,F23-F27))*F8) -> 6.8747925 | G28: =IF(G5=Inputs!$D$31,G25,MIN(G25,MAX(0,G23-G27))*G8) -> 7.5098471 | H28: =IF(H5=Inputs!$D$31,H25,MIN(H25,MAX(0,H23-H27))*H8) -> 8.2119297 | I28: =IF(I5=Inputs!$D$31,I25,MIN(I25,MAX(0,I23-I27))*I8) -> 8.9880767 | J28: =IF(J5=Inputs!$D$31,J25,MIN(J25,MAX(0,J23-J27))*J8) -> 9.8460636 | K28: =IF(K5=Inputs!$D$31,K25,MIN(K25,MAX(0,K23-K27))*K8) -> 10.794482 | L28: =IF(L5=Inputs!$D$31,L25,MIN(L25,MAX(0,L23-L27))*L8) -> 11.842826 | ... AD28: =IF(AD5=Inputs!$D$31,AD25,MIN(AD25,MAX(0,AD23-AD27))*AD8) -> 0
B29: Closing balance | C29: ₹ Cr | D29: =AD29 -> 0 | E29: =E25+E26-E28 -> 107.04991 | F29: =F25+F26-F28 -> 100.17511 | G29: =G25+G26-G28 -> 92.665266 | H29: =H25+H26-H28 -> 84.453336 | I29: =I25+I26-I28 -> 75.46526 | J29: =J25+J26-J28 -> 65.619196 | K29: =K25+K26-K28 -> 54.824714 | L29: =L25+L26-L28 -> 42.981888 | ... AD29: =AD25+AD26-AD28 -> 0
B30: Senior debt service | C30: ₹ Cr | D30: =SUM(E30:AD30) -> 180.09582 | E30: =E27+E28 -> 2.81006 | F30: =F27+F28 -> 18.115033 | G30: =G27+G28 -> 18.028234 | H30: =H27+H28 -> 17.941783 | I30: =I27+I28 -> 17.855677 | J30: =J27+J28 -> 17.769916 | K30: =K27+K28 -> 17.684498 | L30: =L27+L28 -> 17.599421 | ... AD30: =AD27+AD28 -> 0
B31: DSCR, P50 (pre-tax) | C31: x | D31: =MIN(E31:AD31) -> 1.4064783 | E31: =IF(E8=1,E16/E30,"") | F31: =IF(F8=1,F16/F30,"") -> 1.4064783 | G31: =IF(G8=1,G16/G30,"") -> 1.406563 | H31: =IF(H8=1,H16/H30,"") -> 1.4066481 | I31: =IF(I8=1,I16/I30,"") -> 1.4067338 | J31: =IF(J8=1,J16/J30,"") -> 1.4068199 | K31: =IF(K8=1,K16/K30,"") -> 1.4069065 | L31: =IF(L8=1,L16/L30,"") -> 1.4069936 | ... AD31: =IF(AD8=1,AD16/AD30,"")
B32: DSCR, P90 (pre-tax) | C32: x | D32: =MIN(E32:AD32) -> 1.3 | E32: =IF(E8=1,E17/E30,"") | F32: =IF(F8=1,F17/F30,"") -> 1.3 | G32: =IF(G8=1,G17/G30,"") -> 1.3 | H32: =IF(H8=1,H17/H30,"") -> 1.3 | I32: =IF(I8=1,I17/I30,"") -> 1.3 | J32: =IF(J8=1,J17/J30,"") -> 1.3 | K32: =IF(K8=1,K17/K30,"") -> 1.3 | L32: =IF(L8=1,L17/L30,"") -> 1.3 | ... AD32: =IF(AD8=1,AD17/AD30,"")
B33: DSCR, P50 (post-tax) | C33: x | D33: =MIN(E33:AD33) -> 1.4064783 | E33: =IF(E8=1,(E16-E46)/E30,"") | F33: =IF(F8=1,(F16-F46)/F30,"") -> 1.4064783 | G33: =IF(G8=1,(G16-G46)/G30,"") -> 1.406563 | H33: =IF(H8=1,(H16-H46)/H30,"") -> 1.4066481 | I33: =IF(I8=1,(I16-I46)/I30,"") -> 1.4067338 | J33: =IF(J8=1,(J16-J46)/J30,"") -> 1.4068199 | K33: =IF(K8=1,(K16-K46)/K30,"") -> 1.4069065 | L33: =IF(L8=1,(L16-L46)/L30,"") -> 1.4069936 | ... AD33: =IF(AD8=1,(AD16-AD46)/AD30,"")
B34: Depreciation and tax
B35: Book value, opening | C35: ₹ Cr | E35: ='Sources & Uses'!$D$43 -> 171.38973 | F35: =E37 -> 167.53346 | G35: =F37 -> 152.10838 | H35: =G37 -> 136.68331 | I35: =H37 -> 121.25823 | J35: =I37 -> 105.83316 | K35: =J37 -> 96.406722 | L35: =K37 -> 86.980287 | M35: =L37 -> 77.553852 | ... AD35: =AC37 -> 0
B36: Book depreciation | C36: ₹ Cr | D36: =SUM(E36:AD36) -> 171.38973 | E36: =MIN(E35,'Sources & Uses'!$D$43*IF(E5<=4,Inputs!$D$22,Inputs!$D$23)*E7) -> 3.8562689 | F36: =MIN(F35,'Sources & Uses'!$D$43*IF(F5<=4,Inputs!$D$22,Inputs!$D$23)*F7) -> 15.425076 | G36: =MIN(G35,'Sources & Uses'!$D$43*IF(G5<=4,Inputs!$D$22,Inputs!$D$23)*G7) -> 15.425076 | H36: =MIN(H35,'Sources & Uses'!$D$43*IF(H5<=4,Inputs!$D$22,Inputs!$D$23)*H7) -> 15.425076 | I36: =MIN(I35,'Sources & Uses'!$D$43*IF(I5<=4,Inputs!$D$22,Inputs!$D$23)*I7) -> 15.425076 | J36: =MIN(J35,'Sources & Uses'!$D$43*IF(J5<=4,Inputs!$D$22,Inputs!$D$23)*J7) -> 9.426435 | K36: =MIN(K35,'Sources & Uses'!$D$43*IF(K5<=4,Inputs!$D$22,Inputs!$D$23)*K7) -> 9.426435 | L36: =MIN(L35,'Sources & Uses'!$D$43*IF(L5<=4,Inputs!$D$22,Inputs!$D$23)*L7) -> 9.426435 | ... AD36: =MIN(AD35,'Sources & Uses'!$D$43*IF(AD5<=4,Inputs!$D$22,Inputs!$D$23)*AD7) -> 0
B37: Book value, closing | C37: ₹ Cr | E37: =E35-E36 -> 167.53346 | F37: =F35-F36 -> 152.10838 | G37: =G35-G36 -> 136.68331 | H37: =H35-H36 -> 121.25823 | I37: =I35-I36 -> 105.83316 | J37: =J35-J36 -> 96.406722 | K37: =K35-K36 -> 86.980287 | L37: =L35-L36 -> 77.553852 | ... AD37: =AD35-AD36 -> 0
B38: Tax WDV, opening (incl. inverter replacement, added to the block) | C38: ₹ Cr | E38: ='Sources & Uses'!$D$43 -> 171.38973 | F38: =E40+E49 -> 137.11178 | G38: =F40+F49 -> 82.26707 | H38: =G40+G49 -> 49.360242 | I38: =H40+H49 -> 29.616145 | J38: =I40+I49 -> 17.769687 | K38: =J40+J49 -> 10.661812 | L38: =K40+K49 -> 6.3970873 | M38: =L40+L49 -> 3.8382524 | ... AD38: =AC40+AC49 -> 0.026270416
B39: Tax depreciation | C39: ₹ Cr | D39: =SUM(E39:AD39) -> 183.14397 | E39: =E38*Inputs!$D$24*IF(Inputs!$D$9<6,0.5,1)*IF(Inputs!$D$9>0,1,0) -> 34.277946 | F39: =F38*Inputs!$D$24*IF(F7>0,1,0) -> 54.844713 | G39: =G38*Inputs!$D$24*IF(G7>0,1,0) -> 32.906828 | H39: =H38*Inputs!$D$24*IF(H7>0,1,0) -> 19.744097 | I39: =I38*Inputs!$D$24*IF(I7>0,1,0) -> 11.846458 | J39: =J38*Inputs!$D$24*IF(J7>0,1,0) -> 7.1078748 | K39: =K38*Inputs!$D$24*IF(K7>0,1,0) -> 4.2647249 | L39: =L38*Inputs!$D$24*IF(L7>0,1,0) -> 2.5588349 | M39: =M38*Inputs!$D$24*IF(M7>0,1,0) -> 1.535301 | ... AD39: =AD38*Inputs!$D$24*IF(AD7>0,1,0) -> 0.010508166
B40: Tax WDV, closing | C40: ₹ Cr | E40: =E38-E39 -> 137.11178 | F40: =F38-F39 -> 82.26707 | G40: =G38-G39 -> 49.360242 | H40: =H38-H39 -> 29.616145 | I40: =I38-I39 -> 17.769687 | J40: =J38-J39 -> 10.661812 | K40: =K38-K39 -> 6.3970873 | L40: =L38-L39 -> 3.8382524 | ... AD40: =AD38-AD39 -> 0.01576225
B41: LC fee (if DSRA is an LC) | C41: ₹ Cr | D41: =SUM(E41:AD41) -> 0 | E41: =IF(Inputs!$D$41=2,Inputs!$D$42*Inputs!$D$40/12*F30,0) -> 0 | F41: =IF(Inputs!$D$41=2,Inputs!$D$42*Inputs!$D$40/12*G30,0) -> 0 | G41: =IF(Inputs!$D$41=2,Inputs!$D$42*Inputs!$D$40/12*H30,0) -> 0 | H41: =IF(Inputs!$D$41=2,Inputs!$D$42*Inputs!$D$40/12*I30,0) -> 0 | I41: =IF(Inputs!$D$41=2,Inputs!$D$42*Inputs!$D$40/12*J30,0) -> 0 | J41: =IF(Inputs!$D$41=2,Inputs!$D$42*Inputs!$D$40/12*K30,0) -> 0 | K41: =IF(Inputs!$D$41=2,Inputs!$D$42*Inputs!$D$40/12*L30,0) -> 0 | L41: =IF(Inputs!$D$41=2,Inputs!$D$42*Inputs!$D$40/12*M30,0) -> 0 | ... AC41: =IF(Inputs!$D$41=2,Inputs!$D$42*Inputs!$D$40/12*AD30,0) -> 0 | AD41: 0
B42: Taxable income before losses | C42: ₹ Cr | E42: =E16-E39-E27-E64-E41 -> -34.075197 | F42: =F16-F39-F27-F64-F41 -> -46.75909 | G42: =G16-G39-G27-G64-G41 -> -24.729155 | H42: =H16-H39-H27-H64-H41 -> -10.897961 | I42: =I16-I39-I27-I64-I41 -> -2.2576609 | J42: =J16-J39-J27-J64-J41 -> 3.3055576 | K42: =K16-K39-K27-K64-K41 -> 7.063908 | L42: =L16-L39-L27-L64-L41 -> 9.7850568 | ... AD42: =AD16-AD39-AD27-AD64-AD41 -> 17.025278
B43: Tax losses brought forward | C43: ₹ Cr | E43: 0 | F43: =E45 -> 34.075197 | G43: =F45 -> 80.834287 | H43: =G45 -> 105.56344 | I43: =H45 -> 116.4614 | J43: =I45 -> 118.71906 | K43: =J45 -> 115.41351 | L43: =K45 -> 108.3496 | M43: =L45 -> 98.564542 | ... AD43: =AC45 -> 0
B44: Losses used | C44: ₹ Cr | E44: =IF(E42>0,MIN(E43,E42),0) -> 0 | F44: =IF(F42>0,MIN(F43,F42),0) -> 0 | G44: =IF(G42>0,MIN(G43,G42),0) -> 0 | H44: =IF(H42>0,MIN(H43,H42),0) -> 0 | I44: =IF(I42>0,MIN(I43,I42),0) -> 0 | J44: =IF(J42>0,MIN(J43,J42),0) -> 3.3055576 | K44: =IF(K42>0,MIN(K43,K42),0) -> 7.063908 | L44: =IF(L42>0,MIN(L43,L42),0) -> 9.7850568 | ... AD44: =IF(AD42>0,MIN(AD43,AD42),0) -> 0
B45: Tax losses carried forward | C45: ₹ Cr | E45: =E43-E44+MAX(0,-E42) -> 34.075197 | F45: =F43-F44+MAX(0,-F42) -> 80.834287 | G45: =G43-G44+MAX(0,-G42) -> 105.56344 | H45: =H43-H44+MAX(0,-H42) -> 116.4614 | I45: =I43-I44+MAX(0,-I42) -> 118.71906 | J45: =J43-J44+MAX(0,-J42) -> 115.41351 | K45: =K43-K44+MAX(0,-K42) -> 108.3496 | L45: =L43-L44+MAX(0,-L42) -> 98.564542 | ... AD45: =AD43-AD44+MAX(0,-AD42) -> 0
B46: Tax paid | C46: ₹ Cr | D46: =SUM(E46:AD46) -> 69.6939 | E46: =MAX(0,E42-E44)*Inputs!$D$25 -> 0 | F46: =MAX(0,F42-F44)*Inputs!$D$25 -> 0 | G46: =MAX(0,G42-G44)*Inputs!$D$25 -> 0 | H46: =MAX(0,H42-H44)*Inputs!$D$25 -> 0 | I46: =MAX(0,I42-I44)*Inputs!$D$25 -> 0 | J46: =MAX(0,J42-J44)*Inputs!$D$25 -> 0 | K46: =MAX(0,K42-K44)*Inputs!$D$25 -> 0 | L46: =MAX(0,L42-L44)*Inputs!$D$25 -> 0 | ... AD46: =MAX(0,AD42-AD44)*Inputs!$D$25 -> 4.2849219
B47: Profit after tax (book; inverter replacement expensed) | C47: ₹ Cr | D47: =SUM(E47:AD47) -> 207.20507 | E47: =E16-E36-E27-E64-E41-E46-E49 -> -3.6535206 | F47: =F16-F36-F27-F64-F41-F46-F49 -> -7.3394525 | G47: =G16-G36-G27-G64-G41-G46-G49 -> -7.2474025 | H47: =H16-H36-H27-H64-H41-H46-H49 -> -6.5789399 | I47: =I16-I36-I27-I64-I41-I46-I49 -> -5.8362784 | J47: =J16-J36-J27-J64-J41-J46-J49 -> 0.98699739 | K47: =K16-K36-K27-K64-K41-K46-K49 -> 1.9021978 | L47: =L16-L36-L27-L64-L41-L46-L49 -> 2.9174567 | ... AD47: =AD16-AD36-AD27-AD64-AD41-AD46-AD49 -> 12.750864
B48: Cash waterfall
B49: Inverter replacement | C49: ₹ Cr | D49: =SUM(E49:AD49) -> 11.77 | E49: =IF(E5=Inputs!$D$21,Inputs!$D$6*Inputs!$D$20/10000,0) -> 0 | F49: =IF(F5=Inputs!$D$21,Inputs!$D$6*Inputs!$D$20/10000,0) -> 0 | G49: =IF(G5=Inputs!$D$21,Inputs!$D$6*Inputs!$D$20/10000,0) -> 0 | H49: =IF(H5=Inputs!$D$21,Inputs!$D$6*Inputs!$D$20/10000,0) -> 0 | I49: =IF(I5=Inputs!$D$21,Inputs!$D$6*Inputs!$D$20/10000,0) -> 0 | J49: =IF(J5=Inputs!$D$21,Inputs!$D$6*Inputs!$D$20/10000,0) -> 0 | K49: =IF(K5=Inputs!$D$21,Inputs!$D$6*Inputs!$D$20/10000,0) -> 0 | L49: =IF(L5=Inputs!$D$21,Inputs!$D$6*Inputs!$D$20/10000,0) -> 0 | ... AD49: =IF(AD5=Inputs!$D$21,Inputs!$D$6*Inputs!$D$20/10000,0) -> 0
B50: CFADS after tax and lifecycle capex | C50: ₹ Cr | D50: =SUM(E50:AD50) -> 521.10612 | E50: =E16-E46-E49 -> 6.3696 | F50: =F16-F46-F49 -> 25.4784 | G50: =G16-G46-G49 -> 25.357846 | H50: =H16-H46-H49 -> 25.237775 | I50: =I16-I46-I49 -> 25.118184 | J50: =J16-J46-J49 -> 24.999071 | K50: =K16-K46-K49 -> 24.880435 | L50: =L16-L46-L49 -> 24.762273 | ... AD50: =AD16-AD46-AD49 -> 12.750864
B51: Cash after senior debt service | C51: ₹ Cr | E51: =E50-E30 -> 3.55954 | F51: =F50-F30 -> 7.3633674 | G51: =G50-G30 -> 7.3296124 | H51: =H50-H30 -> 7.2959924 | I51: =I50-I30 -> 7.2625069 | J51: =J50-J30 -> 7.2291553 | K51: =K50-K30 -> 7.1959372 | L51: =L50-L30 -> 7.1628519 | ... AD51: =AD50-AD30 -> 12.750864
B52: DSRA target (cash form) | C52: ₹ Cr | E52: =IF(Inputs!$D$41=1,Inputs!$D$40/12*F30,0) -> 9.0575163 | F52: =IF(Inputs!$D$41=1,Inputs!$D$40/12*G30,0) -> 9.014117 | G52: =IF(Inputs!$D$41=1,Inputs!$D$40/12*H30,0) -> 8.9708913 | H52: =IF(Inputs!$D$41=1,Inputs!$D$40/12*I30,0) -> 8.9278385 | I52: =IF(Inputs!$D$41=1,Inputs!$D$40/12*J30,0) -> 8.8849579 | J52: =IF(Inputs!$D$41=1,Inputs!$D$40/12*K30,0) -> 8.8422489 | K52: =IF(Inputs!$D$41=1,Inputs!$D$40/12*L30,0) -> 8.7997106 | L52: =IF(Inputs!$D$41=1,Inputs!$D$40/12*M30,0) -> 8.7573426 | ... AC52: =IF(Inputs!$D$41=1,Inputs!$D$40/12*AD30,0) -> 0 | AD52: 0
B53: DSRA opening | C53: ₹ Cr | E53: =IF(Inputs!$C$110=1,E52,0) -> 0 | F53: =E56 -> 3.55954 | G53: =F56 -> 9.014117 | H53: =G56 -> 8.9708913 | I53: =H56 -> 8.9278385 | J53: =I56 -> 8.8849579 | K53: =J56 -> 8.8422489 | L53: =K56 -> 8.7997106 | M53: =L56 -> 8.7573426 | ... AD53: =AC56 -> 0
B54: DSRA top-up from cash | C54: ₹ Cr | D54: =SUM(E54:AD54) -> 9.014117 | E54: =MIN(MAX(E51,0),MAX(0,E52-E53)) -> 3.55954 | F54: =MIN(MAX(F51,0),MAX(0,F52-F53)) -> 5.454577 | G54: =MIN(MAX(G51,0),MAX(0,G52-G53)) -> 0 | H54: =MIN(MAX(H51,0),MAX(0,H52-H53)) -> 0 | I54: =MIN(MAX(I51,0),MAX(0,I52-I53)) -> 0 | J54: =MIN(MAX(J51,0),MAX(0,J52-J53)) -> 0 | K54: =MIN(MAX(K51,0),MAX(0,K52-K53)) -> 0 | L54: =MIN(MAX(L51,0),MAX(0,L52-L53)) -> 0 | ... AD54: =MIN(MAX(AD51,0),MAX(0,AD52-AD53)) -> 0
B55: DSRA release | C55: ₹ Cr | D55: =SUM(E55:AD55) -> 9.014117 | E55: =MAX(0,E53-E52) -> 0 | F55: =MAX(0,F53-F52) -> 0 | G55: =MAX(0,G53-G52) -> 0.043225699 | H55: =MAX(0,H53-H52) -> 0.043052796 | I55: =MAX(0,I53-I52) -> 0.042880585 | J55: =MAX(0,J53-J52) -> 0.042709062 | K55: =MAX(0,K53-K52) -> 0.042538226 | L55: =MAX(0,L53-L52) -> 0.042368073 | ... AD55: =MAX(0,AD53-AD52) -> 0
B56: DSRA closing | C56: ₹ Cr | E56: =E53+E54-E55 -> 3.55954 | F56: =F53+F54-F55 -> 9.014117 | G56: =G53+G54-G55 -> 8.9708913 | H56: =H53+H54-H55 -> 8.9278385 | I56: =I53+I54-I55 -> 8.8849579 | J56: =J53+J54-J55 -> 8.8422489 | K56: =K53+K54-K55 -> 8.7997106 | L56: =L53+L54-L55 -> 8.7573426 | ... AD56: =AD53+AD54-AD55 -> 0
B57: Cash available for shareholders this year | C57: ₹ Cr | D57: =SUM(E57:AD57) -> 341.0103 | E57: =E51-E54+E55-E41 -> 0 | F57: =F51-F54+F55-F41 -> 1.9087903 | G57: =G51-G54+G55-G41 -> 7.3728381 | H57: =H51-H54+H55-H41 -> 7.3390452 | I57: =I51-I54+I55-I41 -> 7.3053875 | J57: =J51-J54+J55-J41 -> 7.2718644 | K57: =K51-K54+K55-K41 -> 7.2384754 | L57: =L51-L54+L55-L41 -> 7.2052199 | ... AD57: =AD51-AD54+AD55-AD41 -> 12.750864
B58: Cash held in the SPV, opening | C58: ₹ Cr | E58: 0 | F58: =E81 -> 0 | G58: =F81 -> 0 | H58: =G81 -> 0.7110516 | I58: =H81 -> 1.3883103 | J58: =I81 -> 2.0319113 | K58: =J81 -> 2.6419892 | L58: =K81 -> 3.2186781 | M58: =L81 -> 3.7621116 | ... AD58: =AC81 -> 0
B59: Cash available to pay HoldCo | C59: ₹ Cr | E59: =E57+E58 -> 0 | F59: =F57+F58 -> 1.9087903 | G59: =G57+G58 -> 7.3728381 | H59: =H57+H58 -> 8.0500968 | I59: =I57+I58 -> 8.6936978 | J59: =J57+J58 -> 9.3037757 | K59: =K57+K58 -> 9.8804646 | L59: =L57+L58 -> 10.423898 | ... AD59: =AD57+AD58 -> 12.750864
B60: HoldCo → SPV instruments (equity shares + CCD or NCD) and how cash returns
B61: Equity shares subscribed by HoldCo (incl. pre-close PMC, capitalised) | C61: ₹ Cr | D61: =SUM(E61:AD61) -> 16.425473 | E61: ='Sources & Uses'!$D$31+'Sources & Uses'!$D$37+'Sources & Uses'!$D$40 -> 16.425473 | F61: 0 | G61: 0 | H61: 0 | I61: 0 | J61: 0 | K61: 0 | L61: 0 | M61: 0 | N61: 0 | O61: 0 | P61: 0 | Q61: 0 | R61: 0 | S61: 0 | T61: 0 | U61: 0 | V61: 0 | W61: 0 | X61: 0 | Y61: 0 | Z61: 0 | AA61: 0 | AB61: 0 | AC61: 0 | AD61: 0
B62: CCD / NCD balance, opening | C62: ₹ Cr | E62: 0 | F62: =E74 -> 51.271141 | G62: =F74 -> 55.514887 | H62: =G74 -> 55.514887 | I62: =H74 -> 55.514887 | J62: =I74 -> 55.514887 | K62: =J74 -> 55.514887 | L62: =K74 -> 55.514887 | M62: =L74 -> 55.514887 | ... AD62: =AC74 -> 0
B63: CCD / NCD subscribed by HoldCo | C63: ₹ Cr | D63: =SUM(E63:AD63) -> 47.914349 | E63: ='Sources & Uses'!$D$32 -> 47.914349 | F63: 0 | G63: 0 | H63: 0 | I63: 0 | J63: 0 | K63: 0 | L63: 0 | M63: 0 | N63: 0 | O63: 0 | P63: 0 | Q63: 0 | R63: 0 | S63: 0 | T63: 0 | U63: 0 | V63: 0 | W63: 0 | X63: 0 | Y63: 0 | Z63: 0 | AA63: 0 | AB63: 0 | AC63: 0 | AD63: 0
B64: Coupon accrued (from the date HoldCo cash goes in) | C64: ₹ Cr | D64: =SUM(E64:AD64) -> 69.465407 | E64: =(E62+E63*'Construction Draws'!$C$76)*IF(Inputs!$D$56=1,Inputs!$D$57,Inputs!$D$59) -> 3.3567917 | F64: =(F62+F63*'Construction Draws'!$C$76)*IF(Inputs!$D$56=1,Inputs!$D$57,Inputs!$D$59) -> 6.1525369 | G64: =(G62+G63*'Construction Draws'!$C$76)*IF(Inputs!$D$56=1,Inputs!$D$57,Inputs!$D$59) -> 6.6617865 | H64: =(H62+H63*'Construction Draws'!$C$76)*IF(Inputs!$D$56=1,Inputs!$D$57,Inputs!$D$59) -> 6.6617865 | I64: =(I62+I63*'Construction Draws'!$C$76)*IF(Inputs!$D$56=1,Inputs!$D$57,Inputs!$D$59) -> 6.6617865 | J64: =(J62+J63*'Construction Draws'!$C$76)*IF(Inputs!$D$56=1,Inputs!$D$57,Inputs!$D$59) -> 6.6617865 | K64: =(K62+K63*'Construction Draws'!$C$76)*IF(Inputs!$D$56=1,Inputs!$D$57,Inputs!$D$59) -> 6.6617865 | L64: =(L62+L63*'Construction Draws'!$C$76)*IF(Inputs!$D$56=1,Inputs!$D$57,Inputs!$D$59) -> 6.6617865 | ... AD64: =(AD62+AD63*'Construction Draws'!$C$76)*IF(Inputs!$D$56=1,Inputs!$D$57,Inputs!$D$59) -> 0
B65: 1. Coupon paid (surplus cash only, from the servicing year) | C65: ₹ Cr | D65: =SUM(E65:AD65) -> 61.864869 | E65: =IF(E5>=Inputs!$D$60,MIN(MAX(E59,0),E64),0) -> 0 | F65: =IF(F5>=Inputs!$D$60,MIN(MAX(F59,0),F64),0) -> 1.9087903 | G65: =IF(G5>=Inputs!$D$60,MIN(MAX(G59,0),G64),0) -> 6.6617865 | H65: =IF(H5>=Inputs!$D$60,MIN(MAX(H59,0),H64),0) -> 6.6617865 | I65: =IF(I5>=Inputs!$D$60,MIN(MAX(I59,0),I64),0) -> 6.6617865 | J65: =IF(J5>=Inputs!$D$60,MIN(MAX(J59,0),J64),0) -> 6.6617865 | K65: =IF(K5>=Inputs!$D$60,MIN(MAX(K59,0),K64),0) -> 6.6617865 | L65: =IF(L5>=Inputs!$D$60,MIN(MAX(L59,0),L64),0) -> 6.6617865 | ... AD65: =IF(AD5>=Inputs!$D$60,MIN(MAX(AD59,0),AD64),0) -> 0
B66: Unpaid coupon added to the balance (cumulative) | C66: ₹ Cr | E66: =E64-E65 -> 3.3567917 | F66: =F64-F65 -> 4.2437465 | G66: =G64-G65 -> 0 | H66: =H64-H65 -> 0 | I66: =I64-I65 -> 0 | J66: =J64-J65 -> 0 | K66: =K64-K65 -> 0 | L66: =L64-L65 -> 0 | ... AD66: =AD64-AD65 -> 0
B67: Cash after coupon | C67: ₹ Cr | E67: =E59-E65 -> 0 | F67: =F59-F65 -> 0 | G67: =G59-G65 -> 0.7110516 | H67: =H59-H65 -> 1.3883103 | I67: =I59-I65 -> 2.0319113 | J67: =J59-J65 -> 2.6419892 | K67: =K59-K65 -> 3.2186781 | L67: =L59-L65 -> 3.7621116 | ... AD67: =AD59-AD65 -> 12.750864
B68: Distributable reserves, opening | C68: ₹ Cr | E68: 0 | F68: =E70 -> -3.6535206 | G68: =F70 -> -10.992973 | H68: =G70 -> -18.240376 | I68: =H70 -> -24.819316 | J68: =I70 -> -30.655594 | K68: =J70 -> -29.668597 | L68: =K70 -> -27.766399 | M68: =L70 -> -24.848942 | ... AD68: =AC70 -> 0
B69: 2. Dividend (capped at distributable profit; after any NCD principal) | C69: ₹ Cr | D69: =SUM(E69:AD69) -> 207.20507 | E69: =MAX(0,MIN(E67-E72,E68+E47)) -> 0 | F69: =MAX(0,MIN(F67-F72,F68+F47)) -> 0 | G69: =MAX(0,MIN(G67-G72,G68+G47)) -> 0 | H69: =MAX(0,MIN(H67-H72,H68+H47)) -> 0 | I69: =MAX(0,MIN(I67-I72,I68+I47)) -> 0 | J69: =MAX(0,MIN(J67-J72,J68+J47)) -> 0 | K69: =MAX(0,MIN(K67-K72,K68+K47)) -> 0 | L69: =MAX(0,MIN(L67-L72,L68+L47)) -> 0 | ... AD69: =MAX(0,MIN(AD67-AD72,AD68+AD47)) -> 12.750864
B70: Distributable reserves, closing | C70: ₹ Cr | E70: =E68+E47-E69 -> -3.6535206 | F70: =F68+F47-F69 -> -10.992973 | G70: =G68+G47-G69 -> -18.240376 | H70: =H68+H47-H69 -> -24.819316 | I70: =I68+I47-I69 -> -30.655594 | J70: =J68+J47-J69 -> -29.668597 | K70: =K68+K47-K69 -> -27.766399 | L70: =L68+L47-L69 -> -24.848942 | ... AD70: =AD68+AD47-AD69 -> 0
B71: Cash left after coupon, NCD principal and dividends | C71: ₹ Cr | E71: =E67-E72-E69 -> 0 | F71: =F67-F72-F69 -> 0 | G71: =G67-G72-G69 -> 0.7110516 | H71: =H67-H72-H69 -> 1.3883103 | I71: =I67-I72-I69 -> 2.0319113 | J71: =J67-J72-J69 -> 2.6419892 | K71: =K67-K72-K69 -> 3.2186781 | L71: =L67-L72-L69 -> 3.7621116 | ... AD71: =AD67-AD72-AD69 -> 0
B72: 3. NCD principal (ranks ahead of dividends; none for a CCD) | C72: ₹ Cr | D72: =SUM(E72:AD72) -> 0 | E72: =IF(AND(Inputs!$D$56=2,E5>=Inputs!$D$61),MIN(MAX(E67,0),E62+E66),0) -> 0 | F72: =IF(AND(Inputs!$D$56=2,F5>=Inputs!$D$61),MIN(MAX(F67,0),F62+F66),0) -> 0 | G72: =IF(AND(Inputs!$D$56=2,G5>=Inputs!$D$61),MIN(MAX(G67,0),G62+G66),0) -> 0 | H72: =IF(AND(Inputs!$D$56=2,H5>=Inputs!$D$61),MIN(MAX(H67,0),H62+H66),0) -> 0 | I72: =IF(AND(Inputs!$D$56=2,I5>=Inputs!$D$61),MIN(MAX(I67,0),I62+I66),0) -> 0 | J72: =IF(AND(Inputs!$D$56=2,J5>=Inputs!$D$61),MIN(MAX(J67,0),J62+J66),0) -> 0 | K72: =IF(AND(Inputs!$D$56=2,K5>=Inputs!$D$61),MIN(MAX(K67,0),K62+K66),0) -> 0 | L72: =IF(AND(Inputs!$D$56=2,L5>=Inputs!$D$61),MIN(MAX(L67,0),L62+L66),0) -> 0 | ... AD72: =IF(AND(Inputs!$D$56=2,AD5>=Inputs!$D$61),MIN(MAX(AD67,0),AD62+AD66),0) -> 0
B73: CCD converted into equity shares (no cash) | C73: ₹ Cr | D73: =SUM(E73:AD73) -> 55.514887 | E73: =IF(AND(Inputs!$D$56=1,E5=Inputs!$D$58),E62+E63+E66-E72,0) -> 0 | F73: =IF(AND(Inputs!$D$56=1,F5=Inputs!$D$58),F62+F63+F66-F72,0) -> 0 | G73: =IF(AND(Inputs!$D$56=1,G5=Inputs!$D$58),G62+G63+G66-G72,0) -> 0 | H73: =IF(AND(Inputs!$D$56=1,H5=Inputs!$D$58),H62+H63+H66-H72,0) -> 0 | I73: =IF(AND(Inputs!$D$56=1,I5=Inputs!$D$58),I62+I63+I66-I72,0) -> 0 | J73: =IF(AND(Inputs!$D$56=1,J5=Inputs!$D$58),J62+J63+J66-J72,0) -> 0 | K73: =IF(AND(Inputs!$D$56=1,K5=Inputs!$D$58),K62+K63+K66-K72,0) -> 0 | L73: =IF(AND(Inputs!$D$56=1,L5=Inputs!$D$58),L62+L63+L66-L72,0) -> 0 | ... AD73: =IF(AND(Inputs!$D$56=1,AD5=Inputs!$D$58),AD62+AD63+AD66-AD72,0) -> 0
B74: CCD / NCD balance, closing | C74: ₹ Cr | D74: =AD74 -> 0 | E74: =E62+E63+E66-E72-E73 -> 51.271141 | F74: =F62+F63+F66-F72-F73 -> 55.514887 | G74: =G62+G63+G66-G72-G73 -> 55.514887 | H74: =H62+H63+H66-H72-H73 -> 55.514887 | I74: =I62+I63+I66-I72-I73 -> 55.514887 | J74: =J62+J63+J66-J72-J73 -> 55.514887 | K74: =K62+K63+K66-K72-K73 -> 55.514887 | L74: =L62+L63+L66-L72-L73 -> 55.514887 | ... AD74: =AD62+AD63+AD66-AD72-AD73 -> 0
B75: Cash left after routes 1–3 | C75: ₹ Cr | E75: =E71 -> 0 | F75: =F71 -> 0 | G75: =G71 -> 0.7110516 | H75: =H71 -> 1.3883103 | I75: =I71 -> 2.0319113 | J75: =J71 -> 2.6419892 | K75: =K71 -> 3.2186781 | L75: =L71 -> 3.7621116 | ... AD75: =AD71 -> 0
B76: Equity share capital, opening | C76: ₹ Cr | E76: 0 | F76: =E78 -> 16.425473 | G76: =F78 -> 16.425473 | H76: =G78 -> 16.425473 | I76: =H78 -> 16.425473 | J76: =I78 -> 16.425473 | K76: =J78 -> 16.425473 | L76: =K78 -> 16.425473 | M76: =L78 -> 16.425473 | ... AD76: =AC78 -> 4.7961635e-14
B77: 4. Capital reduction (after senior debt is repaid) | C77: ₹ Cr | D77: =SUM(E77:AD77) -> 71.940361 | E77: =IF(E5>=Inputs!$D$62,MIN(MAX(E75,0),E76+E61+E73),0) -> 0 | F77: =IF(F5>=Inputs!$D$62,MIN(MAX(F75,0),F76+F61+F73),0) -> 0 | G77: =IF(G5>=Inputs!$D$62,MIN(MAX(G75,0),G76+G61+G73),0) -> 0 | H77: =IF(H5>=Inputs!$D$62,MIN(MAX(H75,0),H76+H61+H73),0) -> 0 | I77: =IF(I5>=Inputs!$D$62,MIN(MAX(I75,0),I76+I61+I73),0) -> 0 | J77: =IF(J5>=Inputs!$D$62,MIN(MAX(J75,0),J76+J61+J73),0) -> 0 | K77: =IF(K5>=Inputs!$D$62,MIN(MAX(K75,0),K76+K61+K73),0) -> 0 | L77: =IF(L5>=Inputs!$D$62,MIN(MAX(L75,0),L76+L61+L73),0) -> 0 | ... AD77: =IF(AD5>=Inputs!$D$62,MIN(MAX(AD75,0),AD76+AD61+AD73),0) -> 0
B78: Equity share capital, closing | C78: ₹ Cr | E78: =E76+E61+E73-E77-E80 -> 16.425473 | F78: =F76+F61+F73-F77-F80 -> 16.425473 | G78: =G76+G61+G73-G77-G80 -> 16.425473 | H78: =H76+H61+H73-H77-H80 -> 16.425473 | I78: =I76+I61+I73-I77-I80 -> 16.425473 | J78: =J76+J61+J73-J77-J80 -> 16.425473 | K78: =K76+K61+K73-K77-K80 -> 16.425473 | L78: =L76+L61+L73-L77-L80 -> 16.425473 | ... AD78: =AD76+AD61+AD73-AD77-AD80 -> 4.7961635e-14
B79: Cash left after all routes | C79: ₹ Cr | E79: =E75-E77 -> 0 | F79: =F75-F77 -> 0 | G79: =G75-G77 -> 0.7110516 | H79: =H75-H77 -> 1.3883103 | I79: =I75-I77 -> 2.0319113 | J79: =J75-J77 -> 2.6419892 | K79: =K75-K77 -> 3.2186781 | L79: =L75-L77 -> 3.7621116 | ... AD79: =AD75-AD77 -> 0
B80: 5. Final-year capital return | C80: ₹ Cr | D80: =SUM(E80:AD80) -> 0 | E80: =IF(E5=Inputs!$D$17,E79,0) -> 0 | F80: =IF(F5=Inputs!$D$17,F79,0) -> 0 | G80: =IF(G5=Inputs!$D$17,G79,0) -> 0 | H80: =IF(H5=Inputs!$D$17,H79,0) -> 0 | I80: =IF(I5=Inputs!$D$17,I79,0) -> 0 | J80: =IF(J5=Inputs!$D$17,J79,0) -> 0 | K80: =IF(K5=Inputs!$D$17,K79,0) -> 0 | L80: =IF(L5=Inputs!$D$17,L79,0) -> 0 | ... AD80: =IF(AD5=Inputs!$D$17,AD79,0) -> 0
B81: Cash held in the SPV, closing (trapped) | C81: ₹ Cr | D81: =MAX(E81:AD81) -> 13.825459 | E81: =E79-E80 -> 0 | F81: =F79-F80 -> 0 | G81: =G79-G80 -> 0.7110516 | H81: =H79-H80 -> 1.3883103 | I81: =I79-I80 -> 2.0319113 | J81: =J79-J80 -> 2.6419892 | K81: =K79-K80 -> 3.2186781 | L81: =L79-L80 -> 3.7621116 | ... AD81: =AD79-AD80 -> 0
B82: Returns to HoldCo
B83: Cash paid to HoldCo (1 to 5) | C83: ₹ Cr | D83: =SUM(E83:AD83) -> 341.0103 | E83: =E65+E69+E72+E77+E80 -> 0 | F83: =F65+F69+F72+F77+F80 -> 1.9087903 | G83: =G65+G69+G72+G77+G80 -> 6.6617865 | H83: =H65+H69+H72+H77+H80 -> 6.6617865 | I83: =I65+I69+I72+I77+I80 -> 6.6617865 | J83: =J65+J69+J72+J77+J80 -> 6.6617865 | K83: =K65+K69+K72+K77+K80 -> 6.6617865 | L83: =L65+L69+L72+L77+L80 -> 6.6617865 | ... AD83: =AD65+AD69+AD72+AD77+AD80 -> 12.750864
B84: HoldCo investment (equity shares + CCD / NCD) | C84: ₹ Cr | D84: =SUM(E84:AD84) -> -64.339822 | E84: =-(E61+E63) -> -64.339822 | F84: =-(F61+F63) -> 0 | G84: =-(G61+G63) -> 0 | H84: =-(H61+H63) -> 0 | I84: =-(I61+I63) -> 0 | J84: =-(J61+J63) -> 0 | K84: =-(K61+K63) -> 0 | L84: =-(L61+L63) -> 0 | ... AD84: =-(AD61+AD63) -> 0
B85: Net HoldCo cash flow — with instrument limits | C85: ₹ Cr | D85: =SUM(E85:AD85) -> 276.67048 | E85: =E83+E84 -> -64.339822 | F85: =F83+F84 -> 1.9087903 | G85: =G83+G84 -> 6.6617865 | H85: =H83+H84 -> 6.6617865 | I85: =I83+I84 -> 6.6617865 | J85: =J83+J84 -> 6.6617865 | K85: =K83+K84 -> 6.6617865 | L85: =L83+L84 -> 6.6617865 | ... AD85: =AD83+AD84 -> 12.750864
B86: Net cash flow if all free cash could leave (lender-pack basis) | C86: ₹ Cr | D86: =SUM(E86:AD86) -> 276.67048 | E86: =E57+E84 -> -64.339822 | F86: =F57+F84 -> 1.9087903 | G86: =G57+G84 -> 7.3728381 | H86: =H57+H84 -> 7.3390452 | I86: =I57+I84 -> 7.3053875 | J86: =J57+J84 -> 7.2718644 | K86: =K57+K84 -> 7.2384754 | L86: =L57+L84 -> 7.2052199 | ... AD86: =AD57+AD84 -> 12.750864
B87: Project cash flow, pre-tax, unlevered | C87: ₹ Cr | D87: =SUM(E87:AD87) -> 430.53472 | E87: =-'Sources & Uses'!$D$11+E16 -> -153.8957 | F87: =F16-F49 -> 25.4784 | G87: =G16-G49 -> 25.357846 | H87: =H16-H49 -> 25.237775 | I87: =I16-I49 -> 25.118184 | J87: =J16-J49 -> 24.999071 | K87: =K16-K49 -> 24.880435 | L87: =L16-L49 -> 24.762273 | M87: =M16-M49 -> 24.644584 | ... AD87: =AD16-AD49 -> 17.035786
B89: Key results
B90: SPV equity IRR to HoldCo — with instrument limits | D90: =IRR(E85:AD85) -> 0.13994361
B91: SPV equity IRR — lender-pack basis (all free cash paid) | D91: =IRR(E86:AD86) -> 0.14292302
B92: Project IRR, pre-tax, unlevered | D92: =IRR(E87:AD87) -> 0.15441507
B93: NPV of HoldCo cash flow at the discount rate (₹ Cr) | D93: =E85+NPV(Inputs!$C$86,F85:AD85) -> -5.4367034
B94: HoldCo MOIC (cash back ÷ invested) | D94: =D83/-D84 -> 5.3001436
B95: Peak cash trapped in the SPV (₹ Cr) | D95: =MAX(E81:AD81) -> 13.825459
B96: Average DSCR, P50, repayment years | D96: =AVERAGE(F31:AD31) -> 1.4068652
B98: Balance sheet check
B99: Assets: book value + DSRA + cash held | C99: ₹ Cr | E99: =E37+E56+E81 -> 171.093 | F99: =F37+F56+F81 -> 161.1225 | G99: =G37+G56+G81 -> 146.36525 | H99: =H37+H56+H81 -> 131.57438 | I99: =I37+I56+I81 -> 116.75003 | J99: =J37+J56+J81 -> 107.89096 | K99: =K37+K56+K81 -> 98.998676 | L99: =L37+L56+L81 -> 90.073306 | ... AD99: =AD37+AD56+AD81 -> 0
B100: Liabilities: senior debt + CCD / NCD | C100: ₹ Cr | E100: =E29+E74 -> 158.32105 | F100: =F29+F74 -> 155.69 | G100: =G29+G74 -> 148.18015 | H100: =H29+H74 -> 139.96822 | I100: =I29+I74 -> 130.98015 | J100: =J29+J74 -> 121.13408 | K100: =K29+K74 -> 110.3396 | L100: =L29+L74 -> 98.496775 | ... AD100: =AD29+AD74 -> 0
B101: Equity: share capital + distributable reserves | C101: ₹ Cr | E101: =E78+E70 -> 12.771953 | F101: =F78+F70 -> 5.4325003 | G101: =G78+G70 -> -1.8149022 | H101: =H78+H70 -> -8.3938421 | I101: =I78+I70 -> -14.230121 | J101: =J78+J70 -> -13.243123 | K101: =K78+K70 -> -11.340925 | L101: =L78+L70 -> -8.4234687 | ... AD101: =AD78+AD70 -> 4.7961635e-14
B102: Difference (should be zero) | C102: ₹ Cr | D102: =SUMPRODUCT(ABS(E102:AD102)) -> 7.3185902e-13 | E102: =E99-E100-E101 -> 0 | F102: =F99-F100-F101 -> 0 | G102: =G99-G100-G101 -> 0 | H102: =H99-H100-H101 -> -3.1974423e-14 | I102: =I99-I100-I101 -> 0 | J102: =J99-J100-J101 -> 0 | K102: =K99-K100-K101 -> 0 | L102: =L99-L100-L101 -> -4.2632564e-14 | ... AD102: =AD99-AD100-AD101 -> -4.7961635e-14

Sheet HoldCo
B1: HoldCo — Investor funding, transfers to SPV3 & SPV4, and cash back to investors
B2: Promoter cash first, then an equity bridge, then the institutional round priced at P3 COD (CCPS + partner CCD). Columns E:AH = FY2027–FY2056.
B4: Timeline
B5: Financial year | D5: Total | E5: =Inputs!$C$75 -> 2027 | F5: =E5+1 -> 2028 | G5: =F5+1 -> 2029 | H5: =G5+1 -> 2030 | I5: =H5+1 -> 2031 | J5: =I5+1 -> 2032 | K5: =J5+1 -> 2033 | L5: =K5+1 -> 2034 | M5: =L5+1 -> 2035 | ... AH5: =AG5+1 -> 2056
B6: Final operating year flag | E6: =IF(E5=MAX(Inputs!$C$7+Inputs!$C$17,Inputs!$D$7+Inputs!$D$17),1,0) -> 0 | F6: =IF(F5=MAX(Inputs!$C$7+Inputs!$C$17,Inputs!$D$7+Inputs!$D$17),1,0) -> 0 | G6: =IF(G5=MAX(Inputs!$C$7+Inputs!$C$17,Inputs!$D$7+Inputs!$D$17),1,0) -> 0 | H6: =IF(H5=MAX(Inputs!$C$7+Inputs!$C$17,Inputs!$D$7+Inputs!$D$17),1,0) -> 0 | I6: =IF(I5=MAX(Inputs!$C$7+Inputs!$C$17,Inputs!$D$7+Inputs!$D$17),1,0) -> 0 | J6: =IF(J5=MAX(Inputs!$C$7+Inputs!$C$17,Inputs!$D$7+Inputs!$D$17),1,0) -> 0 | K6: =IF(K5=MAX(Inputs!$C$7+Inputs!$C$17,Inputs!$D$7+Inputs!$D$17),1,0) -> 0 | L6: =IF(L5=MAX(Inputs!$C$7+Inputs!$C$17,Inputs!$D$7+Inputs!$D$17),1,0) -> 0 | ... AH6: =IF(AH5=MAX(Inputs!$C$7+Inputs!$C$17,Inputs!$D$7+Inputs!$D$17),1,0) -> 0
B7: 1. HoldCo uses: transfers into the SPVs and pre-close cash
B8: Equity shares into SPV3 | D8: =SUM(E8:AH8) -> 4.2449948 | E8: =IF(E5=Inputs!$C$7,'Sources & Uses'!$C$31,0) -> 0 | F8: =IF(F5=Inputs!$C$7,'Sources & Uses'!$C$31,0) -> 4.2449948 | G8: =IF(G5=Inputs!$C$7,'Sources & Uses'!$C$31,0) -> 0 | H8: =IF(H5=Inputs!$C$7,'Sources & Uses'!$C$31,0) -> 0 | I8: =IF(I5=Inputs!$C$7,'Sources & Uses'!$C$31,0) -> 0 | J8: =IF(J5=Inputs!$C$7,'Sources & Uses'!$C$31,0) -> 0 | K8: =IF(K5=Inputs!$C$7,'Sources & Uses'!$C$31,0) -> 0 | L8: =IF(L5=Inputs!$C$7,'Sources & Uses'!$C$31,0) -> 0 | ... AH8: =IF(AH5=Inputs!$C$7,'Sources & Uses'!$C$31,0) -> 0
B9: CCD / NCD into SPV3 | D9: =SUM(E9:AH9) -> 24.054971 | E9: =SUMIF(SPV3!$E$6:$AD$6,E$5,SPV3!$E$63:$AD$63) -> 0 | F9: =SUMIF(SPV3!$E$6:$AD$6,F$5,SPV3!$E$63:$AD$63) -> 24.054971 | G9: =SUMIF(SPV3!$E$6:$AD$6,G$5,SPV3!$E$63:$AD$63) -> 0 | H9: =SUMIF(SPV3!$E$6:$AD$6,H$5,SPV3!$E$63:$AD$63) -> 0 | I9: =SUMIF(SPV3!$E$6:$AD$6,I$5,SPV3!$E$63:$AD$63) -> 0 | J9: =SUMIF(SPV3!$E$6:$AD$6,J$5,SPV3!$E$63:$AD$63) -> 0 | K9: =SUMIF(SPV3!$E$6:$AD$6,K$5,SPV3!$E$63:$AD$63) -> 0 | L9: =SUMIF(SPV3!$E$6:$AD$6,L$5,SPV3!$E$63:$AD$63) -> 0 | ... AH9: =SUMIF(SPV3!$E$6:$AD$6,AH$5,SPV3!$E$63:$AD$63) -> 0
B10: Equity shares into SPV4 | D10: =SUM(E10:AH10) -> 8.4554734 | E10: =IF(E5=Inputs!$D$7,'Sources & Uses'!$D$31,0) -> 0 | F10: =IF(F5=Inputs!$D$7,'Sources & Uses'!$D$31,0) -> 0 | G10: =IF(G5=Inputs!$D$7,'Sources & Uses'!$D$31,0) -> 8.4554734 | H10: =IF(H5=Inputs!$D$7,'Sources & Uses'!$D$31,0) -> 0 | I10: =IF(I5=Inputs!$D$7,'Sources & Uses'!$D$31,0) -> 0 | J10: =IF(J5=Inputs!$D$7,'Sources & Uses'!$D$31,0) -> 0 | K10: =IF(K5=Inputs!$D$7,'Sources & Uses'!$D$31,0) -> 0 | L10: =IF(L5=Inputs!$D$7,'Sources & Uses'!$D$31,0) -> 0 | ... AH10: =IF(AH5=Inputs!$D$7,'Sources & Uses'!$D$31,0) -> 0
B11: CCD / NCD into SPV4 | D11: =SUM(E11:AH11) -> 47.914349 | E11: =SUMIF(SPV4!$E$6:$AD$6,E$5,SPV4!$E$63:$AD$63) -> 0 | F11: =SUMIF(SPV4!$E$6:$AD$6,F$5,SPV4!$E$63:$AD$63) -> 0 | G11: =SUMIF(SPV4!$E$6:$AD$6,G$5,SPV4!$E$63:$AD$63) -> 47.914349 | H11: =SUMIF(SPV4!$E$6:$AD$6,H$5,SPV4!$E$63:$AD$63) -> 0 | I11: =SUMIF(SPV4!$E$6:$AD$6,I$5,SPV4!$E$63:$AD$63) -> 0 | J11: =SUMIF(SPV4!$E$6:$AD$6,J$5,SPV4!$E$63:$AD$63) -> 0 | K11: =SUMIF(SPV4!$E$6:$AD$6,K$5,SPV4!$E$63:$AD$63) -> 0 | L11: =SUMIF(SPV4!$E$6:$AD$6,L$5,SPV4!$E$63:$AD$63) -> 0 | ... AH11: =SUMIF(SPV4!$E$6:$AD$6,AH$5,SPV4!$E$63:$AD$63) -> 0
B12: PMC and any surety premium paid before close | D12: =SUM(E12:AH12) -> 11.955 | E12: =IF(E5=Inputs!$C$7-1,'Sources & Uses'!$C$37+'Sources & Uses'!$C$40,0)+IF(E5=Inputs!$D$7-1,'Sources & Uses'!$D$37+'Sources & Uses'!$D$40,0) -> 3.985 | F12: =IF(F5=Inputs!$C$7-1,'Sources & Uses'!$C$37+'Sources & Uses'!$C$40,0)+IF(F5=Inputs!$D$7-1,'Sources & Uses'!$D$37+'Sources & Uses'!$D$40,0) -> 7.97 | G12: =IF(G5=Inputs!$C$7-1,'Sources & Uses'!$C$37+'Sources & Uses'!$C$40,0)+IF(G5=Inputs!$D$7-1,'Sources & Uses'!$D$37+'Sources & Uses'!$D$40,0) -> 0 | H12: =IF(H5=Inputs!$C$7-1,'Sources & Uses'!$C$37+'Sources & Uses'!$C$40,0)+IF(H5=Inputs!$D$7-1,'Sources & Uses'!$D$37+'Sources & Uses'!$D$40,0) -> 0 | I12: =IF(I5=Inputs!$C$7-1,'Sources & Uses'!$C$37+'Sources & Uses'!$C$40,0)+IF(I5=Inputs!$D$7-1,'Sources & Uses'!$D$37+'Sources & Uses'!$D$40,0) -> 0 | J12: =IF(J5=Inputs!$C$7-1,'Sources & Uses'!$C$37+'Sources & Uses'!$C$40,0)+IF(J5=Inputs!$D$7-1,'Sources & Uses'!$D$37+'Sources & Uses'!$D$40,0) -> 0 | K12: =IF(K5=Inputs!$C$7-1,'Sources & Uses'!$C$37+'Sources & Uses'!$C$40,0)+IF(K5=Inputs!$D$7-1,'Sources & Uses'!$D$37+'Sources & Uses'!$D$40,0) -> 0 | L12: =IF(L5=Inputs!$C$7-1,'Sources & Uses'!$C$37+'Sources & Uses'!$C$40,0)+IF(L5=Inputs!$D$7-1,'Sources & Uses'!$D$37+'Sources & Uses'!$D$40,0) -> 0 | ... AH12: =IF(AH5=Inputs!$C$7-1,'Sources & Uses'!$C$37+'Sources & Uses'!$C$40,0)+IF(AH5=Inputs!$D$7-1,'Sources & Uses'!$D$37+'Sources & Uses'!$D$40,0) -> 0
B13: PBG cash margin posted | D13: =SUM(E13:AH13) -> 4.21875 | E13: =IF(E5=Inputs!$C$7-1,'Sources & Uses'!$C$39,0)+IF(E5=Inputs!$D$7-1,'Sources & Uses'!$D$39,0) -> 1.40625 | F13: =IF(F5=Inputs!$C$7-1,'Sources & Uses'!$C$39,0)+IF(F5=Inputs!$D$7-1,'Sources & Uses'!$D$39,0) -> 2.8125 | G13: =IF(G5=Inputs!$C$7-1,'Sources & Uses'!$C$39,0)+IF(G5=Inputs!$D$7-1,'Sources & Uses'!$D$39,0) -> 0 | H13: =IF(H5=Inputs!$C$7-1,'Sources & Uses'!$C$39,0)+IF(H5=Inputs!$D$7-1,'Sources & Uses'!$D$39,0) -> 0 | I13: =IF(I5=Inputs!$C$7-1,'Sources & Uses'!$C$39,0)+IF(I5=Inputs!$D$7-1,'Sources & Uses'!$D$39,0) -> 0 | J13: =IF(J5=Inputs!$C$7-1,'Sources & Uses'!$C$39,0)+IF(J5=Inputs!$D$7-1,'Sources & Uses'!$D$39,0) -> 0 | K13: =IF(K5=Inputs!$C$7-1,'Sources & Uses'!$C$39,0)+IF(K5=Inputs!$D$7-1,'Sources & Uses'!$D$39,0) -> 0 | L13: =IF(L5=Inputs!$C$7-1,'Sources & Uses'!$C$39,0)+IF(L5=Inputs!$D$7-1,'Sources & Uses'!$D$39,0) -> 0 | ... AH13: =IF(AH5=Inputs!$C$7-1,'Sources & Uses'!$C$39,0)+IF(AH5=Inputs!$D$7-1,'Sources & Uses'!$D$39,0) -> 0
B14: HoldCo running cost | D14: =SUM(E14:AH14) -> 5.6 | E14: =IF(E5<=MAX(Inputs!$C$7+Inputs!$C$17,Inputs!$D$7+Inputs!$D$17),Inputs!$C$74,0) -> 0.2 | F14: =IF(F5<=MAX(Inputs!$C$7+Inputs!$C$17,Inputs!$D$7+Inputs!$D$17),Inputs!$C$74,0) -> 0.2 | G14: =IF(G5<=MAX(Inputs!$C$7+Inputs!$C$17,Inputs!$D$7+Inputs!$D$17),Inputs!$C$74,0) -> 0.2 | H14: =IF(H5<=MAX(Inputs!$C$7+Inputs!$C$17,Inputs!$D$7+Inputs!$D$17),Inputs!$C$74,0) -> 0.2 | I14: =IF(I5<=MAX(Inputs!$C$7+Inputs!$C$17,Inputs!$D$7+Inputs!$D$17),Inputs!$C$74,0) -> 0.2 | J14: =IF(J5<=MAX(Inputs!$C$7+Inputs!$C$17,Inputs!$D$7+Inputs!$D$17),Inputs!$C$74,0) -> 0.2 | K14: =IF(K5<=MAX(Inputs!$C$7+Inputs!$C$17,Inputs!$D$7+Inputs!$D$17),Inputs!$C$74,0) -> 0.2 | L14: =IF(L5<=MAX(Inputs!$C$7+Inputs!$C$17,Inputs!$D$7+Inputs!$D$17),Inputs!$C$74,0) -> 0.2 | ... AH14: =IF(AH5<=MAX(Inputs!$C$7+Inputs!$C$17,Inputs!$D$7+Inputs!$D$17),Inputs!$C$74,0) -> 0
B15: HoldCo tax paid (previous year's tax) | D15: =SUM(E15:AH15) -> 0.23230653 | E15: 0 | F15: =E59 -> 0 | G15: =F59 -> 0.23230653 | H15: =G59 -> 0 | I15: =H59 -> 0 | J15: =I59 -> 0 | K15: =J59 -> 0 | L15: =K59 -> 0 | M15: =L59 -> 0 | ... AH15: =AG59 -> 0
B16: Total HoldCo uses | D16: =SUM(E16:AH16) -> 106.67584 | E16: =SUM(E8:E15) -> 5.59125 | F16: =SUM(F8:F15) -> 39.282466 | G16: =SUM(G8:G15) -> 56.802129 | H16: =SUM(H8:H15) -> 0.2 | I16: =SUM(I8:I15) -> 0.2 | J16: =SUM(J8:J15) -> 0.2 | K16: =SUM(K8:K15) -> 0.2 | L16: =SUM(L8:L15) -> 0.2 | ... AH16: =SUM(AH8:AH15) -> 0
B17: 2. Receipts from the SPVs
B18: CCD / NCD coupon received | D18: =SUM(E18:AH18) -> 92.390818 | E18: =SUMIF(SPV3!$E$6:$AD$6,E$5,SPV3!$E$65:$AD$65)+SUMIF(SPV4!$E$6:$AD$6,E$5,SPV4!$E$65:$AD$65) -> 0 | F18: =SUMIF(SPV3!$E$6:$AD$6,F$5,SPV3!$E$65:$AD$65)+SUMIF(SPV4!$E$6:$AD$6,F$5,SPV4!$E$65:$AD$65) -> 0 | G18: =SUMIF(SPV3!$E$6:$AD$6,G$5,SPV3!$E$65:$AD$65)+SUMIF(SPV4!$E$6:$AD$6,G$5,SPV4!$E$65:$AD$65) -> 2.1409085 | H18: =SUMIF(SPV3!$E$6:$AD$6,H$5,SPV3!$E$65:$AD$65)+SUMIF(SPV4!$E$6:$AD$6,H$5,SPV4!$E$65:$AD$65) -> 5.0626837 | I18: =SUMIF(SPV3!$E$6:$AD$6,I$5,SPV3!$E$65:$AD$65)+SUMIF(SPV4!$E$6:$AD$6,I$5,SPV4!$E$65:$AD$65) -> 9.8156799 | J18: =SUMIF(SPV3!$E$6:$AD$6,J$5,SPV3!$E$65:$AD$65)+SUMIF(SPV4!$E$6:$AD$6,J$5,SPV4!$E$65:$AD$65) -> 9.8156799 | K18: =SUMIF(SPV3!$E$6:$AD$6,K$5,SPV3!$E$65:$AD$65)+SUMIF(SPV4!$E$6:$AD$6,K$5,SPV4!$E$65:$AD$65) -> 9.8156799 | L18: =SUMIF(SPV3!$E$6:$AD$6,L$5,SPV3!$E$65:$AD$65)+SUMIF(SPV4!$E$6:$AD$6,L$5,SPV4!$E$65:$AD$65) -> 9.8156799 | ... AH18: =SUMIF(SPV3!$E$6:$AD$6,AH$5,SPV3!$E$65:$AD$65)+SUMIF(SPV4!$E$6:$AD$6,AH$5,SPV4!$E$65:$AD$65) -> 0
B19: NCD principal received | D19: =SUM(E19:AH19) -> 0 | E19: =SUMIF(SPV3!$E$6:$AD$6,E$5,SPV3!$E$72:$AD$72)+SUMIF(SPV4!$E$6:$AD$6,E$5,SPV4!$E$72:$AD$72) -> 0 | F19: =SUMIF(SPV3!$E$6:$AD$6,F$5,SPV3!$E$72:$AD$72)+SUMIF(SPV4!$E$6:$AD$6,F$5,SPV4!$E$72:$AD$72) -> 0 | G19: =SUMIF(SPV3!$E$6:$AD$6,G$5,SPV3!$E$72:$AD$72)+SUMIF(SPV4!$E$6:$AD$6,G$5,SPV4!$E$72:$AD$72) -> 0 | H19: =SUMIF(SPV3!$E$6:$AD$6,H$5,SPV3!$E$72:$AD$72)+SUMIF(SPV4!$E$6:$AD$6,H$5,SPV4!$E$72:$AD$72) -> 0 | I19: =SUMIF(SPV3!$E$6:$AD$6,I$5,SPV3!$E$72:$AD$72)+SUMIF(SPV4!$E$6:$AD$6,I$5,SPV4!$E$72:$AD$72) -> 0 | J19: =SUMIF(SPV3!$E$6:$AD$6,J$5,SPV3!$E$72:$AD$72)+SUMIF(SPV4!$E$6:$AD$6,J$5,SPV4!$E$72:$AD$72) -> 0 | K19: =SUMIF(SPV3!$E$6:$AD$6,K$5,SPV3!$E$72:$AD$72)+SUMIF(SPV4!$E$6:$AD$6,K$5,SPV4!$E$72:$AD$72) -> 0 | L19: =SUMIF(SPV3!$E$6:$AD$6,L$5,SPV3!$E$72:$AD$72)+SUMIF(SPV4!$E$6:$AD$6,L$5,SPV4!$E$72:$AD$72) -> 0 | ... AH19: =SUMIF(SPV3!$E$6:$AD$6,AH$5,SPV3!$E$72:$AD$72)+SUMIF(SPV4!$E$6:$AD$6,AH$5,SPV4!$E$72:$AD$72) -> 0
B20: Dividends received | D20: =SUM(E20:AH20) -> 311.67407 | E20: =SUMIF(SPV3!$E$6:$AD$6,E$5,SPV3!$E$69:$AD$69)+SUMIF(SPV4!$E$6:$AD$6,E$5,SPV4!$E$69:$AD$69) -> 0 | F20: =SUMIF(SPV3!$E$6:$AD$6,F$5,SPV3!$E$69:$AD$69)+SUMIF(SPV4!$E$6:$AD$6,F$5,SPV4!$E$69:$AD$69) -> 0 | G20: =SUMIF(SPV3!$E$6:$AD$6,G$5,SPV3!$E$69:$AD$69)+SUMIF(SPV4!$E$6:$AD$6,G$5,SPV4!$E$69:$AD$69) -> 0 | H20: =SUMIF(SPV3!$E$6:$AD$6,H$5,SPV3!$E$69:$AD$69)+SUMIF(SPV4!$E$6:$AD$6,H$5,SPV4!$E$69:$AD$69) -> 0 | I20: =SUMIF(SPV3!$E$6:$AD$6,I$5,SPV3!$E$69:$AD$69)+SUMIF(SPV4!$E$6:$AD$6,I$5,SPV4!$E$69:$AD$69) -> 0 | J20: =SUMIF(SPV3!$E$6:$AD$6,J$5,SPV3!$E$69:$AD$69)+SUMIF(SPV4!$E$6:$AD$6,J$5,SPV4!$E$69:$AD$69) -> 0 | K20: =SUMIF(SPV3!$E$6:$AD$6,K$5,SPV3!$E$69:$AD$69)+SUMIF(SPV4!$E$6:$AD$6,K$5,SPV4!$E$69:$AD$69) -> 0 | L20: =SUMIF(SPV3!$E$6:$AD$6,L$5,SPV3!$E$69:$AD$69)+SUMIF(SPV4!$E$6:$AD$6,L$5,SPV4!$E$69:$AD$69) -> 0 | ... AH20: =SUMIF(SPV3!$E$6:$AD$6,AH$5,SPV3!$E$69:$AD$69)+SUMIF(SPV4!$E$6:$AD$6,AH$5,SPV4!$E$69:$AD$69) -> 0
B21: Capital reductions received | D21: =SUM(E21:AH21) -> 106.4528 | E21: =SUMIF(SPV3!$E$6:$AD$6,E$5,SPV3!$E$77:$AD$77)+SUMIF(SPV4!$E$6:$AD$6,E$5,SPV4!$E$77:$AD$77) -> 0 | F21: =SUMIF(SPV3!$E$6:$AD$6,F$5,SPV3!$E$77:$AD$77)+SUMIF(SPV4!$E$6:$AD$6,F$5,SPV4!$E$77:$AD$77) -> 0 | G21: =SUMIF(SPV3!$E$6:$AD$6,G$5,SPV3!$E$77:$AD$77)+SUMIF(SPV4!$E$6:$AD$6,G$5,SPV4!$E$77:$AD$77) -> 0 | H21: =SUMIF(SPV3!$E$6:$AD$6,H$5,SPV3!$E$77:$AD$77)+SUMIF(SPV4!$E$6:$AD$6,H$5,SPV4!$E$77:$AD$77) -> 0 | I21: =SUMIF(SPV3!$E$6:$AD$6,I$5,SPV3!$E$77:$AD$77)+SUMIF(SPV4!$E$6:$AD$6,I$5,SPV4!$E$77:$AD$77) -> 0 | J21: =SUMIF(SPV3!$E$6:$AD$6,J$5,SPV3!$E$77:$AD$77)+SUMIF(SPV4!$E$6:$AD$6,J$5,SPV4!$E$77:$AD$77) -> 0 | K21: =SUMIF(SPV3!$E$6:$AD$6,K$5,SPV3!$E$77:$AD$77)+SUMIF(SPV4!$E$6:$AD$6,K$5,SPV4!$E$77:$AD$77) -> 0 | L21: =SUMIF(SPV3!$E$6:$AD$6,L$5,SPV3!$E$77:$AD$77)+SUMIF(SPV4!$E$6:$AD$6,L$5,SPV4!$E$77:$AD$77) -> 0 | ... AH21: =SUMIF(SPV3!$E$6:$AD$6,AH$5,SPV3!$E$77:$AD$77)+SUMIF(SPV4!$E$6:$AD$6,AH$5,SPV4!$E$77:$AD$77) -> 0
B22: Final-year capital returns | D22: =SUM(E22:AH22) -> 0 | E22: =SUMIF(SPV3!$E$6:$AD$6,E$5,SPV3!$E$80:$AD$80)+SUMIF(SPV4!$E$6:$AD$6,E$5,SPV4!$E$80:$AD$80) -> 0 | F22: =SUMIF(SPV3!$E$6:$AD$6,F$5,SPV3!$E$80:$AD$80)+SUMIF(SPV4!$E$6:$AD$6,F$5,SPV4!$E$80:$AD$80) -> 0 | G22: =SUMIF(SPV3!$E$6:$AD$6,G$5,SPV3!$E$80:$AD$80)+SUMIF(SPV4!$E$6:$AD$6,G$5,SPV4!$E$80:$AD$80) -> 0 | H22: =SUMIF(SPV3!$E$6:$AD$6,H$5,SPV3!$E$80:$AD$80)+SUMIF(SPV4!$E$6:$AD$6,H$5,SPV4!$E$80:$AD$80) -> 0 | I22: =SUMIF(SPV3!$E$6:$AD$6,I$5,SPV3!$E$80:$AD$80)+SUMIF(SPV4!$E$6:$AD$6,I$5,SPV4!$E$80:$AD$80) -> 0 | J22: =SUMIF(SPV3!$E$6:$AD$6,J$5,SPV3!$E$80:$AD$80)+SUMIF(SPV4!$E$6:$AD$6,J$5,SPV4!$E$80:$AD$80) -> 0 | K22: =SUMIF(SPV3!$E$6:$AD$6,K$5,SPV3!$E$80:$AD$80)+SUMIF(SPV4!$E$6:$AD$6,K$5,SPV4!$E$80:$AD$80) -> 0 | L22: =SUMIF(SPV3!$E$6:$AD$6,L$5,SPV3!$E$80:$AD$80)+SUMIF(SPV4!$E$6:$AD$6,L$5,SPV4!$E$80:$AD$80) -> 0 | ... AH22: =SUMIF(SPV3!$E$6:$AD$6,AH$5,SPV3!$E$80:$AD$80)+SUMIF(SPV4!$E$6:$AD$6,AH$5,SPV4!$E$80:$AD$80) -> 0
B23: PBG cash margin released | D23: =SUM(E23:AH23) -> 4.21875 | E23: =IF(E5=Inputs!$C$7+Inputs!$C$69,'Sources & Uses'!$C$39,0)+IF(E5=Inputs!$D$7+Inputs!$D$69,'Sources & Uses'!$D$39,0) -> 0 | F23: =IF(F5=Inputs!$C$7+Inputs!$C$69,'Sources & Uses'!$C$39,0)+IF(F5=Inputs!$D$7+Inputs!$D$69,'Sources & Uses'!$D$39,0) -> 0 | G23: =IF(G5=Inputs!$C$7+Inputs!$C$69,'Sources & Uses'!$C$39,0)+IF(G5=Inputs!$D$7+Inputs!$D$69,'Sources & Uses'!$D$39,0) -> 1.40625 | H23: =IF(H5=Inputs!$C$7+Inputs!$C$69,'Sources & Uses'!$C$39,0)+IF(H5=Inputs!$D$7+Inputs!$D$69,'Sources & Uses'!$D$39,0) -> 2.8125 | I23: =IF(I5=Inputs!$C$7+Inputs!$C$69,'Sources & Uses'!$C$39,0)+IF(I5=Inputs!$D$7+Inputs!$D$69,'Sources & Uses'!$D$39,0) -> 0 | J23: =IF(J5=Inputs!$C$7+Inputs!$C$69,'Sources & Uses'!$C$39,0)+IF(J5=Inputs!$D$7+Inputs!$D$69,'Sources & Uses'!$D$39,0) -> 0 | K23: =IF(K5=Inputs!$C$7+Inputs!$C$69,'Sources & Uses'!$C$39,0)+IF(K5=Inputs!$D$7+Inputs!$D$69,'Sources & Uses'!$D$39,0) -> 0 | L23: =IF(L5=Inputs!$C$7+Inputs!$C$69,'Sources & Uses'!$C$39,0)+IF(L5=Inputs!$D$7+Inputs!$D$69,'Sources & Uses'!$D$39,0) -> 0 | ... AH23: =IF(AH5=Inputs!$C$7+Inputs!$C$69,'Sources & Uses'!$C$39,0)+IF(AH5=Inputs!$D$7+Inputs!$D$69,'Sources & Uses'!$D$39,0) -> 0
B24: Total receipts | D24: =SUM(E24:AH24) -> 514.73643 | E24: =SUM(E18:E23) -> 0 | F24: =SUM(F18:F23) -> 0 | G24: =SUM(G18:G23) -> 3.5471585 | H24: =SUM(H18:H23) -> 7.8751837 | I24: =SUM(I18:I23) -> 9.8156799 | J24: =SUM(J18:J23) -> 9.8156799 | K24: =SUM(K18:K23) -> 9.8156799 | L24: =SUM(L18:L23) -> 9.8156799 | ... AH24: =SUM(AH18:AH23) -> 0
B25: Funding need (uses above receipts) | D25: =SUM(E25:AH25) -> 98.128686 | E25: =MAX(0,E16-E24) -> 5.59125 | F25: =MAX(0,F16-F24) -> 39.282466 | G25: =MAX(0,G16-G24) -> 53.254971 | H25: =MAX(0,H16-H24) -> 0 | I25: =MAX(0,I16-I24) -> 0 | J25: =MAX(0,J16-J24) -> 0 | K25: =MAX(0,K16-K24) -> 0 | L25: =MAX(0,L16-L24) -> 0 | ... AH25: =MAX(0,AH16-AH24) -> 0
B26: Surplus for investors (receipts above uses) | D26: =SUM(E26:AH26) -> 506.18928 | E26: =MAX(0,E24-E16) -> 0 | F26: =MAX(0,F24-F16) -> 0 | G26: =MAX(0,G24-G16) -> 0 | H26: =MAX(0,H24-H16) -> 7.6751837 | I26: =MAX(0,I24-I16) -> 9.6156799 | J26: =MAX(0,J24-J16) -> 9.6156799 | K26: =MAX(0,K24-K16) -> 9.6156799 | L26: =MAX(0,L24-L16) -> 9.6156799 | ... AH26: =MAX(0,AH24-AH16) -> 0
B27: 3. Who funds the need: promoter → equity bridge → institutional round at COD
B28: Promoter cash available, opening | E28: =Inputs!$C$72+Inputs!$C$73 -> 10 | F28: =E30 -> 4.40875 | G28: =F30 -> 0 | H28: =G30 -> 0 | I28: =H30 -> 0 | J28: =I30 -> 0 | K28: =J30 -> 0 | L28: =K30 -> 0 | M28: =L30 -> 0 | ... AH28: =AG30 -> 0
B29: Promoter cash used | D29: =SUM(E29:AH29) -> 10 | E29: =MIN(E25,E28) -> 5.59125 | F29: =MIN(F25,F28) -> 4.40875 | G29: =MIN(G25,G28) -> 0 | H29: =MIN(H25,H28) -> 0 | I29: =MIN(I25,I28) -> 0 | J29: =MIN(J25,J28) -> 0 | K29: =MIN(K25,K28) -> 0 | L29: =MIN(L25,L28) -> 0 | ... AH29: =MIN(AH25,AH28) -> 0
B30: Promoter cash available, closing | E30: =E28-E29 -> 4.40875 | F30: =F28-F29 -> 0 | G30: =G28-G29 -> 0 | H30: =H28-H29 -> 0 | I30: =I28-I29 -> 0 | J30: =J28-J29 -> 0 | K30: =K28-K29 -> 0 | L30: =L28-L29 -> 0 | ... AH30: =AH28-AH29 -> 0
B31: Need after promoter cash | E31: =E25-E29 -> 0 | F31: =F25-F29 -> 34.873716 | G31: =G25-G29 -> 53.254971 | H31: =H25-H29 -> 0 | I31: =I25-I29 -> 0 | J31: =J25-J29 -> 0 | K31: =K25-K29 -> 0 | L31: =L25-L29 -> 0 | ... AH31: =AH25-AH29 -> 0
B32: HNI pre-COD CCD subscribed | D32: =SUM(E32:AH32) -> 0 | E32: =IF(E5=Inputs!$C$93,MIN(E31,Inputs!$C$92),0) -> 0 | F32: =IF(F5=Inputs!$C$93,MIN(F31,Inputs!$C$92),0) -> 0 | G32: =IF(G5=Inputs!$C$93,MIN(G31,Inputs!$C$92),0) -> 0 | H32: =IF(H5=Inputs!$C$93,MIN(H31,Inputs!$C$92),0) -> 0 | I32: =IF(I5=Inputs!$C$93,MIN(I31,Inputs!$C$92),0) -> 0 | J32: =IF(J5=Inputs!$C$93,MIN(J31,Inputs!$C$92),0) -> 0 | K32: =IF(K5=Inputs!$C$93,MIN(K31,Inputs!$C$92),0) -> 0 | L32: =IF(L5=Inputs!$C$93,MIN(L31,Inputs!$C$92),0) -> 0 | ... AH32: =IF(AH5=Inputs!$C$93,MIN(AH31,Inputs!$C$92),0) -> 0
B33: Need after promoter and HNI money | E33: =E31-E32 -> 0 | F33: =F31-F32 -> 34.873716 | G33: =G31-G32 -> 53.254971 | H33: =H31-H32 -> 0 | I33: =I31-I32 -> 0 | J33: =J31-J32 -> 0 | K33: =K31-K32 -> 0 | L33: =L31-L32 -> 0 | ... AH33: =AH31-AH32 -> 0
B34: Equity bridge, opening | E34: 0 | F34: =E38 -> 0 | G34: =F38 -> 36.871689 | H34: =G38 -> 0 | I34: =H38 -> 0 | J34: =I38 -> 0 | K34: =J38 -> 0 | L34: =K38 -> 0 | M34: =L38 -> 0 | ... AH34: =AG38 -> 0
B35: Equity bridge drawn | D35: =SUM(E35:AH35) -> 34.873716 | E35: =IF(E5<Inputs!$C$77,E33,0) -> 0 | F35: =IF(F5<Inputs!$C$77,F33,0) -> 34.873716 | G35: =IF(G5<Inputs!$C$77,G33,0) -> 0 | H35: =IF(H5<Inputs!$C$77,H33,0) -> 0 | I35: =IF(I5<Inputs!$C$77,I33,0) -> 0 | J35: =IF(J5<Inputs!$C$77,J33,0) -> 0 | K35: =IF(K5<Inputs!$C$77,K33,0) -> 0 | L35: =IF(L5<Inputs!$C$77,L33,0) -> 0 | ... AH35: =IF(AH5<Inputs!$C$77,AH33,0) -> 0
B36: Bridge interest (capitalised) | D36: =SUM(E36:AH36) -> 1.9979733 | E36: =IF(E5<Inputs!$C$77,Inputs!$C$76*(E34+E35*IF(E5=Inputs!$C$7,'Construction Draws'!$C$38,0.5)),0) -> 0 | F36: =IF(F5<Inputs!$C$77,Inputs!$C$76*(F34+F35*IF(F5=Inputs!$C$7,'Construction Draws'!$C$38,0.5)),0) -> 1.9979733 | G36: =IF(G5<Inputs!$C$77,Inputs!$C$76*(G34+G35*IF(G5=Inputs!$C$7,'Construction Draws'!$C$38,0.5)),0) -> 0 | H36: =IF(H5<Inputs!$C$77,Inputs!$C$76*(H34+H35*IF(H5=Inputs!$C$7,'Construction Draws'!$C$38,0.5)),0) -> 0 | I36: =IF(I5<Inputs!$C$77,Inputs!$C$76*(I34+I35*IF(I5=Inputs!$C$7,'Construction Draws'!$C$38,0.5)),0) -> 0 | J36: =IF(J5<Inputs!$C$77,Inputs!$C$76*(J34+J35*IF(J5=Inputs!$C$7,'Construction Draws'!$C$38,0.5)),0) -> 0 | K36: =IF(K5<Inputs!$C$77,Inputs!$C$76*(K34+K35*IF(K5=Inputs!$C$7,'Construction Draws'!$C$38,0.5)),0) -> 0 | L36: =IF(L5<Inputs!$C$77,Inputs!$C$76*(L34+L35*IF(L5=Inputs!$C$7,'Construction Draws'!$C$38,0.5)),0) -> 0 | ... AH36: =IF(AH5<Inputs!$C$77,Inputs!$C$76*(AH34+AH35*IF(AH5=Inputs!$C$7,'Construction Draws'!$C$38,0.5)),0) -> 0
B37: Bridge repaid from the round | D37: =SUM(E37:AH37) -> 36.871689 | E37: =IF(E5=Inputs!$C$77,E34,0) -> 0 | F37: =IF(F5=Inputs!$C$77,F34,0) -> 0 | G37: =IF(G5=Inputs!$C$77,G34,0) -> 36.871689 | H37: =IF(H5=Inputs!$C$77,H34,0) -> 0 | I37: =IF(I5=Inputs!$C$77,I34,0) -> 0 | J37: =IF(J5=Inputs!$C$77,J34,0) -> 0 | K37: =IF(K5=Inputs!$C$77,K34,0) -> 0 | L37: =IF(L5=Inputs!$C$77,L34,0) -> 0 | ... AH37: =IF(AH5=Inputs!$C$77,AH34,0) -> 0
B38: Equity bridge, closing | C38: peak | D38: =MAX(E38:AH38) -> 36.871689 | E38: =E34+E35+E36-E37 -> 0 | F38: =F34+F35+F36-F37 -> 36.871689 | G38: =G34+G35+G36-G37 -> 0 | H38: =H34+H35+H36-H37 -> 0 | I38: =I34+I35+I36-I37 -> 0 | J38: =J34+J35+J36-J37 -> 0 | K38: =K34+K35+K36-K37 -> 0 | L38: =L34+L35+L36-L37 -> 0 | ... AH38: =AH34+AH35+AH36-AH37 -> 0
B39: Institutional capital drawn | D39: =SUM(E39:AH39) -> 90.126659 | E39: =IF(E5>=Inputs!$C$77,E33+E37,0) -> 0 | F39: =IF(F5>=Inputs!$C$77,F33+F37,0) -> 0 | G39: =IF(G5>=Inputs!$C$77,G33+G37,0) -> 90.126659 | H39: =IF(H5>=Inputs!$C$77,H33+H37,0) -> 0 | I39: =IF(I5>=Inputs!$C$77,I33+I37,0) -> 0 | J39: =IF(J5>=Inputs!$C$77,J33+J37,0) -> 0 | K39: =IF(K5>=Inputs!$C$77,K33+K37,0) -> 0 | L39: =IF(L5>=Inputs!$C$77,L33+L37,0) -> 0 | ... AH39: =IF(AH5>=Inputs!$C$77,AH33+AH37,0) -> 0
B40: as CCPS (HoldCo equity) | D40: =SUM(E40:AH40) -> 13.518999 | E40: =E39*(1-Inputs!$C$79) -> 0 | F40: =F39*(1-Inputs!$C$79) -> 0 | G40: =G39*(1-Inputs!$C$79) -> 13.518999 | H40: =H39*(1-Inputs!$C$79) -> 0 | I40: =I39*(1-Inputs!$C$79) -> 0 | J40: =J39*(1-Inputs!$C$79) -> 0 | K40: =K39*(1-Inputs!$C$79) -> 0 | L40: =L39*(1-Inputs!$C$79) -> 0 | ... AH40: =AH39*(1-Inputs!$C$79) -> 0
B41: as partner CCD / NCD | D41: =SUM(E41:AH41) -> 76.607661 | E41: =E39*Inputs!$C$79 -> 0 | F41: =F39*Inputs!$C$79 -> 0 | G41: =G39*Inputs!$C$79 -> 76.607661 | H41: =H39*Inputs!$C$79 -> 0 | I41: =I39*Inputs!$C$79 -> 0 | J41: =J39*Inputs!$C$79 -> 0 | K41: =K39*Inputs!$C$79 -> 0 | L41: =L39*Inputs!$C$79 -> 0 | ... AH41: =AH39*Inputs!$C$79 -> 0
B42: 4. Partner CCD / NCD tranche, HoldCo profit, tax and dividends
B43: Partner CCD / NCD, opening | E43: 0 | F43: =E67 -> 0 | G43: =F67 -> 0 | H43: =G67 -> 85.80058 | I43: =H67 -> 88.421466 | J43: =I67 -> 89.416362 | K43: =J67 -> 90.530645 | L43: =K67 -> 91.778643 | M43: =L67 -> 93.1764 | ... AH43: =AG67 -> 0
B44: Coupon accrued (from the round date) | D44: =SUM(E44:AH44) -> 120.73035 | E44: =(E43+E41)*Inputs!$C$81 -> 0 | F44: =(F43+F41)*Inputs!$C$81 -> 0 | G44: =(G43+G41)*Inputs!$C$81 -> 9.1929193 | H44: =(H43+H41)*Inputs!$C$81 -> 10.29607 | I44: =(I43+I41)*Inputs!$C$81 -> 10.610576 | J44: =(J43+J41)*Inputs!$C$81 -> 10.729963 | K44: =(K43+K41)*Inputs!$C$81 -> 10.863677 | L44: =(L43+L41)*Inputs!$C$81 -> 11.013437 | ... AH44: =(AH43+AH41)*Inputs!$C$81 -> 0
B45: HNI CCD, opening | E45: 0 | F45: =E69 -> 0 | G45: =F69 -> 0 | H45: =G69 -> 0 | I45: =H69 -> 0 | J45: =I69 -> 0 | K45: =J69 -> 0 | L45: =K69 -> 0 | M45: =L69 -> 0 | ... AH45: =AG69 -> 0
B46: HNI coupon accrued (from close or call) | D46: =SUM(E46:AH46) -> 0 | E46: =(E45+E32*Inputs!$C$112/12)*Inputs!$C$94 -> 0 | F46: =(F45+F32*Inputs!$C$112/12)*Inputs!$C$94 -> 0 | G46: =(G45+G32*Inputs!$C$112/12)*Inputs!$C$94 -> 0 | H46: =(H45+H32*Inputs!$C$112/12)*Inputs!$C$94 -> 0 | I46: =(I45+I32*Inputs!$C$112/12)*Inputs!$C$94 -> 0 | J46: =(J45+J32*Inputs!$C$112/12)*Inputs!$C$94 -> 0 | K46: =(K45+K32*Inputs!$C$112/12)*Inputs!$C$94 -> 0 | L46: =(L45+L32*Inputs!$C$112/12)*Inputs!$C$94 -> 0 | ... AH46: =(AH45+AH32*Inputs!$C$112/12)*Inputs!$C$94 -> 0
B47: HoldCo cash held, opening | E47: 0 | F47: =E75 -> 0 | G47: =F75 -> 0 | H47: =G75 -> 0 | I47: =H75 -> 0 | J47: =I75 -> 0 | K47: =J75 -> 0 | L47: =K75 -> 0 | M47: =L75 -> 0 | ... AH47: =AG75 -> 0
B48: Cash available for investors | E48: =E26+E47 -> 0 | F48: =F26+F47 -> 0 | G48: =G26+G47 -> 0 | H48: =H26+H47 -> 7.6751837 | I48: =I26+I47 -> 9.6156799 | J48: =J26+J47 -> 9.6156799 | K48: =K26+K47 -> 9.6156799 | L48: =L26+L47 -> 9.6156799 | ... AH48: =AH26+AH47 -> 0
B49: Partner coupon paid (pro-rata with HNI) | D49: =SUM(E49:AH49) -> 96.679628 | E49: =IF(E44+E46=0,0,MIN(MAX(E48,0),E44+E46)*E44/(E44+E46)) -> 0 | F49: =IF(F44+F46=0,0,MIN(MAX(F48,0),F44+F46)*F44/(F44+F46)) -> 0 | G49: =IF(G44+G46=0,0,MIN(MAX(G48,0),G44+G46)*G44/(G44+G46)) -> 0 | H49: =IF(H44+H46=0,0,MIN(MAX(H48,0),H44+H46)*H44/(H44+H46)) -> 7.6751837 | I49: =IF(I44+I46=0,0,MIN(MAX(I48,0),I44+I46)*I44/(I44+I46)) -> 9.6156799 | J49: =IF(J44+J46=0,0,MIN(MAX(J48,0),J44+J46)*J44/(J44+J46)) -> 9.6156799 | K49: =IF(K44+K46=0,0,MIN(MAX(K48,0),K44+K46)*K44/(K44+K46)) -> 9.6156799 | L49: =IF(L44+L46=0,0,MIN(MAX(L48,0),L44+L46)*L44/(L44+L46)) -> 9.6156799 | ... AH49: =IF(AH44+AH46=0,0,MIN(MAX(AH48,0),AH44+AH46)*AH44/(AH44+AH46)) -> 0
B50: HNI coupon paid (pro-rata with partner) | D50: =SUM(E50:AH50) -> 0 | E50: =IF(E44+E46=0,0,MIN(MAX(E48,0),E44+E46)*E46/(E44+E46)) -> 0 | F50: =IF(F44+F46=0,0,MIN(MAX(F48,0),F44+F46)*F46/(F44+F46)) -> 0 | G50: =IF(G44+G46=0,0,MIN(MAX(G48,0),G44+G46)*G46/(G44+G46)) -> 0 | H50: =IF(H44+H46=0,0,MIN(MAX(H48,0),H44+H46)*H46/(H44+H46)) -> 0 | I50: =IF(I44+I46=0,0,MIN(MAX(I48,0),I44+I46)*I46/(I44+I46)) -> 0 | J50: =IF(J44+J46=0,0,MIN(MAX(J48,0),J44+J46)*J46/(J44+J46)) -> 0 | K50: =IF(K44+K46=0,0,MIN(MAX(K48,0),K44+K46)*K46/(K44+K46)) -> 0 | L50: =IF(L44+L46=0,0,MIN(MAX(L48,0),L44+L46)*L46/(L44+L46)) -> 0 | ... AH50: =IF(AH44+AH46=0,0,MIN(MAX(AH48,0),AH44+AH46)*AH46/(AH44+AH46)) -> 0
B51: Unpaid partner coupon added to the balance | E51: =E44-E49 -> 0 | F51: =F44-F49 -> 0 | G51: =G44-G49 -> 9.1929193 | H51: =H44-H49 -> 2.6208858 | I51: =I44-I49 -> 0.994896 | J51: =J44-J49 -> 1.1142835 | K51: =K44-K49 -> 1.2479975 | L51: =L44-L49 -> 1.3977572 | ... AH51: =AH44-AH49 -> 0
B52: Unpaid HNI coupon added to the balance | D52: =SUM(E52:AH52) -> 0 | E52: =E46-E50 -> 0 | F52: =F46-F50 -> 0 | G52: =G46-G50 -> 0 | H52: =H46-H50 -> 0 | I52: =I46-I50 -> 0 | J52: =J46-J50 -> 0 | K52: =K46-K50 -> 0 | L52: =L46-L50 -> 0 | ... AH52: =AH46-AH50 -> 0
B53: Cash after coupons | E53: =E48-E49-E50 -> 0 | F53: =F48-F49-F50 -> 0 | G53: =G48-G49-G50 -> 0 | H53: =H48-H49-H50 -> 0 | I53: =I48-I49-I50 -> 0 | J53: =J48-J49-J50 -> 0 | K53: =K48-K49-K50 -> 0 | L53: =L48-L49-L50 -> 0 | ... AH53: =AH48-AH49-AH50 -> 0
B54: Partner coupon deductible (s.94B cap if non-resident) | D54: =SUM(E54:AH54) -> 120.73035 | E54: =IF(Inputs!$C$104=1,MIN(E44,Inputs!$C$105*MAX(0,E139-E14)),E44) -> 0 | F54: =IF(Inputs!$C$104=1,MIN(F44,Inputs!$C$105*MAX(0,F139-F14)),F44) -> 0 | G54: =IF(Inputs!$C$104=1,MIN(G44,Inputs!$C$105*MAX(0,G139-G14)),G44) -> 9.1929193 | H54: =IF(Inputs!$C$104=1,MIN(H44,Inputs!$C$105*MAX(0,H139-H14)),H44) -> 10.29607 | I54: =IF(Inputs!$C$104=1,MIN(I44,Inputs!$C$105*MAX(0,I139-I14)),I44) -> 10.610576 | J54: =IF(Inputs!$C$104=1,MIN(J44,Inputs!$C$105*MAX(0,J139-J14)),J44) -> 10.729963 | K54: =IF(Inputs!$C$104=1,MIN(K44,Inputs!$C$105*MAX(0,K139-K14)),K44) -> 10.863677 | L54: =IF(Inputs!$C$104=1,MIN(L44,Inputs!$C$105*MAX(0,L139-L14)),L44) -> 11.013437 | ... AH54: =IF(Inputs!$C$104=1,MIN(AH44,Inputs!$C$105*MAX(0,AH139-AH14)),AH44) -> 0
B55: Taxable income (SPV coupon accrued − costs − deductible coupons) | E55: =E139-E14-E54-E46 -> -0.2 | F55: =F139-F14-F54-F46 -> 1.1230234 | G55: =G139-G14-G54-G46 -> -2.9907683 | H55: =H139-H14-H54-H46 -> -1.1896393 | I55: =I139-I14-I54-I46 -> -0.994896 | J55: =J139-J14-J54-J46 -> -1.1142835 | K55: =K139-K14-K54-K46 -> -1.2479975 | L55: =L139-L14-L54-L46 -> -1.3977572 | ... AH55: =AH139-AH14-AH54-AH46 -> 0
B56: Tax losses brought forward | E56: 0 | F56: =E58 -> 0.2 | G56: =F58 -> 0 | H56: =G58 -> 2.9907683 | I56: =H58 -> 4.1804076 | J56: =I58 -> 5.1753036 | K56: =J58 -> 6.2895871 | L56: =K58 -> 7.5375846 | M56: =L58 -> 8.9353419 | ... AH56: =AG58 -> 25.034542
B57: Losses used | E57: =IF(E55>0,MIN(E56,E55),0) -> 0 | F57: =IF(F55>0,MIN(F56,F55),0) -> 0.2 | G57: =IF(G55>0,MIN(G56,G55),0) -> 0 | H57: =IF(H55>0,MIN(H56,H55),0) -> 0 | I57: =IF(I55>0,MIN(I56,I55),0) -> 0 | J57: =IF(J55>0,MIN(J56,J55),0) -> 0 | K57: =IF(K55>0,MIN(K56,K55),0) -> 0 | L57: =IF(L55>0,MIN(L56,L55),0) -> 0 | ... AH57: =IF(AH55>0,MIN(AH56,AH55),0) -> 0
B58: Tax losses carried forward | E58: =E56-E57+MAX(0,-E55) -> 0.2 | F58: =F56-F57+MAX(0,-F55) -> 0 | G58: =G56-G57+MAX(0,-G55) -> 2.9907683 | H58: =H56-H57+MAX(0,-H55) -> 4.1804076 | I58: =I56-I57+MAX(0,-I55) -> 5.1753036 | J58: =J56-J57+MAX(0,-J55) -> 6.2895871 | K58: =K56-K57+MAX(0,-K55) -> 7.5375846 | L58: =L56-L57+MAX(0,-L55) -> 8.9353419 | ... AH58: =AH56-AH57+MAX(0,-AH55) -> 25.034542
B59: Tax | D59: =SUM(E59:AH59) -> 0.23230653 | E59: =MAX(0,E55-E57)*Inputs!$C$85 -> 0 | F59: =MAX(0,F55-F57)*Inputs!$C$85 -> 0.23230653 | G59: =MAX(0,G55-G57)*Inputs!$C$85 -> 0 | H59: =MAX(0,H55-H57)*Inputs!$C$85 -> 0 | I59: =MAX(0,I55-I57)*Inputs!$C$85 -> 0 | J59: =MAX(0,J55-J57)*Inputs!$C$85 -> 0 | K59: =MAX(0,K55-K57)*Inputs!$C$85 -> 0 | L59: =MAX(0,L55-L57)*Inputs!$C$85 -> 0 | ... AH59: =MAX(0,AH55-AH57)*Inputs!$C$85 -> 0
B60: HoldCo profit after tax | D60: =SUM(E60:AH60) -> 285.33227 | E60: =E139+E20-E14-E36-E44-E46-E59 -> -0.2 | F60: =F139+F20-F14-F36-F44-F46-F59 -> -1.1072564 | G60: =G139+G20-G14-G36-G44-G46-G59 -> -2.9907683 | H60: =H139+H20-H14-H36-H44-H46-H59 -> -1.1896393 | I60: =I139+I20-I14-I36-I44-I46-I59 -> -0.994896 | J60: =J139+J20-J14-J36-J44-J46-J59 -> -1.1142835 | K60: =K139+K20-K14-K36-K44-K46-K59 -> -1.2479975 | L60: =L139+L20-L14-L36-L44-L46-L59 -> -1.3977572 | ... AH60: =AH139+AH20-AH14-AH36-AH44-AH46-AH59 -> 0
B61: Distributable reserves, opening | E61: 0 | F61: =E63 -> -0.2 | G61: =F63 -> -1.3072564 | H61: =G63 -> -4.2980247 | I61: =H63 -> -5.487664 | J61: =I63 -> -6.48256 | K61: =J63 -> -7.5968435 | L61: =K63 -> -8.8448411 | M61: =L63 -> -10.242598 | ... AH61: =AG63 -> 0
B62: Dividend to shareholders (capped at distributable profit) | D62: =SUM(E62:AH62) -> 285.33227 | E62: =MAX(0,MIN(E53-E65,E61+E60)) -> 0 | F62: =MAX(0,MIN(F53-F65,F61+F60)) -> 0 | G62: =MAX(0,MIN(G53-G65,G61+G60)) -> 0 | H62: =MAX(0,MIN(H53-H65,H61+H60)) -> 0 | I62: =MAX(0,MIN(I53-I65,I61+I60)) -> 0 | J62: =MAX(0,MIN(J53-J65,J61+J60)) -> 0 | K62: =MAX(0,MIN(K53-K65,K61+K60)) -> 0 | L62: =MAX(0,MIN(L53-L65,L61+L60)) -> 0 | ... AH62: =MAX(0,MIN(AH53-AH65,AH61+AH60)) -> 0
B63: Distributable reserves, closing | E63: =E61+E60-E62 -> -0.2 | F63: =F61+F60-F62 -> -1.3072564 | G63: =G61+G60-G62 -> -4.2980247 | H63: =H61+H60-H62 -> -5.487664 | I63: =I61+I60-I62 -> -6.48256 | J63: =J61+J60-J62 -> -7.5968435 | K63: =K61+K60-K62 -> -8.8448411 | L63: =L61+L60-L62 -> -10.242598 | ... AH63: =AH61+AH60-AH62 -> 0
B64: Cash left after coupons, NCD principal and dividends | E64: =E53-E65-E62 -> 0 | F64: =F53-F65-F62 -> 0 | G64: =G53-G65-G62 -> 0 | H64: =H53-H65-H62 -> 0 | I64: =I53-I65-I62 -> 0 | J64: =J53-J65-J62 -> 0 | K64: =K53-K65-K62 -> 0 | L64: =L53-L65-L62 -> 0 | ... AH64: =AH53-AH65-AH62 -> 0
B65: Partner NCD principal (ranks ahead of dividends; none for a CCD) | D65: =SUM(E65:AH65) -> 0 | E65: =IF(Inputs!$C$80=2,MIN(MAX(E53,0),E43+E51),0) -> 0 | F65: =IF(Inputs!$C$80=2,MIN(MAX(F53,0),F43+F51),0) -> 0 | G65: =IF(Inputs!$C$80=2,MIN(MAX(G53,0),G43+G51),0) -> 0 | H65: =IF(Inputs!$C$80=2,MIN(MAX(H53,0),H43+H51),0) -> 0 | I65: =IF(Inputs!$C$80=2,MIN(MAX(I53,0),I43+I51),0) -> 0 | J65: =IF(Inputs!$C$80=2,MIN(MAX(J53,0),J43+J51),0) -> 0 | K65: =IF(Inputs!$C$80=2,MIN(MAX(K53,0),K43+K51),0) -> 0 | L65: =IF(Inputs!$C$80=2,MIN(MAX(L53,0),L43+L51),0) -> 0 | ... AH65: =IF(Inputs!$C$80=2,MIN(MAX(AH53,0),AH43+AH51),0) -> 0
B66: Partner CCD converted into HoldCo equity (no cash) | D66: =SUM(E66:AH66) -> 100.65838 | E66: =IF(AND(Inputs!$C$80=1,E5=Inputs!$C$82),E43+E41+E51-E65,0) -> 0 | F66: =IF(AND(Inputs!$C$80=1,F5=Inputs!$C$82),F43+F41+F51-F65,0) -> 0 | G66: =IF(AND(Inputs!$C$80=1,G5=Inputs!$C$82),G43+G41+G51-G65,0) -> 0 | H66: =IF(AND(Inputs!$C$80=1,H5=Inputs!$C$82),H43+H41+H51-H65,0) -> 0 | I66: =IF(AND(Inputs!$C$80=1,I5=Inputs!$C$82),I43+I41+I51-I65,0) -> 0 | J66: =IF(AND(Inputs!$C$80=1,J5=Inputs!$C$82),J43+J41+J51-J65,0) -> 0 | K66: =IF(AND(Inputs!$C$80=1,K5=Inputs!$C$82),K43+K41+K51-K65,0) -> 0 | L66: =IF(AND(Inputs!$C$80=1,L5=Inputs!$C$82),L43+L41+L51-L65,0) -> 0 | ... AH66: =IF(AND(Inputs!$C$80=1,AH5=Inputs!$C$82),AH43+AH41+AH51-AH65,0) -> 0
B67: Partner CCD / NCD, closing | E67: =E43+E41+E51-E65-E66 -> 0 | F67: =F43+F41+F51-F65-F66 -> 0 | G67: =G43+G41+G51-G65-G66 -> 85.80058 | H67: =H43+H41+H51-H65-H66 -> 88.421466 | I67: =I43+I41+I51-I65-I66 -> 89.416362 | J67: =J43+J41+J51-J65-J66 -> 90.530645 | K67: =K43+K41+K51-K65-K66 -> 91.778643 | L67: =L43+L41+L51-L65-L66 -> 93.1764 | ... AH67: =AH43+AH41+AH51-AH65-AH66 -> 0
B68: HNI CCD converted into HoldCo equity (no cash) | D68: =SUM(E68:AH68) -> 0 | E68: =IF(E5=Inputs!$C$97,E45+E32+E52,0) -> 0 | F68: =IF(F5=Inputs!$C$97,F45+F32+F52,0) -> 0 | G68: =IF(G5=Inputs!$C$97,G45+G32+G52,0) -> 0 | H68: =IF(H5=Inputs!$C$97,H45+H32+H52,0) -> 0 | I68: =IF(I5=Inputs!$C$97,I45+I32+I52,0) -> 0 | J68: =IF(J5=Inputs!$C$97,J45+J32+J52,0) -> 0 | K68: =IF(K5=Inputs!$C$97,K45+K32+K52,0) -> 0 | L68: =IF(L5=Inputs!$C$97,L45+L32+L52,0) -> 0 | ... AH68: =IF(AH5=Inputs!$C$97,AH45+AH32+AH52,0) -> 0
B69: HNI CCD, closing | E69: =E45+E32+E52-E68 -> 0 | F69: =F45+F32+F52-F68 -> 0 | G69: =G45+G32+G52-G68 -> 0 | H69: =H45+H32+H52-H68 -> 0 | I69: =I45+I32+I52-I68 -> 0 | J69: =J45+J32+J52-J68 -> 0 | K69: =K45+K32+K52-K68 -> 0 | L69: =L45+L32+L52-L68 -> 0 | ... AH69: =AH45+AH32+AH52-AH68 -> 0
B70: Cash left after the partner tranche | E70: =E64 -> 0 | F70: =F64 -> 0 | G70: =G64 -> 0 | H70: =H64 -> 0 | I70: =I64 -> 0 | J70: =J64 -> 0 | K70: =K64 -> 0 | L70: =L64 -> 0 | ... AH70: =AH64 -> 0
B71: HoldCo equity capital, opening | E71: 0 | F71: =E73 -> 5.59125 | G71: =F73 -> 10 | H71: =G73 -> 23.518999 | I71: =H73 -> 23.518999 | J71: =I73 -> 23.518999 | K71: =J73 -> 23.518999 | L71: =K73 -> 23.518999 | M71: =L73 -> 23.518999 | ... AH71: =AG73 -> 5.8619776e-14
B72: HoldCo capital reduction | D72: =SUM(E72:AH72) -> 124.17738 | E72: =IF(E5>=Inputs!$C$87,MIN(MAX(E70,0),E71+E40+E29+E66+E68),0) -> 0 | F72: =IF(F5>=Inputs!$C$87,MIN(MAX(F70,0),F71+F40+F29+F66+F68),0) -> 0 | G72: =IF(G5>=Inputs!$C$87,MIN(MAX(G70,0),G71+G40+G29+G66+G68),0) -> 0 | H72: =IF(H5>=Inputs!$C$87,MIN(MAX(H70,0),H71+H40+H29+H66+H68),0) -> 0 | I72: =IF(I5>=Inputs!$C$87,MIN(MAX(I70,0),I71+I40+I29+I66+I68),0) -> 0 | J72: =IF(J5>=Inputs!$C$87,MIN(MAX(J70,0),J71+J40+J29+J66+J68),0) -> 0 | K72: =IF(K5>=Inputs!$C$87,MIN(MAX(K70,0),K71+K40+K29+K66+K68),0) -> 0 | L72: =IF(L5>=Inputs!$C$87,MIN(MAX(L70,0),L71+L40+L29+L66+L68),0) -> 0 | ... AH72: =IF(AH5>=Inputs!$C$87,MIN(MAX(AH70,0),AH71+AH40+AH29+AH66+AH68),0) -> 0
B73: HoldCo equity capital, closing | E73: =E71+E40+E29+E66+E68-E72-E74 -> 5.59125 | F73: =F71+F40+F29+F66+F68-F72-F74 -> 10 | G73: =G71+G40+G29+G66+G68-G72-G74 -> 23.518999 | H73: =H71+H40+H29+H66+H68-H72-H74 -> 23.518999 | I73: =I71+I40+I29+I66+I68-I72-I74 -> 23.518999 | J73: =J71+J40+J29+J66+J68-J72-J74 -> 23.518999 | K73: =K71+K40+K29+K66+K68-K72-K74 -> 23.518999 | L73: =L71+L40+L29+L66+L68-L72-L74 -> 23.518999 | ... AH73: =AH71+AH40+AH29+AH66+AH68-AH72-AH74 -> 5.8619776e-14
B74: Final-year capital return to shareholders | D74: =SUM(E74:AH74) -> 0 | E74: =IF(E6=1,E70-E72,0) -> 0 | F74: =IF(F6=1,F70-F72,0) -> 0 | G74: =IF(G6=1,G70-G72,0) -> 0 | H74: =IF(H6=1,H70-H72,0) -> 0 | I74: =IF(I6=1,I70-I72,0) -> 0 | J74: =IF(J6=1,J70-J72,0) -> 0 | K74: =IF(K6=1,K70-K72,0) -> 0 | L74: =IF(L6=1,L70-L72,0) -> 0 | ... AH74: =IF(AH6=1,AH70-AH72,0) -> 0
B75: HoldCo cash held, closing | C75: peak | D75: =MAX(E75:AH75) -> 0 | E75: =E70-E72-E74 -> 0 | F75: =F70-F72-F74 -> 0 | G75: =G70-G72-G74 -> 0 | H75: =H70-H72-H74 -> 0 | I75: =I70-I72-I74 -> 0 | J75: =J70-J72-J74 -> 0 | K75: =K70-K72-K74 -> 0 | L75: =L70-L72-L74 -> 0 | ... AH75: =AH70-AH72-AH74 -> 0
B76: Total shareholder distributions | D76: =SUM(E76:AH76) -> 409.50965 | E76: =E62+E72+E74 -> 0 | F76: =F62+F72+F74 -> 0 | G76: =G62+G72+G74 -> 0 | H76: =H62+H72+H74 -> 0 | I76: =I62+I72+I74 -> 0 | J76: =J62+J72+J74 -> 0 | K76: =K62+K72+K74 -> 0 | L76: =L62+L72+L74 -> 0 | ... AH76: =AH62+AH72+AH74 -> 0
B77: 6. Split between HNIs (pro-rata), partner and promoter (15% preferred return, then 20% promote)
B78: HNI share of distributions (pro-rata) | D78: =SUM(E78:AH78) -> 0 | E78: =E76*$D$124 -> 0 | F78: =F76*$D$124 -> 0 | G78: =G76*$D$124 -> 0 | H78: =H76*$D$124 -> 0 | I78: =I76*$D$124 -> 0 | J78: =J76*$D$124 -> 0 | K78: =K76*$D$124 -> 0 | L78: =L76*$D$124 -> 0 | ... AH78: =AH76*$D$124 -> 0
B79: Partner contributions (CCPS + CCD / NCD) | D79: =SUM(E79:AH79) -> 90.126659 | E79: =E40+E41 -> 0 | F79: =F40+F41 -> 0 | G79: =G40+G41 -> 90.126659 | H79: =H40+H41 -> 0 | I79: =I40+I41 -> 0 | J79: =J40+J41 -> 0 | K79: =K40+K41 -> 0 | L79: =L40+L41 -> 0 | ... AH79: =AH40+AH41 -> 0
B80: Partner coupon and NCD principal received | D80: =SUM(E80:AH80) -> 96.679628 | E80: =E49+E65 -> 0 | F80: =F49+F65 -> 0 | G80: =G49+G65 -> 0 | H80: =H49+H65 -> 7.6751837 | I80: =I49+I65 -> 9.6156799 | J80: =J49+J65 -> 9.6156799 | K80: =K49+K65 -> 9.6156799 | L80: =L49+L65 -> 9.6156799 | ... AH80: =AH49+AH65 -> 0
B81: Partner hurdle balance before distributions | E81: =MAX(0,E79-E80) -> 0 | F81: =MAX(0,E85*(1+Inputs!$C$83)+F79-F80) -> 0 | G81: =MAX(0,F85*(1+Inputs!$C$83)+G79-G80) -> 90.126659 | H81: =MAX(0,G85*(1+Inputs!$C$83)+H79-H80) -> 95.970475 | I81: =MAX(0,H85*(1+Inputs!$C$83)+I79-I80) -> 100.75037 | J81: =MAX(0,I85*(1+Inputs!$C$83)+J79-J80) -> 106.24724 | K81: =MAX(0,J85*(1+Inputs!$C$83)+K79-K80) -> 112.56865 | L81: =MAX(0,K85*(1+Inputs!$C$83)+L79-L80) -> 119.83826 | M81: =MAX(0,L85*(1+Inputs!$C$83)+M79-M80) -> 128.19832 | ... AH81: =MAX(0,AG85*(1+Inputs!$C$83)+AH79-AH80) -> 143.12796
B82: Partner pro-rata share of distributions | E82: =(E76-E78)*$D$125 -> 0 | F82: =(F76-F78)*$D$125 -> 0 | G82: =(G76-G78)*$D$125 -> 0 | H82: =(H76-H78)*$D$125 -> 0 | I82: =(I76-I78)*$D$125 -> 0 | J82: =(J76-J78)*$D$125 -> 0 | K82: =(K76-K78)*$D$125 -> 0 | L82: =(L76-L78)*$D$125 -> 0 | ... AH82: =(AH76-AH78)*$D$125 -> 0
B83: Partner distributions | D83: =SUM(E83:AH83) -> 359.72981 | E83: =IF(E82<=E81,E82,E81+(E76-E78-E81/$D$125)*$D$125*(1-Inputs!$C$84)) -> 0 | F83: =IF(F82<=F81,F82,F81+(F76-F78-F81/$D$125)*$D$125*(1-Inputs!$C$84)) -> 0 | G83: =IF(G82<=G81,G82,G81+(G76-G78-G81/$D$125)*$D$125*(1-Inputs!$C$84)) -> 0 | H83: =IF(H82<=H81,H82,H81+(H76-H78-H81/$D$125)*$D$125*(1-Inputs!$C$84)) -> 0 | I83: =IF(I82<=I81,I82,I81+(I76-I78-I81/$D$125)*$D$125*(1-Inputs!$C$84)) -> 0 | J83: =IF(J82<=J81,J82,J81+(J76-J78-J81/$D$125)*$D$125*(1-Inputs!$C$84)) -> 0 | K83: =IF(K82<=K81,K82,K81+(K76-K78-K81/$D$125)*$D$125*(1-Inputs!$C$84)) -> 0 | L83: =IF(L82<=L81,L82,L81+(L76-L78-L81/$D$125)*$D$125*(1-Inputs!$C$84)) -> 0 | ... AH83: =IF(AH82<=AH81,AH82,AH81+(AH76-AH78-AH81/$D$125)*$D$125*(1-Inputs!$C$84)) -> 0
B84: Promoter distributions (incl. promote) | D84: =SUM(E84:AH84) -> 49.779834 | E84: =E76-E78-E83 -> 0 | F84: =F76-F78-F83 -> 0 | G84: =G76-G78-G83 -> 0 | H84: =H76-H78-H83 -> 0 | I84: =I76-I78-I83 -> 0 | J84: =J76-J78-J83 -> 0 | K84: =K76-K78-K83 -> 0 | L84: =L76-L78-L83 -> 0 | ... AH84: =AH76-AH78-AH83 -> 0
B85: Partner hurdle balance, closing | E85: =MAX(0,E81-E83) -> 0 | F85: =MAX(0,F81-F83) -> 0 | G85: =MAX(0,G81-G83) -> 90.126659 | H85: =MAX(0,H81-H83) -> 95.970475 | I85: =MAX(0,I81-I83) -> 100.75037 | J85: =MAX(0,J81-J83) -> 106.24724 | K85: =MAX(0,K81-K83) -> 112.56865 | L85: =MAX(0,L81-L83) -> 119.83826 | ... AH85: =MAX(0,AH81-AH83) -> 143.12796
B86: 7. Investor cash flows
B87: HNI CCDs sold to the partner at the COD round | D87: =SUM(E87:AH87) -> 0 | E87: =IF(E5=Inputs!$C$77,Inputs!$C$98*$D$132,0) -> 0 | F87: =IF(F5=Inputs!$C$77,Inputs!$C$98*$D$132,0) -> 0 | G87: =IF(G5=Inputs!$C$77,Inputs!$C$98*$D$132,0) -> 0 | H87: =IF(H5=Inputs!$C$77,Inputs!$C$98*$D$132,0) -> 0 | I87: =IF(I5=Inputs!$C$77,Inputs!$C$98*$D$132,0) -> 0 | J87: =IF(J5=Inputs!$C$77,Inputs!$C$98*$D$132,0) -> 0 | K87: =IF(K5=Inputs!$C$77,Inputs!$C$98*$D$132,0) -> 0 | L87: =IF(L5=Inputs!$C$77,Inputs!$C$98*$D$132,0) -> 0 | ... AH87: =IF(AH5=Inputs!$C$77,Inputs!$C$98*$D$132,0) -> 0
B88: Share of the HNI tranche still held by HNIs | E88: =IF(E5>=Inputs!$C$77,1-Inputs!$C$98,1) -> 1 | F88: =IF(F5>=Inputs!$C$77,1-Inputs!$C$98,1) -> 1 | G88: =IF(G5>=Inputs!$C$77,1-Inputs!$C$98,1) -> 1 | H88: =IF(H5>=Inputs!$C$77,1-Inputs!$C$98,1) -> 1 | I88: =IF(I5>=Inputs!$C$77,1-Inputs!$C$98,1) -> 1 | J88: =IF(J5>=Inputs!$C$77,1-Inputs!$C$98,1) -> 1 | K88: =IF(K5>=Inputs!$C$77,1-Inputs!$C$98,1) -> 1 | L88: =IF(L5>=Inputs!$C$77,1-Inputs!$C$98,1) -> 1 | ... AH88: =IF(AH5>=Inputs!$C$77,1-Inputs!$C$98,1) -> 1
B89: Partner net cash flow (incl. any HNI buy-out) | D89: =SUM(E89:AH89) -> 366.28278 | E89: =-E79+E80+E83-E87+(1-E88)*(E50+E78) -> 0 | F89: =-F79+F80+F83-F87+(1-F88)*(F50+F78) -> 0 | G89: =-G79+G80+G83-G87+(1-G88)*(G50+G78) -> -90.126659 | H89: =-H79+H80+H83-H87+(1-H88)*(H50+H78) -> 7.6751837 | I89: =-I79+I80+I83-I87+(1-I88)*(I50+I78) -> 9.6156799 | J89: =-J79+J80+J83-J87+(1-J88)*(J50+J78) -> 9.6156799 | K89: =-K79+K80+K83-K87+(1-K88)*(K50+K78) -> 9.6156799 | L89: =-L79+L80+L83-L87+(1-L88)*(L50+L78) -> 9.6156799 | ... AH89: =-AH79+AH80+AH83-AH87+(1-AH88)*(AH50+AH78) -> 0
B90: Promoter net cash flow | D90: =SUM(E90:AH90) -> 39.779834 | E90: =-E29+E84 -> -5.59125 | F90: =-F29+F84 -> -4.40875 | G90: =-G29+G84 -> 0 | H90: =-H29+H84 -> 0 | I90: =-I29+I84 -> 0 | J90: =-J29+J84 -> 0 | K90: =-K29+K84 -> 0 | L90: =-L29+L84 -> 0 | ... AH90: =-AH29+AH84 -> 0
B91: HNI net cash flow (after any COD sale) | D91: =SUM(E91:AH91) -> 0 | E91: =-E32+E87+E88*(E50+E78) -> 0 | F91: =-F32+F87+F88*(F50+F78) -> 0 | G91: =-G32+G87+G88*(G50+G78) -> 0 | H91: =-H32+H87+H88*(H50+H78) -> 0 | I91: =-I32+I87+I88*(I50+I78) -> 0 | J91: =-J32+J87+J88*(J50+J78) -> 0 | K91: =-K32+K87+K88*(K50+K78) -> 0 | L91: =-L32+L87+L88*(L50+L78) -> 0 | ... AH91: =-AH32+AH87+AH88*(AH50+AH78) -> 0
B92: HNI net cash flow after personal tax | D92: =SUM(E92:AH92) -> 0 | E92: =-E32+E87-MAX(0,E87-Inputs!$C$98*$D$32)*Inputs!$C$101+E88*(E50*(1-Inputs!$C$101)+E62*$D$124*(1-Inputs!$C$101)+(E72+E74)*$D$124) -> 0 | F92: =-F32+F87-MAX(0,F87-Inputs!$C$98*$D$32)*Inputs!$C$101+F88*(F50*(1-Inputs!$C$101)+F62*$D$124*(1-Inputs!$C$101)+(F72+F74)*$D$124) -> 0 | G92: =-G32+G87-MAX(0,G87-Inputs!$C$98*$D$32)*Inputs!$C$101+G88*(G50*(1-Inputs!$C$101)+G62*$D$124*(1-Inputs!$C$101)+(G72+G74)*$D$124) -> 0 | H92: =-H32+H87-MAX(0,H87-Inputs!$C$98*$D$32)*Inputs!$C$101+H88*(H50*(1-Inputs!$C$101)+H62*$D$124*(1-Inputs!$C$101)+(H72+H74)*$D$124) -> 0 | I92: =-I32+I87-MAX(0,I87-Inputs!$C$98*$D$32)*Inputs!$C$101+I88*(I50*(1-Inputs!$C$101)+I62*$D$124*(1-Inputs!$C$101)+(I72+I74)*$D$124) -> 0 | J92: =-J32+J87-MAX(0,J87-Inputs!$C$98*$D$32)*Inputs!$C$101+J88*(J50*(1-Inputs!$C$101)+J62*$D$124*(1-Inputs!$C$101)+(J72+J74)*$D$124) -> 0 | K92: =-K32+K87-MAX(0,K87-Inputs!$C$98*$D$32)*Inputs!$C$101+K88*(K50*(1-Inputs!$C$101)+K62*$D$124*(1-Inputs!$C$101)+(K72+K74)*$D$124) -> 0 | L92: =-L32+L87-MAX(0,L87-Inputs!$C$98*$D$32)*Inputs!$C$101+L88*(L50*(1-Inputs!$C$101)+L62*$D$124*(1-Inputs!$C$101)+(L72+L74)*$D$124) -> 0 | ... AH92: =-AH32+AH87-MAX(0,AH87-Inputs!$C$98*$D$32)*Inputs!$C$101+AH88*(AH50*(1-Inputs!$C$101)+AH62*$D$124*(1-Inputs!$C$101)+(AH72+AH74)*$D$124) -> 0
B93: All HoldCo investors, net cash flow | D93: =SUM(E93:AH93) -> 406.06262 | E93: =E89+E90+E91 -> -5.59125 | F93: =F89+F90+F91 -> -4.40875 | G93: =G89+G90+G91 -> -90.126659 | H93: =H89+H90+H91 -> 7.6751837 | I93: =I89+I90+I91 -> 9.6156799 | J93: =J89+J90+J91 -> 9.6156799 | K93: =K89+K90+K91 -> 9.6156799 | L93: =L89+L90+L91 -> 9.6156799 | ... AH93: =AH89+AH90+AH91 -> 0
B94: 8. Option: partner sells its whole stake after the lock-in (promoter unaffected)
B95: Partner cash after the sale year, incl. any HNI CCDs it bought (what the buyer acquires) | D95: =SUM(E95:AH95) -> 410.27154 | E95: =IF(E5>Inputs!$C$88,E80+E83+(1-E88)*(E50+E78),0) -> 0 | F95: =IF(F5>Inputs!$C$88,F80+F83+(1-F88)*(F50+F78),0) -> 0 | G95: =IF(G5>Inputs!$C$88,G80+G83+(1-G88)*(G50+G78),0) -> 0 | H95: =IF(H5>Inputs!$C$88,H80+H83+(1-H88)*(H50+H78),0) -> 0 | I95: =IF(I5>Inputs!$C$88,I80+I83+(1-I88)*(I50+I78),0) -> 0 | J95: =IF(J5>Inputs!$C$88,J80+J83+(1-J88)*(J50+J78),0) -> 0 | K95: =IF(K5>Inputs!$C$88,K80+K83+(1-K88)*(K50+K78),0) -> 0 | L95: =IF(L5>Inputs!$C$88,L80+L83+(1-L88)*(L50+L78),0) -> 0 | ... AH95: =IF(AH5>Inputs!$C$88,AH80+AH83+(1-AH88)*(AH50+AH78),0) -> 0
B96: Discount factor at the buyer's return | E96: =IF(E5>Inputs!$C$88,1/(1+Inputs!$C$89)^(E5-Inputs!$C$88),0) -> 0 | F96: =IF(F5>Inputs!$C$88,1/(1+Inputs!$C$89)^(F5-Inputs!$C$88),0) -> 0 | G96: =IF(G5>Inputs!$C$88,1/(1+Inputs!$C$89)^(G5-Inputs!$C$88),0) -> 0 | H96: =IF(H5>Inputs!$C$88,1/(1+Inputs!$C$89)^(H5-Inputs!$C$88),0) -> 0 | I96: =IF(I5>Inputs!$C$88,1/(1+Inputs!$C$89)^(I5-Inputs!$C$88),0) -> 0 | J96: =IF(J5>Inputs!$C$88,1/(1+Inputs!$C$89)^(J5-Inputs!$C$88),0) -> 0 | K96: =IF(K5>Inputs!$C$88,1/(1+Inputs!$C$89)^(K5-Inputs!$C$88),0) -> 0 | L96: =IF(L5>Inputs!$C$88,1/(1+Inputs!$C$89)^(L5-Inputs!$C$88),0) -> 0 | ... AH96: =IF(AH5>Inputs!$C$88,1/(1+Inputs!$C$89)^(AH5-Inputs!$C$88),0) -> 0.067963266
B97: Partner net cash flow with the sale | D97: =SUM(E97:AH97) -> 74.571225 | E97: =IF(E5<Inputs!$C$88,E89,IF(E5=Inputs!$C$88,E89+$D$120,0)) -> 0 | F97: =IF(F5<Inputs!$C$88,F89,IF(F5=Inputs!$C$88,F89+$D$120,0)) -> 0 | G97: =IF(G5<Inputs!$C$88,G89,IF(G5=Inputs!$C$88,G89+$D$120,0)) -> -90.126659 | H97: =IF(H5<Inputs!$C$88,H89,IF(H5=Inputs!$C$88,H89+$D$120,0)) -> 7.6751837 | I97: =IF(I5<Inputs!$C$88,I89,IF(I5=Inputs!$C$88,I89+$D$120,0)) -> 9.6156799 | J97: =IF(J5<Inputs!$C$88,J89,IF(J5=Inputs!$C$88,J89+$D$120,0)) -> 9.6156799 | K97: =IF(K5<Inputs!$C$88,K89,IF(K5=Inputs!$C$88,K89+$D$120,0)) -> 9.6156799 | L97: =IF(L5<Inputs!$C$88,L89,IF(L5=Inputs!$C$88,L89+$D$120,0)) -> 128.17566 | ... AH97: =IF(AH5<Inputs!$C$88,AH89,IF(AH5=Inputs!$C$88,AH89+$D$120,0)) -> 0
B98: 9. Option: HNIs sell their pre-COD CCDs or shares
B99: HNI cash after the sale year (what a buyer acquires) | D99: =SUM(E99:AH99) -> 0 | E99: =IF(E5>Inputs!$C$96,E88*(E50+E78),0) -> 0 | F99: =IF(F5>Inputs!$C$96,F88*(F50+F78),0) -> 0 | G99: =IF(G5>Inputs!$C$96,G88*(G50+G78),0) -> 0 | H99: =IF(H5>Inputs!$C$96,H88*(H50+H78),0) -> 0 | I99: =IF(I5>Inputs!$C$96,I88*(I50+I78),0) -> 0 | J99: =IF(J5>Inputs!$C$96,J88*(J50+J78),0) -> 0 | K99: =IF(K5>Inputs!$C$96,K88*(K50+K78),0) -> 0 | L99: =IF(L5>Inputs!$C$96,L88*(L50+L78),0) -> 0 | ... AH99: =IF(AH5>Inputs!$C$96,AH88*(AH50+AH78),0) -> 0
B100: Discount factor at the buyer's return | E100: =IF(E5>Inputs!$C$96,1/(1+Inputs!$C$89)^(E5-Inputs!$C$96),0) -> 0 | F100: =IF(F5>Inputs!$C$96,1/(1+Inputs!$C$89)^(F5-Inputs!$C$96),0) -> 0 | G100: =IF(G5>Inputs!$C$96,1/(1+Inputs!$C$89)^(G5-Inputs!$C$96),0) -> 0 | H100: =IF(H5>Inputs!$C$96,1/(1+Inputs!$C$89)^(H5-Inputs!$C$96),0) -> 0 | I100: =IF(I5>Inputs!$C$96,1/(1+Inputs!$C$89)^(I5-Inputs!$C$96),0) -> 0 | J100: =IF(J5>Inputs!$C$96,1/(1+Inputs!$C$89)^(J5-Inputs!$C$96),0) -> 0 | K100: =IF(K5>Inputs!$C$96,1/(1+Inputs!$C$89)^(K5-Inputs!$C$96),0) -> 0 | L100: =IF(L5>Inputs!$C$96,1/(1+Inputs!$C$89)^(L5-Inputs!$C$96),0) -> 0.88495575 | ... AH100: =IF(AH5>Inputs!$C$96,1/(1+Inputs!$C$89)^(AH5-Inputs!$C$96),0) -> 0.060144484
B101: HNI net cash flow with the sale | D101: =SUM(E101:AH101) -> 0 | E101: =IF(E5<Inputs!$C$96,E91,IF(E5=Inputs!$C$96,E91+$D$128,0)) -> 0 | F101: =IF(F5<Inputs!$C$96,F91,IF(F5=Inputs!$C$96,F91+$D$128,0)) -> 0 | G101: =IF(G5<Inputs!$C$96,G91,IF(G5=Inputs!$C$96,G91+$D$128,0)) -> 0 | H101: =IF(H5<Inputs!$C$96,H91,IF(H5=Inputs!$C$96,H91+$D$128,0)) -> 0 | I101: =IF(I5<Inputs!$C$96,I91,IF(I5=Inputs!$C$96,I91+$D$128,0)) -> 0 | J101: =IF(J5<Inputs!$C$96,J91,IF(J5=Inputs!$C$96,J91+$D$128,0)) -> 0 | K101: =IF(K5<Inputs!$C$96,K91,IF(K5=Inputs!$C$96,K91+$D$128,0)) -> 0 | L101: =IF(L5<Inputs!$C$96,L91,IF(L5=Inputs!$C$96,L91+$D$128,0)) -> 0 | ... AH101: =IF(AH5<Inputs!$C$96,AH91,IF(AH5=Inputs!$C$96,AH91+$D$128,0)) -> 0
...

Sheet Checks
B1: Model checks
B2: Each check returns TRUE when it passes.
B4: Sources = uses, SPV3 | C4: =ABS('Sources & Uses'!C35)<0.0001 -> TRUE
B5: Sources = uses, SPV4 | C5: =ABS('Sources & Uses'!D35)<0.0001 -> TRUE
B6: Senior debt fully repaid, SPV3 | C6: =ABS(SPV3!D29)<0.0001 -> TRUE
B7: Senior debt fully repaid, SPV4 | C7: =ABS(SPV4!D29)<0.0001 -> TRUE
B8: Min P50 DSCR ≥ target, SPV3 | C8: =SPV3!D31>=Inputs!$C$29-0.0001 -> TRUE
B9: Min P50 DSCR ≥ target, SPV4 | C9: =SPV4!D31>=Inputs!$D$29-0.0001 -> TRUE
B10: CCD converted / NCD repaid by end, SPV3 | C10: =ABS(SPV3!D74)<0.0001 -> TRUE
B11: CCD converted / NCD repaid by end, SPV4 | C11: =ABS(SPV4!D74)<0.0001 -> TRUE
B12: No cash left trapped at end, SPV3 | C12: =ABS(SPV3!AD81)<0.0001 -> TRUE
B13: No cash left trapped at end, SPV4 | C13: =ABS(SPV4!AD81)<0.0001 -> TRUE
B14: HoldCo funding identity: promoter + HNI + bridge + round − bridge repaid = need | C14: =ABS(HoldCo!D29+HoldCo!D32+HoldCo!D35+HoldCo!D39-HoldCo!D37-HoldCo!D25)<0.0001 -> TRUE
B15: Equity bridge repaid | C15: =ABS(HoldCo!AH38)<0.0001 -> TRUE
B16: Partner CCD converted / NCD repaid | C16: =ABS(HoldCo!AH67)<0.0001 -> TRUE
B17: HNI CCD converted by end | C17: =ABS(HoldCo!AH69)<0.0001 -> TRUE
B18: HNI CCDs convert within 10 years of issue (deposit rules) | C18: =OR(Inputs!$C$92=0,Inputs!$C$97-Inputs!$C$93<=9) -> TRUE
B19: HNI share sold at COD is between 0% and 100% | C19: =AND(Inputs!$C$98>=0,Inputs!$C$98<=1) -> TRUE
B20: Ownership adds to 100% | C20: =ABS(HoldCo!D107+HoldCo!D108+HoldCo!D124-1)<0.0001 -> TRUE
B21: HoldCo cash never negative | C21: =MIN(HoldCo!E75:AH75)>=-0.0001 -> TRUE
B22: Distributions split fully | C22: =ABS(HoldCo!D83+HoldCo!D84+HoldCo!D78-HoldCo!D76)<0.0001 -> TRUE
B23: Cash conservation: SPV payments to HoldCo = HoldCo receipts | C23: =ABS(SPV3!D83+SPV4!D83-HoldCo!D18-HoldCo!D19-HoldCo!D20-HoldCo!D21-HoldCo!D22)<0.0001 -> TRUE
B24: Balance sheet balances every year, SPV3 | C24: =SPV3!D102<0.001 -> TRUE
B25: Balance sheet balances every year, SPV4 | C25: =SPV4!D102<0.001 -> TRUE
B26: Balance sheet balances every year, HoldCo | C26: =HoldCo!D145<0.001 -> TRUE
B28: All checks pass | C28: =AND(C4:C26) -> TRUE
